Workbook

Sheet Staging >>>

Sheet Requirements
A1: Requirement ID | B1: Requirement | C1: Epic ID | D1: Epic Name | E1: Business Role | F1: Additional Commentary | G1: A6 Reference (JS) | H1: ZR Only
B2: Generate a report of customers, their credit limits and whether they are exceeding the credit limit | C2: Q2C-010-040 | D2: Perform Periodic Credit Review | E2: Credit Officer
B3: Place an active customer on Hold | C3: Q2C-010-040 | D3: Perform Periodic Credit Review | E3: Credit Officer | F3: -Placing a customer on hold requires a reason - If the person putting a customer on hold is not a customer administrator then it will go for approval by a customer administrator - A credit officer may not be a customer administrator
B4: Make a customer inactive | C4: Q2C-010-050 | D4: Perform Customer Closure | E4: Accounts Recievable Officer | F4: No approvals needed for the accounts receivable officer
B5: Where a customer has an on-account balance, the balance needs to be written up to the balance sheet | C5: Q2C-010-050 | D5: Perform Customer Closure | E5: Accounts Recievable Officer | F5: In workday the teminology for a "write up" is the "Customer overpayment" business process
B6: Request a Customer Contract creation in Service Now | C6: Q2C-020-010 | D6: Establish Contract Portfolio Management | E6: Business User
B7: Create a customer contract in Workday | C7: Q2C-020-010 | D7: Establish Contract Portfolio Management | E7: Accounts Recievable Officer | F7: One example of a customer contract that would be created is a Property Rental Contract
B8: Where a contract has a defined billing schedule this should be associated with the created customer contract | C8: Q2C-020-010 | D8: Establish Contract Portfolio Management | E8: Accounts Recievable Officer | F8: A customer contract must already be in the system
B9: Where a contract is flagged as deferred revenue, a revenue recognition schedule needs to be created | C9: Q2C-020-010 | D9: Establish Contract Portfolio Management | E9: Revenue Specialist
B10: Process an amendment to an existing contract | C10: Q2C-020-030 | D10: Manage Contract Compliance and Administration | E10: Accounts Recievable Officer | F10: - the amendment will be a dollar amount - the amendment will affect the already defined billing schedule
B11: Report that a contract has issued all invoices and billed to the maximum amount of the contract | C11: Q2C-020-040 | D11: Close Out Contract | E11: Accounts Recievable Officer
B12: Ability to update and change a customers payment terms | C12: Q2C-040-010 | D12: Manage Billing and Payment Methods | E12: Accounts Recievable Officer
B13: Ability to change an existing billing schedule to have different terms of payment | C13: Q2C-040-010 | D13: Manage Billing and Payment Methods | E13: Accounts Recievable Officer
B14: Ability to request a customer invoice to be created by the Accounts Receivable Team | C14: Q2C-040-020 | D14: Generate, Review & Approve Invoice | E14: Business User | F14: This occurs in Service Now
A15: REQ001 | B15: Ability to process a standalone customer invoice based on a request from the business | C15: Q2C-040-020 | D15: Generate, Review & Approve Invoice | E15: Accounts Recievable Officer | F15: A customer invoice can also have attachments that the user can select are issued to the customer as an attachment, or kept internally
A16: REQ002 | B16: Ability to process a standalone customer invoice based on a request from the business | C16: Q2C-040-020 | D16: Generate, Review & Approve Invoice | E16: Accounts Recievable Officer | F16: - A warning is shown if the customers credit limit is exceeded - A warning is shown if the customer is set to mail delivery - A warning is shown if the invoice date is not todays date
A17: REQ003 | B17: Ability to process a student sponsorship invoice | C17: Q2C-040-020 | D17: Generate, Review & Approve Invoice | E17: Accounts Recievable Officer | F17: -a sponsorship invoice is for capturing income for student placements by a third party and is to be captured as a specific scenario
A18: REQ004 | B18: Ability to automatically generate an invoice based on a customer contracts billing schedule | C18: Q2C-040-020 | D18: Generate, Review & Approve Invoice | E18: Accounts Recievable Officer | F18: - this will be for a rental customer contract; where the rental invoices have a different printed invoice layout
B19: Where an invoice has deferred revenue, a revenue recognition schedule is to be created | C19: Q2C-040-020 | D19: Generate, Review & Approve Invoice | E19: Revenue Specialist
B20: Ability to email an invoice to a customer | C20: Q2C-040-030 | D20: Distribute Invoice | E20: Accounts Recievable Officer | F20: - Emailing the invoice occurs immediately after processing the invoice - the invoice will be created as a PDF and stored in Workday -if the customer is not setup to receive emails then the system will prompt the Accounts Recievable officer to update the customer record - the customer record is to be updated before the system will let you send an email
B21: Abilty to generate an invoice without sending the invoice as an email | C21: Q2C-040-030 | D21: Distribute Invoice | E21: Accounts Recievable Officer | F21: - the invoice can be generated as a PDF manually
B22: Ability to update a purchase order number onto the customer invoice after it was generated | C22: Q2C-040-030 | D22: Distribute Invoice | E22: Accounts Recievable Officer | F22: the invoice print can be regenerated with the updated purchase order number visible
B23: Ability to schedule customer statements being sent monthly | C23: Q2C-040-040 | D23: Generate and Distribute Statements | E23: Accounts Recievable Officer
B24: Ability to generate a customer statement and manually email it to a customer | C24: Q2C-040-040 | D24: Generate and Distribute Statements | E24: Accounts Recievable Officer
B25: Ability to generate a customer statement and have the system email it to the customer | C25: Q2C-040-040 | D25: Generate and Distribute Statements | E25: Accounts Recievable Officer | F25: -if the customer is not setup to receive emails then the system will prompt the Accounts Recievable officer to update the customer record - the customer record is to be updated before the system will let you send an email
B26: Ability to mark invoices as in dispute and provide reason, and free text notes | C26: Q2C-050-010 | D26: Manage Customer Service Inquiry and Orders | E26: Credit Officer | F26: This can be done en masse and also for an individual invoice
B27: Ability to resolve the dispute and mark the invoice as such | C27: Q2C-050-010 | D27: Manage Customer Service Inquiry and Orders | E27: Credit Officer
B28: Ability to resolve the dispute and mark the invoice as such | C28: Q2C-050-020 | D28: Manage Customer Service Inquiry and Orders | E28: Credit Officer
B29: ability to create a credit note | C29: Q2C-050-030 | D29: Process Charge Backs & credit memos | E29: Accounts Recievable Officer | F29: a credit note can be associated with a customer invoice or can be freestanding
B30: Ability to create a rebill invoice and automatically have a credit note generated to offset the original invoice | C30: Q2C-050-030 | D30: Process Charge Backs & credit memos | E30: Accounts Recievable Officer
B31: Where a credit note is against the customer account I need to be able to issue a refund to the customer | C31: Q2C-050-030 | D31: Process Charge Backs & credit memos | E31: Accounts Recievable Officer | F31: - a refund will require the customer to have their bank account added to the customer record so that a refund can be processed '- adding a bank account requires an approval by a different Accounts Receivable officer due to segregation of duties
B32: ability to check if a customer has a bank account already associated with the customer record | C32: Q2C-050-030 | D32: Process Charge Backs & credit memos | E32: Accounts Recievable Officer
B33: Automatically process customer payments based on the bank statement being imported into workday | C33: Q2C-060-010 | D33: Process Payments & Apply Receipts | E33: System | F33: These will be created only if the format of the addenda on the bank statement line follows the Customer Invoice ID (e.g. CIV00001)
B34: Manually create a customer payment based on reviewing the bank statement line | C34: Q2C-060-010 | D34: Process Payments & Apply Receipts | E34: bank Reconciliation Officer | F34: A customer payment may or may not contain remittance advice to be input within Workday
B35: Where a customer payment cannot be associated with an invoice it is to be placed on the customers account | C35: Q2C-060-010 | D35: Process Payments & Apply Receipts | E35: bank Reconciliation Officer
B36: Where a customer payment does not entirely offset the invoice amount, the invoice will be automatically written off | C36: Q2C-060-010 | D36: Process Payments & Apply Receipts | E36: System | F36: - The small amount is written off to a central cost center not the invoices original cost center - This only occurs when the invoice has a remaining balance of less than $1 after a payment is applied
B37: Ability to look at loaded bank statements to identify potential customer payments | C37: Q2C-060-020 | D37: Reconcile Unapplied, Misapplied, and Unidentified Payments | E37: bank Reconciliation Officer
B38: Ability to unapply a payment and apply to a different invoice | C38: Q2C-060-020 | D38: Reconcile Unapplied, Misapplied, and Unidentified Payments | E38: bank Reconciliation Officer
B39: ability to update the remittance advice of an already recorded payment to then apply to an invoice if the payment is on account | C39: Q2C-060-020 | D39: Reconcile Unapplied, Misapplied, and Unidentified Payments | E39: bank Reconciliation Officer | F39: this can be done by either the user manually or automatically through a system process called "Auto Apply Customer Payments"
B40: ability to run a receivables aging report | C40: Q2C-070-020 | D40: Perform Collection Activity | E40: Credit Officer
B41: Ability to mark invoices as in collection and provide reason, and free text notes | C41: Q2C-070-020 | D41: Perform Collection Activity | E41: Credit Officer
B42: Ability to resolve the collection and mark the invoice as such | C42: Q2C-070-020 | D42: Perform Collection Activity | E42: Credit Officer
B43: Ability to generate a dunning letter as a PDF and manually send to the customer | C43: Q2C-070-020 | D43: Perform Collection Activity | E43: Credit Officer | F43: There are 3 levels of dunning based on how long the invoice has been aged
B44: Ability to generate a dunning letter and have the system email it to the customer | C44: Q2C-070-020 | D44: Perform Collection Activity | E44: Credit Officer | F44: -if the customer is not setup to receive emails then the system will prompt the Accounts Recievable officer to update the customer record - the customer record is to be updated before the system will let you send an email - There are 3 levels of dunning based on how long the invoice has been aged
B45: Ability to produce different levels of dunning letter with escalating language when an invoice exceeds the aging buckets | C45: Q2C-070-030 | D45: Perform Escalation & Follow-up | E45: Credit Officer | F45: There are 3 levels of dunning based on how long the invoice has been aged
B46: Ability to put a customer on hold due to poor payment | C46: Q2C-070-030 | D46: Perform Escalation & Follow-up | E46: Credit Officer | F46: when a credit officer marks a customer on hold the accounts recievable officer is required to approve
B47: Ability to request a customer invoice write off in Service Now | C47: Q2C-070-030 | D47: Perform Escalation & Follow-up | E47: Business User
B48: Ability to process a customer write off in Workday | C48: Q2C-070-030 | D48: Perform Escalation & Follow-up | E48: Credit Officer | F48: an approval is required by the accounts receivable team lead
B49: Ability to post a journal to correct the tax impact of the write off in Workday | C49: TAX-020-020 | D49: Prepare Business Activity Statement (BAS) | E49: Financial Accountant | F49: - run report to generate required journal & validate - accountant submits journal, should enter normal approval workflow - should correct impact to bas
B50: Ability to post a journal to recognise the prepayment of scheduled lease payments in Workday | C50: A2R-040-020 | D50: Close Leased Asset Sub ledger and Reconcile with GL | E50: Fixed Asset Accountant | F50: - run report to generate required journal & validate - accountant submits journal, should enter normal approval workflow - should be reflected in GL/reporting - journal reverses in month of recognition
A51: A2R0001 | B51: Ability to produce an asset from a supplier invoice where it meets the capitalisation policy | C51: A2R-020-010 | D51: Create Book/Tax Asset Record & Components | E51: Business Asset Accountant | F51: - this occurs when a supplier invoice is processed before the goods receipt on a purchase order - Only certain spend categories will produce assets, others will be treated as expense - the business asset accountant should receive a confirmation step that the invoice is generating an asset and then the system will automatically - An asset must have a description - an asset must have a location
A52: A2R0002 | B52: Ability to produce an asset from a goods receipt where it meets the capitalisation policy | C52: A2R-020-010 | D52: Create Book/Tax Asset Record & Components | E52: Business Asset Accountant | F52: - this occurs when a goods receipt happens before receiving the supplier invoice on a purchase order - Only certain spend categories will produce assets, others will be treated as expense - the business asset accountant should receive a confirmation step that the invoice is generating an asset and then the system will automatically - Only certain spend categories will produce assets, others will be treated as expense - the business asset accountant should receive a confirmation step that the invoice is generating an asset and then the system will automatically - An asset must have a description - an asset must have a location
A53: A2R0003 | B53: Ability to produce an asset from a supplier invoice where it meets the capitalisation policy but not placed in service immediately | C53: A2R-020-010 | D53: Create Book/Tax Asset Record & Components | E53: Business Asset Accountant | F53: - this occurs when a supplier invoice is processed before the goods receipt on a purchase order - Only certain spend categories will produce assets not placed in service automatically (e.g. Laptops)
A54: A2R0004 | B54: Ability to review an asset that has been capitalised from a capital project | C54: A2R-020-010 | D54: Create Book/Tax Asset Record & Components | E54: Business Asset Accountant | F54: - Requires a capital project to complete its lifecycle and capitalise from WIP
A55: A2R0005 | B55: Ability to manually register an in-kind asset received from a donation | C55: A2R-020-010 | D55: Create Book/Tax Asset Record & Components | E55: Business Asset Accountant | F55: - this will also require a manual journal to be produced in order to update the Asset Cost Ledger Account - the asset should be flagged as an In-Kind asset - an in-kind asset should have a worktag of a gift associated with it
A56: A2R0038 | B56: Ability to post a manual journal for a manually registered asset | C56: A2R-020-010 | D56: Create Book/Tax Asset Record & Components | E56: Fixed Asset Accountant | F56: - must use the journal source of 'manual asset registration' - must use a location for on journal lines relating to assets
A57: A2R0006 | B57: Ability to remove an asset manually registered in error | C57: A2R-020-010 | D57: Create Book/Tax Asset Record & Components | E57: Business Asset Accountant
A58: A2R0007 | B58: Ability to manually register an asset by exception | C58: A2R-020-010 | D58: Create Book/Tax Asset Record & Components | E58: Asset Control Officer | F58: - this will also require a manual journal to be produced in order to update the Asset Cost Ledger Account '- This requires approval by the business asset accountant
A59: A2R0008 | B59: Ability to remove an asset manually registered in error | C59: A2R-020-010 | D59: Create Book/Tax Asset Record & Components | E59: Asset Control Officer | F59: - This requires approval by the business asset accountant - if denied the initiator will get a notification informing as such
A60: A2R0009 | B60: ability to override an asset with a single cost center to have its cost and depreciation shared across multiple cost centers | C60: A2R-020-010 | D60: Create Book/Tax Asset Record & Components | E60: Business Asset Accountant | F60: - This will generate accounting to reclassify the split to each of the cost centers nominated in the split
A61: A2R0010 | B61: Ability to adjust the assets secondary book (Tax) useful life if the default was not accurate | C61: A2R-020-010 | D61: Create Book/Tax Asset Record & Components | E61: Business Asset Accountant | F61: - This will not generate any accounting
A62: A2R0011 | B62: Ability to report on assets created so that an external system can additionally record the assets | C62: A2R-020-010 | D62: Create Book/Tax Asset Record & Components | E62: Business Asset Accountant | F62: - This is the fixed asset register
A63: A2R0012 | B63: Ability to report on assets registered but not in service | C63: A2R-020-040 | D63: Place in Service & Issue Asset | E63: Business Asset Accountant
A64: A2R0013 | B64: Abliity to put a non in service asset in service so it can start depreciating | C64: A2R-020-040 | D64: Place in Service & Issue Asset | E64: Business Asset Accountant
A65: A2R0014 | B65: Ability to assign an asset to a worker as its custodian | C65: A2R-020-040 | D65: Place in Service & Issue Asset | E65: Business Asset Accountant
A66: A2R0015 | B66: Ability to preview the expected depreciation posting for a month or future months | C66: A2R-030-010 | D66: Run & Review Depreciation | E66: Business Asset Accountant
A67: A2R0016 | B67: Ability to run depreciation for the given month | C67: A2R-030-010 | D67: Run & Review Depreciation | E67: Business Asset Accountant
A68: A2R0017 | B68: Ability to report on the Fixed Asset Register | C68: A2R-030-020 | D68: Identify Asset Retirements | E68: Asset Control Officer
A69: A2R0018 | B69: Ability to report on the secondary book for a given fixed asset | C69: A2R-030-030 | D69: Communicate Secondary Book Retirement Implications | E69: Business Asset Accountant
A70: A2R0019 | B70: Ability to dispose $0 carrying value assets | C70: A2R-030-040 | D70: Record Asset Retirement | E70: Business Asset Accountant
A71: A2R0020 | B71: ability to dispose assets with a carrying value and record gains / losses accordingly | C71: A2R-030-040 | D71: Record Asset Retirement | E71: Business Asset Accountant
A72: A2R0021 | B72: ability to reinstate a previously disposed asset | C72: A2R-030-040 | D72: Record Asset Retirement | E72: Business Asset Accountant
A73: A2R0022 | B73: ability to request the sale of an asset | C73: A2R-030-050 | D73: Record Asset Sale/Trade | E73: Asset Owner | F73: - This occurs in Service Now
A74: A2R0023 | B74: ability to record the sale of an asset | C74: A2R-030-050 | D74: Record Asset Sale/Trade | E74: Business Asset Accountant | F74: - This is recording the sale based on the prior request from Service Now in Workday - this will go for approval by the Accounting Manager - This does not generate a customer invoice; and requires the Accounts Recievable Officer to create a customer invoice off the back of the transaction (they will get notified as a To-Do in their inbox)
A75: A2R0024 | B75: ability to generate an invoice based on the recording of a sale of the asset | C75: A2R-030-050 | D75: Record Asset Sale/Trade | E75: Accounts Recievable Officer | F75: - This is notified off the back of recording the sale of the asset prior - Once complete the accounting from both the disposal and the invoice will offset and the P&L will be accurate
A76: A2R0025 | B76: Ability to record a cost adjustment post-acquisition of the asset | C76: A2R-030-060 | D76: Perform Asset Revaluation | E76: Business Asset Accountant | F76: -This can occur from an existing supplier invoice or based on a manual journal - Cost adjustments require approval by the accounting manager - where there is no supplier invoice associated with the adjustment, the accountants are notified with a To-Do to create a journal
A77: A2R0026 | B77: Ability to record the impairment of an asset | C77: A2R-030-070 | D77: Record Asset Impairment | E77: Business Asset Accountant | F77: - The impairment is to be approved by the accounting manager - if its denied in the approval step the initiator is notified
A78: A2R0027 | B78: Ability to request an asset to be transferred | C78: A2R-030-090 | D78: Process Transfers | E78: Asset Owner | F78: - This is to occur in Service Now
A79: A2R0028 | B79: Ability to transfer an asset to a different cost center | C79: A2R-030-090 | D79: Process Transfers | E79: Business Asset Accountant | F79: - no approval required when raised by the business asset accountant
A80: A2R0029 | B80: ability to transfer an asset to a different custodian | C80: A2R-030-090 | D80: Process Transfers | E80: Business Asset Accountant | F80: - no approval required when raised by the business asset accountant
A81: A2R0030 | B81: ability to transfer an asset to a different location | C81: A2R-030-090 | D81: Process Transfers | E81: Business Asset Accountant | F81: - Assets can be tracked at building or room level '- no approval required when raised by the business asset accountant
A82: A2R0031 | B82: Ability to transfer an asset to a different cost center | C82: A2R-030-090 | D82: Process Transfers | E82: Asset Control Officer | F82: -when the asset control officer processes the transaction an approval is required by the business asset accountant
A83: A2R0032 | B83: ability to transfer an asset to a different custodian | C83: A2R-030-090 | D83: Process Transfers | E83: Asset Control Officer | F83: -when the asset control officer processes the transaction an approval is required by the business asset accountant
A84: A2R0033 | B84: ability to transfer an asset to a different location | C84: A2R-030-090 | D84: Process Transfers | E84: Asset Control Officer | F84: -when the asset control officer processes the transaction an approval is required by the business asset accountant
... A88: A2R0037 | B88: ability to reclassify an asset as a different spend category | C88: A2R-030-080 | D88: Record Adjustments to Asset Details | E88: Business Asset Accountant | F88: - when processed there are expected to be updated journals to offset the change in spend category
B89: Ability to execute changes to Assets in bulk | F89: - Edit Asset - Dispose Asset - Transfer Asset
A92: S2P100001 | B92: ability to process a supplier invoice as the accounts payable officer | C92: S2P-100-010 | D92: Receive Invoices & Credit Notes (incl. Self Billing & Prepayments) | E92: Accounts Payable Officer | F92: -these invoices may or may not have an associated approved purchase order (PO). If the invoice has an associated PO, the invoice is not expected to undergo DOA approval. These invoices will however undergo matching. -Matching (for invoices associated with a PO) is driven by the type of line. Goods require 3-way matching and thus there is an expected goods receipt, otherwise the invoice will end up in "match exception". Services do not require a receipt, however will incurr an additional approval (as part of the invoice approval workflow) by the associate requistion requester, to confirm the services have been rendered. -Some invoices will be manually entered by AP. Some will be ingested by email, scanned by OCR, and "reviewed" by AP before submitting. Some will be created by the system automatically as a scheduled installment. -Some invoices will be prepaid, which AP will flag on the relevant invoice line upon creating the invoice. This will then route to the Account as a "To Do" to create the prepaid spend amortisation schedule. The general approval workflow for an invoice (in order) is: 1) Accounts Payable Data Entry Specialist (if the invoice is generated as part of an installment, so that they can attach the invoice number and attachment) 2) Requisition Requester (if the invoice has an associated PO). This is only required when the associated PO line is a service. 3) Matching - this is explained above. 4) Appropriateness approval - if the invoice has no associated PO (Cost Center Manager if the invoice line has no associated project or gift, Project Manager if the invoice line has an associated project, Gift Manager if the invoice line has an associated gift but no project). 5) Technical Category Approval - if the invoice has no associated PO (if the invoice contains a "technical" spend category, subject to additional approval by an expert. 6) DoA - if the invoice has no associated PO. 7) Accountant (if the invoice is prepaid, the accountant will receive a "To Do" as described above). Errors are shown for the following scenarios: -Billable checkbox is not checked for billable project -Intercompany Worktags can only be used on Intercompany Transactions -Invoice Line Item Description is Missing -Location cannot have a Job Posting Usage -Location is required for Asset related invoices -Payment Terms do not Equal the Supplier's Default Payment Terms -This Supplier is Inactive or On Hold -Tax Applicability and Tax Code are required -Taggable Project is Closed -Taggable Project has a Status of 'Acquitted - Residual Funds' and Requires a Project Phase '8 Unspent Funds' -Supplier Remit-To Connection Must be Selected if the supplier has multiple bank accounts -Supplier Invoice is Missing Invoice Number -Supplier Invoice Attachment is Missing -Purpose of Payment receiving code required for India, Kenya, Kuwait, Malaysia, Pakistan, Philippnes and UAE. Warnings are shown for the folowing scenarios: -Confirm if the Invoice Line Should be Checked as 'Prepaid' (for select spend categories) -Contract is past end date -Spend Category Requires Contract (for select spend categories) -Spend Exceeds Contract Amount -Supplier Invoice is Not Linked to a Purchase Order -Taggable Project is in Defect Liability Period Status -The B-PAY Biller ID populated on the supplier invoice does not match the Biller ID stored against the supplier
A93: S2P100002 | B93: ability to request a supplier invoice is created by AP | C93: S2P-100-010 | D93: Receive Invoices & Credit Notes (incl. Self Billing & Prepayments) | E93: Employee | F93: -These will route to an accounts payable data entry specialist to approve/review. if approved, the subsequent invoice will follow and align to the invoice process described in requirement S2P1000001
A94: S2P100003 | B94: ability to create a recurring supplier invoice | C94: S2P-100-010 | D94: Receive Invoices & Credit Notes (incl. Self Billing & Prepayments) | E94: Accounts Payable Officer | F94: -These will route to an accounts payable operations lead to approve. As per the defined schedule, the system will then generate invoices, which will be subject to the same approval workflow and validations as defined in the process described in requirement S2P1000001 | G94: D.219; D.206
A95: S2P100004 | B95: ability to override a match exception | C95: S2P-100-020 | D95: Validate, Approve, & Post Invoices/Credit Notes | E95: Accounts Payable Manager | F95: -when an invoice is stuck in match exception (which occurs when it fails the matching rules configured), by exception it can be overriden, for which an approval by the shared services manager is required.
A96: S2P100005 | B96: ability to create an ad hoc payment | C96: S2P-100-030 | D96: Generate Payments File & Release Payments | E96: Accounts Payable Officer | F96: -These will either be loaded via EIB (Excel), or created manually in the UI. Neither require approval. Those created in the UI require an attachment, whereas those loaded via EIB do not. Other rules these payments need to follow are: -Ad Hoc Payment External Reference is Required -Ad Hoc Payment Memo is required -Please Provide an Email in Additional Field 1 if the Payee is Ad Hoc (for remittance advice) -Please Provide the B-Pay Biller Code in Additional Field 2 (if payment type is BPAY) -Receiving Country Payment Purpose is required for ad hoc payment for select countries -Tax Applicability and Tax Code are required | G96: D.206; D.207; D.208; D.209; D.210; D.211
A97: S2P100006 | B97: ability to create an ad hoc payment template | C97: S2P-100-030 | D97: Generate Payments File & Release Payments | E97: Accounts Payable Officer | F97: -Ad Hoc Bank Transaction Template Cost Centre is Required with Income Statement Accounts -Ad Hoc Bank Transaction Template Requires a Purpose
A98: S2P100007 | B98: ability to create a settlement run | C98: S2P-100-030 | D98: Generate Payments File & Release Payments | E98: Accounts Payable Officer | F98: -Settlement runs, if created manually will route for 2 (different) signatory approvals. If the settlement run is created off the back of a schedule, it will first route to a settlement specialist to review and approve before routing or the same 2 signatory approvals. -If a settlement run contains any 'manual' payments, it will, once approved, route to the initiating settlement specialist as a "To Do" to process in the banking portal. -Once a settlement run is approved, it will generate and issue all associated payment files and remittance advice.
A99: S2P100008 | B99: ability to schedule a settlement run | C99: S2P-100-030 | D99: Generate Payments File & Release Payments | E99: Accounts Payable Officer | F99: -before scheduling a settlement run, a settlement specialist must first create a 'custom settlement run filter', which specifies which transactions to pull into the settlement run (e.g., all invoices due in the next 7 days). The scheduled settlment run will then contain both the filter to be applied, and the schedule upon which to run. | G99: D.139
A100: S2P100009 | B100: ability to create a receipt accrual | C100: S2P-130-030 | D100: Prepare GRNI & Other Month End Accruals | E100: Financial Accountant | F100: -As a pre-requisite, this requires that a PO has been receipted but not yet invoices. | G100: D.125
A101: S2P100010 | C101: S2P-040-030 | D101: On-board Supplier & Setup Supplier Master Data
A102: S2P100011 | C102: S2P-040-040 | D102: Manage Supplier Performance & Risk
A103: S2P100012 | C103: S2P-040-050 | D103: Off-board Supplier
A104: S2P100013 | C104: S2P-050-020 | D104: Develop Sourcing Strategy
A105: S2P100014 | C105: S2P-050-030 | D105: Execute Sourcing Strategy
...

Sheet Output >>>

Sheet Taxonomy and Epics
A1: Area | B1: Numbering | C1: Code | D1: Naming | E1: Level 1 Service | F1: L2 Code | G1: Level 2 Service Name | H1: L3 Code (EPIC) | I1: Level 3 Process Name | J1: >>> | K1: Number of User Stories
A2: Finance | B2: 1.0 | C2: FGV | D2: Finance Governance | E2: =B2&" - "&C2&" - "&D2 -> 1.0 - FGV - Finance Governance | F2: =LEFT(H2,7) -> GOV-010 | G2: Data Management | H2: GOV-010-01 | I2: Maintain Data Model (Chart of Accounts, Dimensions, Hierarchies) | K2: =COUNTIF('User Stories'!H:H,'Taxonomy and Epics'!H2) -> 0
A3: Finance | B3: 1.0 | C3: FGV | D3: Finance Governance | E3: =B3&" - "&C3&" - "&D3 -> 1.0 - FGV - Finance Governance | F3: =LEFT(H3,7) -> GOV-010 | G3: Data Management | H3: GOV-010-02 | I3: Maintain Master Data | K3: =COUNTIF('User Stories'!H:H,'Taxonomy and Epics'!H3) -> 0
A4: Finance | B4: 1.0 | C4: FGV | D4: Finance Governance | E4: =B4&" - "&C4&" - "&D4 -> 1.0 - FGV - Finance Governance | F4: =LEFT(H4,7) -> GOV-010 | G4: Data Management | H4: GOV-010-03 | I4: Maintain Reports | K4: =COUNTIF('User Stories'!H:H,'Taxonomy and Epics'!H4) -> 0
A5: Finance | B5: 1.0 | C5: FGV | D5: Finance Governance | E5: =B5&" - "&C5&" - "&D5 -> 1.0 - FGV - Finance Governance | F5: =LEFT(H5,7) -> GOV-020 | G5: Application and Interface Management & Maintenance | H5: GOV-020-010 | I5: Maintain Application Configuration & Security | K5: =COUNTIF('User Stories'!H:H,'Taxonomy and Epics'!H5) -> 0
A6: Finance | B6: 1.0 | C6: FGV | D6: Finance Governance | E6: =B6&" - "&C6&" - "&D6 -> 1.0 - FGV - Finance Governance | F6: =LEFT(H6,7) -> GOV-020 | G6: Application and Interface Management & Maintenance | H6: GOV-020-020 | I6: Manage Application Releases & Upgrades | K6: =COUNTIF('User Stories'!H:H,'Taxonomy and Epics'!H6) -> 0
A7: Finance | B7: 1.0 | C7: FGV | D7: Finance Governance | E7: =B7&" - "&C7&" - "&D7 -> 1.0 - FGV - Finance Governance | F7: =LEFT(H7,7) -> GOV-020 | G7: Application and Interface Management & Maintenance | H7: GOV-020-030 | I7: Manage Interfaces | K7: =COUNTIF('User Stories'!H:H,'Taxonomy and Epics'!H7) -> 0
A8: Finance | B8: 1.0 | C8: FGV | D8: Finance Governance | E8: =B8&" - "&C8&" - "&D8 -> 1.0 - FGV - Finance Governance | F8: =LEFT(H8,7) -> GOV-030 | G8: Automation | H8: GOV-030-010 | I8: Maintain Process Automation | K8: =COUNTIF('User Stories'!H:H,'Taxonomy and Epics'!H8) -> 0
A9: Finance | B9: 1.0 | C9: FGV | D9: Finance Governance | E9: =B9&" - "&C9&" - "&D9 -> 1.0 - FGV - Finance Governance | F9: =LEFT(H9,7) -> GOV-04- | G9: Admin and Records Management | H9: GOV-04-010 | I9: Manage Planning/ Forecast Calendar | K9: =COUNTIF('User Stories'!H:H,'Taxonomy and Epics'!H9) -> 0
A10: Finance | B10: 1.0 | C10: FGV | D10: Finance Governance | E10: =B10&" - "&C10&" - "&D10 -> 1.0 - FGV - Finance Governance | F10: =LEFT(H10,7) -> GOV-040 | G10: Admin and Records Management | H10: GOV-040-020 | I10: Manage Close Process & Calendar | K10: =COUNTIF('User Stories'!H:H,'Taxonomy and Epics'!H10) -> 0
A11: Finance | B11: 1.0 | C11: FGV | D11: Finance Governance | E11: =B11&" - "&C11&" - "&D11 -> 1.0 - FGV - Finance Governance | F11: =LEFT(H11,7) -> GOV-040 | G11: Admin and Records Management | H11: GOV-040-030 | I11: Archive & Maintain Records | K11: =COUNTIF('User Stories'!H:H,'Taxonomy and Epics'!H11) -> 0
A12: Finance | B12: 1.0 | C12: FGV | D12: Finance Governance | E12: =B12&" - "&C12&" - "&D12 -> 1.0 - FGV - Finance Governance | F12: =LEFT(H12,7) -> GOV-050 | G12: Compliance and Controls | H12: GOV-050-010 | I12: Maintain Policies, Procedures, & Templates | K12: =COUNTIF('User Stories'!H:H,'Taxonomy and Epics'!H12) -> 0
A13: Finance | B13: 1.0 | C13: FGV | D13: Finance Governance | E13: =B13&" - "&C13&" - "&D13 -> 1.0 - FGV - Finance Governance | F13: =LEFT(H13,7) -> GOV-050 | G13: Compliance and Controls | H13: GOV-050-020 | I13: Maintain Internal Controls | K13: =COUNTIF('User Stories'!H:H,'Taxonomy and Epics'!H13) -> 0
... A16: Finance | B16: 1.0 | C16: FGV | D16: Finance Governance | E16: =B16&" - "&C16&" - "&D16 -> 1.0 - FGV - Finance Governance | F16: =LEFT(H16,7) -> GOV-060 | G16: Process Efficiency | H16: GOV-060-010 | I16: Manage Process Efficiency & Effectiveness | K16: =COUNTIF('User Stories'!H:H,'Taxonomy and Epics'!H16) -> 0
A17: Finance | B17: 1.0 | C17: FGV | D17: Finance Governance | E17: =B17&" - "&C17&" - "&D17 -> 1.0 - FGV - Finance Governance | F17: =LEFT(H17,7) -> GOV-060 | G17: Process Efficiency | H17: GOV-060-020 | I17: Enhance Business Partner/ Employee Experience
A18: Finance | B18: 1.0 | C18: FGV | D18: Finance Governance | E18: =B18&" - "&C18&" - "&D18 -> 1.0 - FGV - Finance Governance | F18: =LEFT(H18,7) -> GOV-060 | G18: Process Efficiency | H18: GOV-060-030 | I18: Retain & Update Predictive Models
A19: Finance | B19: 10.0 | C19: TRE | D19: Treasury | E19: =B19&" - "&C19&" - "&D19 -> 10.0 - TRE - Treasury | F19: =LEFT(H19,7) -> TRE-010 | G19: Treasury Administration | H19: TRE-010-010 | I19: Manage Bank Accounts | K19: =COUNTIF('User Stories'!H:H,'Taxonomy and Epics'!H19) -> 1
A20: Finance | B20: 10.0 | C20: TRE | D20: Treasury | E20: =B20&" - "&C20&" - "&D20 -> 10.0 - TRE - Treasury | F20: =LEFT(H20,7) -> TRE-010 | G20: Treasury Administration | H20: TRE-010-020 | I20: Treasury and Liquidity Reporting | K20: =COUNTIF('User Stories'!H:H,'Taxonomy and Epics'!H20) -> 0
A21: Finance | B21: 10.0 | C21: TRE | D21: Treasury | E21: =B21&" - "&C21&" - "&D21 -> 10.0 - TRE - Treasury | F21: =LEFT(H21,7) -> TRE-010 | G21: Treasury Administration | H21: TRE-010-030 | I21: Manage and Report Debt Covenants | K21: =COUNTIF('User Stories'!H:H,'Taxonomy and Epics'!H21) -> 0
A22: Finance | B22: 10.0 | C22: TRE | D22: Treasury | E22: =B22&" - "&C22&" - "&D22 -> 10.0 - TRE - Treasury | F22: =LEFT(H22,7) -> TRE-010 | G22: Treasury Administration | H22: TRE-010-040 | I22: Manage Banking Relationships | K22: =COUNTIF('User Stories'!H:H,'Taxonomy and Epics'!H22) -> 0
A23: Finance | B23: 10.0 | C23: TRE | D23: Treasury | E23: =B23&" - "&C23&" - "&D23 -> 10.0 - TRE - Treasury | F23: =LEFT(H23,7) -> TRE-020 | G23: Cash and Liquidity Management | H23: TRE-020-010 | I23: Manage Bank Account Cash Balances | K23: =COUNTIF('User Stories'!H:H,'Taxonomy and Epics'!H23) -> 7
A24: Finance | B24: 10.0 | C24: TRE | D24: Treasury | E24: =B24&" - "&C24&" - "&D24 -> 10.0 - TRE - Treasury | F24: =LEFT(H24,7) -> TRE-020 | G24: Cash and Liquidity Management | H24: TRE-020-020 | I24: Cash Management Reporting and Analytics | K24: =COUNTIF('User Stories'!H:H,'Taxonomy and Epics'!H24) -> 0
A25: Finance | B25: 10.0 | C25: TRE | D25: Treasury | E25: =B25&" - "&C25&" - "&D25 -> 10.0 - TRE - Treasury | F25: =LEFT(H25,7) -> TRE-030 | G25: Bank Reconciliations | H25: TRE-030-010 | I25: Perform Bank Reconciliation | K25: =COUNTIF('User Stories'!H:H,'Taxonomy and Epics'!H25) -> 13
A26: Finance | B26: 10.0 | C26: TRE | D26: Treasury | E26: =B26&" - "&C26&" - "&D26 -> 10.0 - TRE - Treasury | F26: =LEFT(H26,7) -> TRE-030 | G26: Bank Reconciliations | H26: TRE-030-020 | I26: Process Book-to-Bank Reconciliation | K26: =COUNTIF('User Stories'!H:H,'Taxonomy and Epics'!H26) -> 0
A27: Finance | B27: 10.0 | C27: TRE | D27: Treasury | E27: =B27&" - "&C27&" - "&D27 -> 10.0 - TRE - Treasury | F27: =LEFT(H27,7) -> TRE-040 | G27: Settlement & Payment | H27: TRE-040-010 | I27: Process Payment Return Statements | K27: =COUNTIF('User Stories'!H:H,'Taxonomy and Epics'!H27) -> 4
A28: Finance | B28: 10.0 | C28: TRE | D28: Treasury | E28: =B28&" - "&C28&" - "&D28 -> 10.0 - TRE - Treasury | F28: =LEFT(H28,7) -> TRE-040 | G28: Settlement & Payment | H28: TRE-040-020 | I28: Process Stopped Payments | K28: =COUNTIF('User Stories'!H:H,'Taxonomy and Epics'!H28) -> 1
A29: Finance | B29: 10.0 | C29: TRE | D29: Treasury | E29: =B29&" - "&C29&" - "&D29 -> 10.0 - TRE - Treasury | F29: =LEFT(H29,7) -> TRE-040 | G29: Settlement & Payment | H29: TRE-040-040 | I29: Manage Intercompany Settlements | K29: =COUNTIF('User Stories'!H:H,'Taxonomy and Epics'!H29) -> 0
A30: Finance | B30: 10.0 | C30: TRE | D30: Treasury | E30: =B30&" - "&C30&" - "&D30 -> 10.0 - TRE - Treasury | F30: =LEFT(H30,7) -> TRE-050 | G30: Debt, Investment & Equity Management | H30: TRE-050-010 | I30: Manage Treasury, Debt and Capital Markets | K30: =COUNTIF('User Stories'!H:H,'Taxonomy and Epics'!H30) -> 0
... A79: Finance | B79: 2.0 | C79: PLN | D79: Plan to Perform | E79: =B79&" - "&C79&" - "&D79 -> 2.0 - PLN - Plan to Perform | F79: =LEFT(H79,7) -> P2P-080 | G79: Agree Action Plans & Update Forecast | H79: P2P-080-040 | I79: Update Business & External Drivers | K79: =COUNTIF('User Stories'!H:H,'Taxonomy and Epics'!H79) -> 0
A80: Finance | B80: 2.0 | C80: PLN | D80: Plan to Perform | E80: =B80&" - "&C80&" - "&D80 -> 2.0 - PLN - Plan to Perform | F80: =LEFT(H80,7) -> P2P-080 | G80: Agree Action Plans & Update Forecast | H80: P2P-080-050 | I80: Update Forecast & Performance Targets
A81: Finance | B81: 2.0 | C81: PLN | D81: Plan to Perform | E81: =B81&" - "&C81&" - "&D81 -> 2.0 - PLN - Plan to Perform | F81: =LEFT(H81,7) -> P2P-080 | G81: Agree Action Plans & Update Forecast | H81: P2P-080-060 | I81: Input to External Guidance
A82: Finance | B82: 3.0 | C82: Q2C | D82: Quote to Cash | E82: =B82&" - "&C82&" - "&D82 -> 3.0 - Q2C - Quote to Cash | F82: Q2C-010 | G82: Setup Customer & Credit | H82: #N/A | I82: Establish Credit Methodology and Credit Limits | K82: =COUNTIF('User Stories'!H:H,'Taxonomy and Epics'!H82) -> 0
A83: Finance | B83: 3.0 | C83: Q2C | D83: Quote to Cash | E83: =B83&" - "&C83&" - "&D83 -> 3.0 - Q2C - Quote to Cash | F83: Q2C-010 | G83: Setup Customer & Credit | H83: Q2C-010-020 | I83: Process New Customer Credit Application | K83: =COUNTIF('User Stories'!H:H,'Taxonomy and Epics'!H83) -> 3
A84: Finance | B84: 3.0 | C84: Q2C | D84: Quote to Cash | E84: =B84&" - "&C84&" - "&D84 -> 3.0 - Q2C - Quote to Cash | F84: Q2C-010 | G84: Setup Customer & Credit | H84: Q2C-010-030 | I84: Setup Customer Financial Master Data | K84: =COUNTIF('User Stories'!H:H,'Taxonomy and Epics'!H84) -> 5
A85: Finance | B85: 3.0 | C85: Q2C | D85: Quote to Cash | E85: =B85&" - "&C85&" - "&D85 -> 3.0 - Q2C - Quote to Cash | F85: Q2C-010 | G85: Setup Customer & Credit | H85: Q2C-010-040 | I85: Perform Periodic Credit Review | K85: =COUNTIF('User Stories'!H:H,'Taxonomy and Epics'!H85) -> 2
A86: Finance | B86: 3.0 | C86: Q2C | D86: Quote to Cash | E86: =B86&" - "&C86&" - "&D86 -> 3.0 - Q2C - Quote to Cash | F86: Q2C-010 | G86: Setup Customer & Credit | H86: Q2C-010-050 | I86: Perform Customer Closure | K86: =COUNTIF('User Stories'!H:H,'Taxonomy and Epics'!H86) -> 2
A87: Finance | B87: 3.0 | C87: Q2C | D87: Quote to Cash | E87: =B87&" - "&C87&" - "&D87 -> 3.0 - Q2C - Quote to Cash | F87: Q2C-020 | G87: Contract Lifecycle Management (Customer) | H87: Q2C-020-010 | I87: Establish Contract Portfolio Management | K87: =COUNTIF('User Stories'!H:H,'Taxonomy and Epics'!H87) -> 4
A88: Finance | B88: 3.0 | C88: Q2C | D88: Quote to Cash | E88: =B88&" - "&C88&" - "&D88 -> 3.0 - Q2C - Quote to Cash | F88: Q2C-020 | G88: Contract Lifecycle Management (Customer) | H88: #N/A | I88: Manage T&C’s and Contract Templates | K88: =COUNTIF('User Stories'!H:H,'Taxonomy and Epics'!H88) -> 0
A89: Finance | B89: 3.0 | C89: Q2C | D89: Quote to Cash | E89: =B89&" - "&C89&" - "&D89 -> 3.0 - Q2C - Quote to Cash | F89: Q2C-020 | G89: Contract Lifecycle Management (Customer) | H89: Q2C-020-030 | I89: Manage Contract Compliance and Administration | K89: =COUNTIF('User Stories'!H:H,'Taxonomy and Epics'!H89) -> 1
A90: Finance | B90: 3.0 | C90: Q2C | D90: Quote to Cash | E90: =B90&" - "&C90&" - "&D90 -> 3.0 - Q2C - Quote to Cash | F90: Q2C-020 | G90: Contract Lifecycle Management (Customer) | H90: Q2C-020-040 | I90: Close Out Contract | K90: =COUNTIF('User Stories'!H:H,'Taxonomy and Epics'!H90) -> 1
A91: Finance | B91: 3.0 | C91: Q2C | D91: Quote to Cash | E91: =B91&" - "&C91&" - "&D91 -> 3.0 - Q2C - Quote to Cash | F91: Q2C-020 | G91: Quote, Order & Fulfilment Management | H91: #N/A | I91: Develop Quote | K91: =COUNTIF('User Stories'!H:H,'Taxonomy and Epics'!H91) -> 0
A92: Finance | B92: 3.0 | C92: Q2C | D92: Quote to Cash | E92: =B92&" - "&C92&" - "&D92 -> 3.0 - Q2C - Quote to Cash | F92: Q2C-020 | G92: Quote, Order & Fulfilment Management | H92: #N/A | I92: Review, Approve and Distribute Quote | K92: =COUNTIF('User Stories'!H:H,'Taxonomy and Epics'!H92) -> 0
A93: Finance | B93: 3.0 | C93: Q2C | D93: Quote to Cash | E93: =B93&" - "&C93&" - "&D93 -> 3.0 - Q2C - Quote to Cash | F93: Q2C-020 | G93: Quote, Order & Fulfilment Management | H93: #N/A | I93: Receive, Enter and Validate Order | K93: =COUNTIF('User Stories'!H:H,'Taxonomy and Epics'!H93) -> 0
A94: Finance | B94: 3.0 | C94: Q2C | D94: Quote to Cash | E94: =B94&" - "&C94&" - "&D94 -> 3.0 - Q2C - Quote to Cash | F94: Q2C-040 | G94: Billing Management | H94: Q2C-040-010 | I94: Manage Billing and Payment Methods | K94: =COUNTIF('User Stories'!H:H,'Taxonomy and Epics'!H94) -> 2
A95: Finance | B95: 3.0 | C95: Q2C | D95: Quote to Cash | E95: =B95&" - "&C95&" - "&D95 -> 3.0 - Q2C - Quote to Cash | F95: Q2C-040 | G95: Billing Management | H95: Q2C-040-020 | I95: Generate, Review & Approve Invoice | K95: =COUNTIF('User Stories'!H:H,'Taxonomy and Epics'!H95) -> 8
A96: Finance | B96: 3.0 | C96: Q2C | D96: Quote to Cash | E96: =B96&" - "&C96&" - "&D96 -> 3.0 - Q2C - Quote to Cash | F96: Q2C-040 | G96: Billing Management | H96: Q2C-040-030 | I96: Distribute Invoice | K96: =COUNTIF('User Stories'!H:H,'Taxonomy and Epics'!H96) -> 3
A97: Finance | B97: 3.0 | C97: Q2C | D97: Quote to Cash | E97: =B97&" - "&C97&" - "&D97 -> 3.0 - Q2C - Quote to Cash | F97: Q2C-040 | G97: Billing Management | H97: Q2C-040-040 | I97: Generate and Distribute Statements | K97: =COUNTIF('User Stories'!H:H,'Taxonomy and Epics'!H97) -> 2
A98: Finance | B98: 3.0 | C98: Q2C | D98: Quote to Cash | E98: =B98&" - "&C98&" - "&D98 -> 3.0 - Q2C - Quote to Cash | F98: Q2C-050 | G98: Customer Inquiry and Dispute | H98: Q2C-050-010 | I98: Manage Customer Service Inquiry and Orders | K98: =COUNTIF('User Stories'!H:H,'Taxonomy and Epics'!H98) -> 2
A99: Finance | B99: 3.0 | C99: Q2C | D99: Quote to Cash | E99: =B99&" - "&C99&" - "&D99 -> 3.0 - Q2C - Quote to Cash | F99: Q2C-050 | G99: Customer Inquiry and Dispute | H99: Q2C-050-020 | I99: Manage Customer Complaints, Disputes and Refunds | K99: =COUNTIF('User Stories'!H:H,'Taxonomy and Epics'!H99) -> 0
A100: Finance | B100: 3.0 | C100: Q2C | D100: Quote to Cash | E100: =B100&" - "&C100&" - "&D100 -> 3.0 - Q2C - Quote to Cash | F100: Q2C-050 | G100: Customer Inquiry and Dispute | H100: Q2C-050-030 | I100: Process Charge Backs & credit memos | K100: =COUNTIF('User Stories'!H:H,'Taxonomy and Epics'!H100) -> 6
A101: Finance | B101: 3.0 | C101: Q2C | D101: Quote to Cash | E101: =B101&" - "&C101&" - "&D101 -> 3.0 - Q2C - Quote to Cash | F101: Q2C-060 | G101: Cash Applications | H101: Q2C-060-010 | I101: Process Payments & Apply Receipts | K101: =COUNTIF('User Stories'!H:H,'Taxonomy and Epics'!H101) -> 5
A102: Finance | B102: 3.0 | C102: Q2C | D102: Quote to Cash | E102: =B102&" - "&C102&" - "&D102 -> 3.0 - Q2C - Quote to Cash | F102: Q2C-060 | G102: Cash Applications | H102: Q2C-060-020 | I102: Reconcile Unapplied, Misapplied, and Unidentified Payments | K102: =COUNTIF('User Stories'!H:H,'Taxonomy and Epics'!H102) -> 2
A103: Finance | B103: 3.0 | C103: Q2C | D103: Quote to Cash | E103: =B103&" - "&C103&" - "&D103 -> 3.0 - Q2C - Quote to Cash | F103: Q2C-070 | G103: Collections Management | H103: #N/A | I103: Define Collections Strategy | K103: =COUNTIF('User Stories'!H:H,'Taxonomy and Epics'!H103) -> 0
A104: Finance | B104: 3.0 | C104: Q2C | D104: Quote to Cash | E104: =B104&" - "&C104&" - "&D104 -> 3.0 - Q2C - Quote to Cash | F104: Q2C-070 | G104: Collections Management | H104: Q2C-070-020 | I104: Perform Collection Activity | K104: =COUNTIF('User Stories'!H:H,'Taxonomy and Epics'!H104) -> 3
A105: Finance | B105: 3.0 | C105: Q2C | D105: Quote to Cash | E105: =B105&" - "&C105&" - "&D105 -> 3.0 - Q2C - Quote to Cash | F105: Q2C-070 | G105: Collections Management | H105: Q2C-070-030 | I105: Perform Escalation & Follow-up | K105: =COUNTIF('User Stories'!H:H,'Taxonomy and Epics'!H105) -> 2
A106: Finance | B106: 3.0 | C106: Q2C | D106: Quote to Cash | E106: =B106&" - "&C106&" - "&D106 -> 3.0 - Q2C - Quote to Cash | F106: Q2C-080 | G106: Period End Close | H106: Q2C-080-010 | I106: Reconcile Bank Transactions | K106: =COUNTIF('User Stories'!H:H,'Taxonomy and Epics'!H106) -> 0
A107: Finance | B107: 3.0 | C107: Q2C | D107: Quote to Cash | E107: =B107&" - "&C107&" - "&D107 -> 3.0 - Q2C - Quote to Cash | F107: Q2C-080 | G107: Period End Close | H107: Q2C-080-020 | I107: Close AR Sub Ledger and Reconcile with GL | K107: =COUNTIF('User Stories'!H:H,'Taxonomy and Epics'!H107) -> 1
A108: Finance | B108: 3.0 | C108: Q2C | D108: Quote to Cash | E108: =B108&" - "&C108&" - "&D108 -> 3.0 - Q2C - Quote to Cash | F108: Q2C-080 | G108: Period End Close | H108: Q2C-080-030 | I108: Perform Revenue Recognition Accounting | K108: =COUNTIF('User Stories'!H:H,'Taxonomy and Epics'!H108) -> 0
A109: Finance | B109: 3.0 | C109: Q2C | D109: Quote to Cash | E109: =B109&" - "&C109&" - "&D109 -> 3.0 - Q2C - Quote to Cash | F109: Q2C-080 | G109: Period End Close | H109: Q2C-080-040 | I109: Prepare Bad Debt and Other Month End Accruals | K109: =COUNTIF('User Stories'!H:H,'Taxonomy and Epics'!H109) -> 0
A110: Finance | B110: 3.0 | C110: Q2C | D110: Quote to Cash | E110: =B110&" - "&C110&" - "&D110 -> 3.0 - Q2C - Quote to Cash | F110: Q2C-090 | G110: Reporting and Analytics - C2C | H110: Q2C-090-010 | I110: Reporting & Analytics AR | K110: =COUNTIF('User Stories'!H:H,'Taxonomy and Epics'!H110) -> 0
A111: Finance | B111: 4.0 | C111: P2R | D111: Project to Result | E111: =B111&" - "&C111&" - "&D111 -> 4.0 - P2R - Project to Result | F111: =LEFT(H111,7) -> P2R-010 | G111: Project Program Planning | H111: P2R-010-010 | I111: Review Capital Plan | K111: =COUNTIF('User Stories'!H:H,'Taxonomy and Epics'!H111) -> 0
A112: Finance | B112: 4.0 | C112: P2R | D112: Project to Result | E112: =B112&" - "&C112&" - "&D112 -> 4.0 - P2R - Project to Result | F112: =LEFT(H112,7) -> P2R-010 | G112: Project Program Planning | H112: P2R-010-020 | I112: Run Predictive Analytics Related to Projects | K112: =COUNTIF('User Stories'!H:H,'Taxonomy and Epics'!H112) -> 0
A113: Finance | B113: 4.0 | C113: P2R | D113: Project to Result | E113: =B113&" - "&C113&" - "&D113 -> 4.0 - P2R - Project to Result | F113: =LEFT(H113,7) -> P2R-010 | G113: Project Program Planning | H113: P2R-010-030 | I113: Define and Maintain Portfolio of Programs | K113: =COUNTIF('User Stories'!H:H,'Taxonomy and Epics'!H113) -> 0
A114: Finance | B114: 4.0 | C114: P2R | D114: Project to Result | E114: =B114&" - "&C114&" - "&D114 -> 4.0 - P2R - Project to Result | F114: =LEFT(H114,7) -> P2R-010 | G114: Project Program Planning | H114: P2R-010-040 | I114: Determine OPEX Project Plans & Budget | K114: =COUNTIF('User Stories'!H:H,'Taxonomy and Epics'!H114) -> 0
A115: Finance | B115: 4.0 | C115: P2R | D115: Project to Result | E115: =B115&" - "&C115&" - "&D115 -> 4.0 - P2R - Project to Result | F115: =LEFT(H115,7) -> P2R-020 | G115: Project Creation and Approval | H115: P2R-020-010 | I115: Define and Approve Project | K115: =COUNTIF('User Stories'!H:H,'Taxonomy and Epics'!H115) -> 0
A116: Finance | B116: 4.0 | C116: P2R | D116: Project to Result | E116: =B116&" - "&C116&" - "&D116 -> 4.0 - P2R - Project to Result | F116: =LEFT(H116,7) -> P2R-020 | G116: Project Creation and Approval | H116: P2R-020-020 | I116: Create Project | K116: =COUNTIF('User Stories'!H:H,'Taxonomy and Epics'!H116) -> 7
A117: Finance | B117: 4.0 | C117: P2R | D117: Project to Result | E117: =B117&" - "&C117&" - "&D117 -> 4.0 - P2R - Project to Result | F117: =LEFT(H117,7) -> P2R-020 | G117: Project Creation and Approval | H117: P2R-020-030 | I117: Setup Project Budget and Resource Plan | K117: =COUNTIF('User Stories'!H:H,'Taxonomy and Epics'!H117) -> 12
A118: Finance | B118: 4.0 | C118: P2R | D118: Project to Result | E118: =B118&" - "&C118&" - "&D118 -> 4.0 - P2R - Project to Result | F118: =LEFT(H118,7) -> P2R-030 | G118: Execute, Monitor and Control Project | H118: P2R-030-010 | I118: Execute Project, Capture & Track Costs | K118: =COUNTIF('User Stories'!H:H,'Taxonomy and Epics'!H118) -> 4
A119: Finance | B119: 4.0 | C119: P2R | D119: Project to Result | E119: =B119&" - "&C119&" - "&D119 -> 4.0 - P2R - Project to Result | F119: =LEFT(H119,7) -> P2R-030 | G119: Execute, Monitor and Control Project | H119: P2R-030-020 | I119: Capture and Track Commitments | K119: =COUNTIF('User Stories'!H:H,'Taxonomy and Epics'!H119) -> 0
A120: Finance | B120: 4.0 | C120: P2R | D120: Project to Result | E120: =B120&" - "&C120&" - "&D120 -> 4.0 - P2R - Project to Result | F120: =LEFT(H120,7) -> P2R-030 | G120: Execute, Monitor and Control Project | H120: P2R-030-030 | I120: Generate Progress Reports & Variance Analysis | K120: =COUNTIF('User Stories'!H:H,'Taxonomy and Epics'!H120) -> 5
A121: Finance | B121: 4.0 | C121: P2R | D121: Project to Result | E121: =B121&" - "&C121&" - "&D121 -> 4.0 - P2R - Project to Result | F121: =LEFT(H121,7) -> P2R-030 | G121: Execute, Monitor and Control Project | H121: P2R-030-040 | I121: Record Project Adjustments | K121: =COUNTIF('User Stories'!H:H,'Taxonomy and Epics'!H121) -> 0
A122: Finance | B122: 4.0 | C122: P2R | D122: Project to Result | E122: =B122&" - "&C122&" - "&D122 -> 4.0 - P2R - Project to Result | F122: =LEFT(H122,7) -> P2R-030 | G122: Execute, Monitor and Control Project | H122: P2R-030-050 | I122: Revise Project Budget/Forecast | K122: =COUNTIF('User Stories'!H:H,'Taxonomy and Epics'!H122) -> 12
... A181: Finance | B181: 6.0 | C181: A2R | D181: Acquire to Retire | E181: =B181&" - "&C181&" - "&D181 -> 6.0 - A2R - Acquire to Retire | F181: =LEFT(H181,7) -> A2R-010 | G181: Capital Program Planning | H181: A2R-010-020 | I181: Define & Maintain Portfolio of Capital Programs | K181: =COUNTIF('User Stories'!H:H,'Taxonomy and Epics'!H181) -> 0
A182: Finance | B182: 6.0 | C182: A2R | D182: Acquire to Retire | E182: =B182&" - "&C182&" - "&D182 -> 6.0 - A2R - Acquire to Retire | F182: =LEFT(H182,7) -> A2R-010 | G182: Capital Program Planning | H182: A2R-010-030 | I182: Complete Capital Appropriations Request & Business Case
A183: Finance | B183: 6.0 | C183: A2R | D183: Acquire to Retire | E183: =B183&" - "&C183&" - "&D183 -> 6.0 - A2R - Acquire to Retire | F183: =LEFT(H183,7) -> A2R-010 | G183: Capital Program Planning | H183: A2R-010-040 | I183: Approve & Communicate Capital Program & Appropriations
A184: Finance | B184: 6.0 | C184: A2R | D184: Acquire to Retire | E184: =B184&" - "&C184&" - "&D184 -> 6.0 - A2R - Acquire to Retire | F184: =LEFT(H184,7) -> A2R-020 | G184: Asset Creation | H184: A2R-020-010 | I184: Create Book/Tax Asset Record & Components | K184: =COUNTIF('User Stories'!H:H,'Taxonomy and Epics'!H182) -> 0
A185: Finance | B185: 6.0 | C185: A2R | D185: Acquire to Retire | E185: =B185&" - "&C185&" - "&D185 -> 6.0 - A2R - Acquire to Retire | F185: =LEFT(H185,7) -> A2R-020 | G185: Asset Creation | H185: A2R-020-020 | I185: Setup Right of Use Assets (Leases) | K185: =COUNTIF('User Stories'!H:H,'Taxonomy and Epics'!#REF!) -> 0
A186: Finance | B186: 6.0 | C186: A2R | D186: Acquire to Retire | E186: =B186&" - "&C186&" - "&D186 -> 6.0 - A2R - Acquire to Retire | F186: =LEFT(H186,7) -> A2R-020 | G186: Asset Creation | H186: A2R-020-030 | I186: Record Contractual Asset Retirement Obligations | K186: =COUNTIF('User Stories'!H:H,'Taxonomy and Epics'!H184) -> 13
A187: Finance | B187: 6.0 | C187: A2R | D187: Acquire to Retire | E187: =B187&" - "&C187&" - "&D187 -> 6.0 - A2R - Acquire to Retire | F187: =LEFT(H187,7) -> A2R-020 | G187: Asset Creation | H187: A2R-020-040 | I187: Place in Service & Issue Asset | K187: =COUNTIF('User Stories'!H:H,'Taxonomy and Epics'!H185) -> 4
A188: Finance | B188: 6.0 | C188: A2R | D188: Acquire to Retire | E188: =B188&" - "&C188&" - "&D188 -> 6.0 - A2R - Acquire to Retire | F188: =LEFT(H188,7) -> A2R-030 | G188: Asset Lifecycle | H188: A2R-030-010 | I188: Run & Review Depreciation | K188: =COUNTIF('User Stories'!H:H,'Taxonomy and Epics'!H186) -> 0
A189: Finance | B189: 6.0 | C189: A2R | D189: Acquire to Retire | E189: =B189&" - "&C189&" - "&D189 -> 6.0 - A2R - Acquire to Retire | F189: =LEFT(H189,7) -> A2R-030 | G189: Asset Lifecycle | H189: A2R-030-020 | I189: Identify Asset Retirements | K189: =COUNTIF('User Stories'!H:H,'Taxonomy and Epics'!H187) -> 2
A190: Finance | B190: 6.0 | C190: A2R | D190: Acquire to Retire | E190: =B190&" - "&C190&" - "&D190 -> 6.0 - A2R - Acquire to Retire | F190: =LEFT(H190,7) -> A2R-030 | G190: Asset Lifecycle | H190: A2R-030-030 | I190: Communicate Secondary Book Retirement Implications | K190: =COUNTIF('User Stories'!H:H,'Taxonomy and Epics'!H188) -> 2
A191: Finance | B191: 6.0 | C191: A2R | D191: Acquire to Retire | E191: =B191&" - "&C191&" - "&D191 -> 6.0 - A2R - Acquire to Retire | F191: =LEFT(H191,7) -> A2R-030 | G191: Asset Lifecycle | H191: A2R-030-040 | I191: Record Asset Retirement | K191: =COUNTIF('User Stories'!H:H,'Taxonomy and Epics'!H189) -> 1
A192: Finance | B192: 6.0 | C192: A2R | D192: Acquire to Retire | E192: =B192&" - "&C192&" - "&D192 -> 6.0 - A2R - Acquire to Retire | F192: =LEFT(H192,7) -> A2R-030 | G192: Asset Lifecycle | H192: A2R-030-050 | I192: Record Asset Sale/Trade | K192: =COUNTIF('User Stories'!H:H,'Taxonomy and Epics'!H190) -> 1
A193: Finance | B193: 6.0 | C193: A2R | D193: Acquire to Retire | E193: =B193&" - "&C193&" - "&D193 -> 6.0 - A2R - Acquire to Retire | F193: =LEFT(H193,7) -> A2R-030 | G193: Asset Lifecycle | H193: A2R-030-060 | I193: Perform Asset Revaluation | K193: =COUNTIF('User Stories'!H:H,'Taxonomy and Epics'!H191) -> 4
A194: Finance | B194: 6.0 | C194: A2R | D194: Acquire to Retire | E194: =B194&" - "&C194&" - "&D194 -> 6.0 - A2R - Acquire to Retire | F194: =LEFT(H194,7) -> A2R-030 | G194: Asset Lifecycle | H194: A2R-030-070 | I194: Record Asset Impairment | K194: =COUNTIF('User Stories'!H:H,'Taxonomy and Epics'!H192) -> 3
A195: Finance | B195: 6.0 | C195: A2R | D195: Acquire to Retire | E195: =B195&" - "&C195&" - "&D195 -> 6.0 - A2R - Acquire to Retire | F195: =LEFT(H195,7) -> A2R-030 | G195: Asset Lifecycle | H195: A2R-030-080 | I195: Record Adjustments to Asset Details | K195: =COUNTIF('User Stories'!H:H,'Taxonomy and Epics'!H193) -> 1
A196: Finance | B196: 6.0 | C196: A2R | D196: Acquire to Retire | E196: =B196&" - "&C196&" - "&D196 -> 6.0 - A2R - Acquire to Retire | F196: =LEFT(H196,7) -> A2R-030 | G196: Asset Lifecycle | H196: A2R-030-090 | I196: Process Transfers | K196: =COUNTIF('User Stories'!H:H,'Taxonomy and Epics'!H194) -> 1
A197: Finance | B197: 6.0 | C197: A2R | D197: Acquire to Retire | E197: =B197&" - "&C197&" - "&D197 -> 6.0 - A2R - Acquire to Retire | F197: =LEFT(H197,7) -> A2R-030 | G197: Asset Lifecycle | H197: A2R-030-100 | I197: Asset Stocktake | K197: =COUNTIF('User Stories'!H:H,'Taxonomy and Epics'!H195) -> 4
... A203: Finance | B203: 7.0 | C203: T2R | D203: Transact to Record | E203: =B203&" - "&C203&" - "&D203 -> 7.0 - T2R - Transact to Record | F203: =LEFT(H203,7) -> T2R-010 | G203: Retrieve & Stage Source Data | H203: T2R-010-020 | I203: Create Journal Input | K203: =COUNTIF('User Stories'!H:H,'Taxonomy and Epics'!H201) -> 0
A204: Finance | B204: 7.0 | C204: T2R | D204: Transact to Record | E204: =B204&" - "&C204&" - "&D204 -> 7.0 - T2R - Transact to Record | F204: =LEFT(H204,7) -> T2R-020 | G204: Import Data & Process Accounting | H204: T2R-020-010 | I204: Import Journal | K204: =COUNTIF('User Stories'!H:H,'Taxonomy and Epics'!H204) -> 0
A205: Finance | B205: 8.0 | C205: R2R | D205: Record to Report | E205: =B205&" - "&C205&" - "&D205 -> 8.0 - R2R - Record to Report | F205: =LEFT(H205,7) -> R2R-010 | G205: Close General Ledger Data Sources | H205: R2R-010-010 | I205: Close & Transfer General Ledger Data Sources | K205: =COUNTIF('User Stories'!H:H,'Taxonomy and Epics'!H205) -> 0
A206: Finance | B206: 8.0 | C206: R2R | D206: Record to Report | E206: =B206&" - "&C206&" - "&D206 -> 8.0 - R2R - Record to Report | F206: =LEFT(H206,7) -> R2R-010 | G206: Close General Ledger Data Sources | H206: R2R-010-020 | I206: Reconcile General Ledger Data Sources | K206: =COUNTIF('User Stories'!H:H,'Taxonomy and Epics'!H206) -> 3
A207: Finance | B207: 8.0 | C207: R2R | D207: Record to Report | E207: =B207&" - "&C207&" - "&D207 -> 8.0 - R2R - Record to Report | F207: =LEFT(H207,7) -> R2R-020 | G207: Pre-Close Activities | H207: R2R-020-010 | I207: Record Journal Entries | K207: =COUNTIF('User Stories'!H:H,'Taxonomy and Epics'!H207) -> 5
A208: Finance | B208: 8.0 | C208: R2R | D208: Record to Report | E208: =B208&" - "&C208&" - "&D208 -> 8.0 - R2R - Record to Report | F208: =LEFT(H208,7) -> R2R-020 | G208: Pre-Close Activities | H208: R2R-020-020 | I208: Process General Ledger Allocations | K208: =COUNTIF('User Stories'!H:H,'Taxonomy and Epics'!H208) -> 1
A209: Finance | B209: 8.0 | C209: R2R | D209: Record to Report | E209: =B209&" - "&C209&" - "&D209 -> 8.0 - R2R - Record to Report | F209: =LEFT(H209,7) -> R2R-020 | G209: Pre-Close Activities | H209: R2R-020-030 | I209: Perform General Ledger Foreign Currency Accounting | K209: =COUNTIF('User Stories'!H:H,'Taxonomy and Epics'!H209) -> 2
A210: Finance | B210: 8.0 | C210: R2R | D210: Record to Report | E210: =B210&" - "&C210&" - "&D210 -> 8.0 - R2R - Record to Report | F210: =LEFT(H210,7) -> R2R-020 | G210: Pre-Close Activities | H210: R2R-020-040 | I210: Perform Intercompany Accounting | K210: =COUNTIF('User Stories'!H:H,'Taxonomy and Epics'!H210) -> 3
A211: Finance | B211: 8.0 | C211: R2R | D211: Record to Report | E211: =B211&" - "&C211&" - "&D211 -> 8.0 - R2R - Record to Report | F211: =LEFT(H211,7) -> R2R-020 | G211: Pre-Close Activities | H211: R2R-020-050 | I211: Perform Accounting Adjustments | K211: =COUNTIF('User Stories'!H:H,'Taxonomy and Epics'!H211) -> 3
A212: Finance | B212: 8.0 | C212: R2R | D212: Record to Report | E212: =B212&" - "&C212&" - "&D212 -> 8.0 - R2R - Record to Report | F212: =LEFT(H212,7) -> R2R-020 | G212: Pre-Close Activities | H212: R2R-020-060 | I212: Perform Journal Review Checks | K212: =COUNTIF('User Stories'!H:H,'Taxonomy and Epics'!H212) -> 4
A213: Finance | B213: 8.0 | C213: R2R | D213: Record to Report | E213: =B213&" - "&C213&" - "&D213 -> 8.0 - R2R - Record to Report | F213: =LEFT(H213,7) -> R2R-030 | G213: Preliminary Financial Reviews & General Ledger Close | H213: R2R-030-010 | I213: Review Trial Balance | K213: =COUNTIF('User Stories'!H:H,'Taxonomy and Epics'!H213) -> 1
...

Sheet User Stories
A1: User Story ID | B1: High Level Summary | C1: User Story | D1: Acceptance Criteria | E1: Business User | F1: A6 Reference | G1: Linked Requirement | H1: Linked Epic ID | I1: Linked Epic | J1: L1 | K1: L2 Code | L1: L2 | M1: L3 Code | N1: L3 | O1: Integration ID | P1: Integratio Name
A2: 1 | B2: Check if customer exists in ERP during credit application processing | C2: As an AR Officer I want to check if a customer already exists in the ERP, so that I can avoid creating duplicate customer records and process credit applications efficiently. | D2: Given I am processing a new customer credit application, When I enter the customer details, Then the system displays whether the customer exists in the ERP or not. | E2: AR Officer | F2: D.40 | H2: Q2C-010-020 | I2: =_xlfn.XLOOKUP(H2,'Taxonomy and Epics'!H:H,'Taxonomy and Epics'!I:I) -> Process New Customer Credit Application | J2: =_xlfn.XLOOKUP($H2,'Taxonomy and Epics'!$H:$H,'Taxonomy and Epics'!E:E) -> 3.0 - Q2C - Quote to Cash | K2: =_xlfn.XLOOKUP($H2,'Taxonomy and Epics'!$H:$H,'Taxonomy and Epics'!F:F) -> Q2C-010 | L2: =_xlfn.XLOOKUP($H2,'Taxonomy and Epics'!$H:$H,'Taxonomy and Epics'!G:G) -> Setup Customer & Credit | M2: =_xlfn.XLOOKUP($H2,'Taxonomy and Epics'!$H:$H,'Taxonomy and Epics'!H:H) -> Q2C-010-020 | N2: =_xlfn.XLOOKUP($H2,'Taxonomy and Epics'!$H:$H,'Taxonomy and Epics'!I:I) -> Process New Customer Credit Application
A3: 2 | B3: Display stored credit rating for existing customers | C3: As an AR Officer I want to view the stored credit rating for existing customers, so that I can make informed credit decisions based on up-to-date information. | D3: Given the customer exists in the ERP, When I view the customer's credit information, Then the system displays the current credit rating (displayed in the D&B Commercial Credit field) retrieved from Workday. | E3: AR Officer | F3: D.67 | H3: Q2C-010-020 | I3: =_xlfn.XLOOKUP(H3,'Taxonomy and Epics'!H:H,'Taxonomy and Epics'!I:I) -> Process New Customer Credit Application | J3: =_xlfn.XLOOKUP($H3,'Taxonomy and Epics'!$H:$H,'Taxonomy and Epics'!E:E) -> 3.0 - Q2C - Quote to Cash | K3: =_xlfn.XLOOKUP($H3,'Taxonomy and Epics'!$H:$H,'Taxonomy and Epics'!F:F) -> Q2C-010 | L3: =_xlfn.XLOOKUP($H3,'Taxonomy and Epics'!$H:$H,'Taxonomy and Epics'!G:G) -> Setup Customer & Credit | M3: =_xlfn.XLOOKUP($H3,'Taxonomy and Epics'!$H:$H,'Taxonomy and Epics'!H:H) -> Q2C-010-020 | N3: =_xlfn.XLOOKUP($H3,'Taxonomy and Epics'!$H:$H,'Taxonomy and Epics'!I:I) -> Process New Customer Credit Application
A4: 3a | B4: Update Credit Score for existing customer | C4: As an AR Officer I want to update the stored credit rating for an existing customer, so that I can make informed credit decisions based on up-to-date information. | D4: Given the customer exists in the ERP, When I update the customer's credit information, Then the system displays the updated credit rating (displayed in the D&B Commercial Credit field) in Workday. | E4: AR Officer | F4: D.39 | H4: Q2C-010-020 | I4: =_xlfn.XLOOKUP(H4,'Taxonomy and Epics'!H:H,'Taxonomy and Epics'!I:I) -> Process New Customer Credit Application | J4: =_xlfn.XLOOKUP($H4,'Taxonomy and Epics'!$H:$H,'Taxonomy and Epics'!E:E) -> 3.0 - Q2C - Quote to Cash | K4: =_xlfn.XLOOKUP($H4,'Taxonomy and Epics'!$H:$H,'Taxonomy and Epics'!F:F) -> Q2C-010 | L4: =_xlfn.XLOOKUP($H4,'Taxonomy and Epics'!$H:$H,'Taxonomy and Epics'!G:G) -> Setup Customer & Credit | M4: =_xlfn.XLOOKUP($H4,'Taxonomy and Epics'!$H:$H,'Taxonomy and Epics'!H:H) -> Q2C-010-020 | N4: =_xlfn.XLOOKUP($H4,'Taxonomy and Epics'!$H:$H,'Taxonomy and Epics'!I:I) -> Process New Customer Credit Application
A5: 3 | B5: Prevent duplicate customer creation using smart validation | C5: As an AR Officer I want to have smart validation when creating new customers, so that duplicate customers are prevented using checks like primary tax ID (ABN) and name. | D5: Given I am creating a new customer, When I enter customer details, Then the system should validate against existing records using ABN and name and prevent duplicates. | E5: AR Officer | F5: D.39 | G5: D.39 | H5: Q2C-010-030 | I5: =_xlfn.XLOOKUP(H5,'Taxonomy and Epics'!H:H,'Taxonomy and Epics'!I:I) -> Setup Customer Financial Master Data | J5: =_xlfn.XLOOKUP($H5,'Taxonomy and Epics'!$H:$H,'Taxonomy and Epics'!E:E) -> 3.0 - Q2C - Quote to Cash | K5: =_xlfn.XLOOKUP($H5,'Taxonomy and Epics'!$H:$H,'Taxonomy and Epics'!F:F) -> Q2C-010 | L5: =_xlfn.XLOOKUP($H5,'Taxonomy and Epics'!$H:$H,'Taxonomy and Epics'!G:G) -> Setup Customer & Credit | M5: =_xlfn.XLOOKUP($H5,'Taxonomy and Epics'!$H:$H,'Taxonomy and Epics'!H:H) -> Q2C-010-030 | N5: =_xlfn.XLOOKUP($H5,'Taxonomy and Epics'!$H:$H,'Taxonomy and Epics'!I:I) -> Setup Customer Financial Master Data
A6: 4 | B6: Single view of customer record | C6: As an AR Officer I want to see a single view of the customer, so that I can access all relevant information in one place. | D6: Given I am searching for a customer, When I select a customer record, Then I should see a consolidated view of all customer information. | E6: AR Officer | F6: D.41 | G6: D.41 | H6: Q2C-010-030 | I6: =_xlfn.XLOOKUP(H6,'Taxonomy and Epics'!H:H,'Taxonomy and Epics'!I:I) -> Setup Customer Financial Master Data | J6: =_xlfn.XLOOKUP($H6,'Taxonomy and Epics'!$H:$H,'Taxonomy and Epics'!E:E) -> 3.0 - Q2C - Quote to Cash | K6: =_xlfn.XLOOKUP($H6,'Taxonomy and Epics'!$H:$H,'Taxonomy and Epics'!F:F) -> Q2C-010 | L6: =_xlfn.XLOOKUP($H6,'Taxonomy and Epics'!$H:$H,'Taxonomy and Epics'!G:G) -> Setup Customer & Credit | M6: =_xlfn.XLOOKUP($H6,'Taxonomy and Epics'!$H:$H,'Taxonomy and Epics'!H:H) -> Q2C-010-030 | N6: =_xlfn.XLOOKUP($H6,'Taxonomy and Epics'!$H:$H,'Taxonomy and Epics'!I:I) -> Setup Customer Financial Master Data
A7: 5 | B7: Requesting a Customer | C7: As a Business User I want to request a new customer through ServiceNow so that a formal customer creation process is initiated | D7: Given a business user needs a new customer, when they complete the ServiceNow request form, then the request is recorded in ServiceNow and a notification is sent to the AR Officer to start customer creation. | E7: Business User | F7: D.40 | H7: Q2C-010-030 | I7: =_xlfn.XLOOKUP(H7,'Taxonomy and Epics'!H:H,'Taxonomy and Epics'!I:I) -> Setup Customer Financial Master Data | J7: =_xlfn.XLOOKUP($H7,'Taxonomy and Epics'!$H:$H,'Taxonomy and Epics'!E:E) -> 3.0 - Q2C - Quote to Cash | K7: =_xlfn.XLOOKUP($H7,'Taxonomy and Epics'!$H:$H,'Taxonomy and Epics'!F:F) -> Q2C-010 | L7: =_xlfn.XLOOKUP($H7,'Taxonomy and Epics'!$H:$H,'Taxonomy and Epics'!G:G) -> Setup Customer & Credit | M7: =_xlfn.XLOOKUP($H7,'Taxonomy and Epics'!$H:$H,'Taxonomy and Epics'!H:H) -> Q2C-010-030 | N7: =_xlfn.XLOOKUP($H7,'Taxonomy and Epics'!$H:$H,'Taxonomy and Epics'!I:I) -> Setup Customer Financial Master Data
A8: 6 | B8: Creating a Customer In Workday | C8: As an AR Officer I want the system to allow creation of a new customer record in Workday so that the organisation can invoice and manage the customer | D8: 1. Given the AR Officer has valid request data, when they create the customer record, then the customer record is saved in Workday with a unique customer identifier and is available for invoicing and reporting. 2. Given the AR Officer is creating a customer, when they submit the record without a billing address, then the system rejects the save and shows an error indicating the billing address is required. 3. Given the AR Officer is creating or editing a customer, a shipping address is required, then the system uses that shipping address to determine tax defaults on invoices 4. Given the AR Officer is creating a customer, when the customer is save-attempted without a Tax ID, then the system rejects the save and displays an error stating a Tax ID is required; and when a Tax ID is provided, then it is stored and visible on the customer record. 5. Given the AR Officer is creating or updating a customer, when they set the Tax Status, then the chosen status is saved and applied to invoice tax calculations; and when no Tax Status is set, then the system prompts the AR Officer to select one before saving. 6. Given the AR Officer is creating a customer, when they select payment terms, then those terms are saved on the customer record and used as the default on invoices; and when payment terms are missing, then the system blocks saving the record and prompts for terms. 7. Given the AR Officer enters an email for the customer, when the record is saved, then the email is stored on the customer record and available for communications 8. Given the AR officer enters Bank Account details for the customer, when the record is submitted for processing then there is an additional approval by another AR Officer than the initiator | E8: AR Officer | F8: D.289 | G8: D.289 | H8: Q2C-010-030 | I8: =_xlfn.XLOOKUP(H8,'Taxonomy and Epics'!H:H,'Taxonomy and Epics'!I:I) -> Setup Customer Financial Master Data | J8: =_xlfn.XLOOKUP($H8,'Taxonomy and Epics'!$H:$H,'Taxonomy and Epics'!E:E) -> 3.0 - Q2C - Quote to Cash | K8: =_xlfn.XLOOKUP($H8,'Taxonomy and Epics'!$H:$H,'Taxonomy and Epics'!F:F) -> Q2C-010 | L8: =_xlfn.XLOOKUP($H8,'Taxonomy and Epics'!$H:$H,'Taxonomy and Epics'!G:G) -> Setup Customer & Credit | M8: =_xlfn.XLOOKUP($H8,'Taxonomy and Epics'!$H:$H,'Taxonomy and Epics'!H:H) -> Q2C-010-030 | N8: =_xlfn.XLOOKUP($H8,'Taxonomy and Epics'!$H:$H,'Taxonomy and Epics'!I:I) -> Setup Customer Financial Master Data
A9: US001 | B9: Viewing Credit Limits | C9: As a Credit Officer, I want to generate a report on customer credit limits and usage, so that I can proactively manage credit risk. | D9: - Given I have the necessary permissions, when I run the credit review report, then the system displays a list of customers with their credit limits and current outstanding balances. - Given the report is generated, when a customer's balance exceeds their credit limit, then they are clearly flagged in the report. | E9: Credit Officer | F9: D.67 | H9: Q2C-010-040 | I9: =_xlfn.XLOOKUP(H9,'Taxonomy and Epics'!H:H,'Taxonomy and Epics'!I:I) -> Perform Periodic Credit Review | J9: =_xlfn.XLOOKUP($H9,'Taxonomy and Epics'!$H:$H,'Taxonomy and Epics'!E:E) -> 3.0 - Q2C - Quote to Cash | K9: =_xlfn.XLOOKUP($H9,'Taxonomy and Epics'!$H:$H,'Taxonomy and Epics'!F:F) -> Q2C-010 | L9: =_xlfn.XLOOKUP($H9,'Taxonomy and Epics'!$H:$H,'Taxonomy and Epics'!G:G) -> Setup Customer & Credit | M9: =_xlfn.XLOOKUP($H9,'Taxonomy and Epics'!$H:$H,'Taxonomy and Epics'!H:H) -> Q2C-010-040 | N9: =_xlfn.XLOOKUP($H9,'Taxonomy and Epics'!$H:$H,'Taxonomy and Epics'!I:I) -> Perform Periodic Credit Review
A10: US002 | B10: Placing a customer on hold | C10: As a Credit Officer, I want to place a customer on hold, so that I can prevent further transactions until credit issues are resolved. | D10: - Given I am viewing an active customer's record, when I initiate the 'Place on Hold' action, then the system requires me to enter a reason for the hold. - Given I am a Credit Officer (but not a Customer Administrator), when I submit the hold request, then it is routed to an Accounts Receivable Officer (Customer Administrator) for approval. - Given the hold request is approved, then the customer's status is updated to 'On Hold'. | E10: Credit Officer | F10: 0 | H10: Q2C-010-040 | I10: =_xlfn.XLOOKUP(H10,'Taxonomy and Epics'!H:H,'Taxonomy and Epics'!I:I) -> Perform Periodic Credit Review | J10: =_xlfn.XLOOKUP($H10,'Taxonomy and Epics'!$H:$H,'Taxonomy and Epics'!E:E) -> 3.0 - Q2C - Quote to Cash | K10: =_xlfn.XLOOKUP($H10,'Taxonomy and Epics'!$H:$H,'Taxonomy and Epics'!F:F) -> Q2C-010 | L10: =_xlfn.XLOOKUP($H10,'Taxonomy and Epics'!$H:$H,'Taxonomy and Epics'!G:G) -> Setup Customer & Credit | M10: =_xlfn.XLOOKUP($H10,'Taxonomy and Epics'!$H:$H,'Taxonomy and Epics'!H:H) -> Q2C-010-040 | N10: =_xlfn.XLOOKUP($H10,'Taxonomy and Epics'!$H:$H,'Taxonomy and Epics'!I:I) -> Perform Periodic Credit Review
A11: US003 | B11: Making a customer inactive | C11: As an Accounts Receivable Officer, I want to make a customer inactive, so that their record is closed and no new transactions can be processed against it. | D11: - Given I am an Accounts Receivable Officer viewing a customer record, when I initiate the customer summary change process to make a customer 'Inactive', then the system updates the customer's status to 'Inactive' without requiring an approval step. - Given a customer is inactive, when a user attempts to create a new invoice for an 'inactive' customer they are unable to select the record. | E11: Accounts Receivable Officer | F11: 0 | H11: Q2C-010-050 | I11: =_xlfn.XLOOKUP(H11,'Taxonomy and Epics'!H:H,'Taxonomy and Epics'!I:I) -> Perform Customer Closure | J11: =_xlfn.XLOOKUP($H11,'Taxonomy and Epics'!$H:$H,'Taxonomy and Epics'!E:E) -> 3.0 - Q2C - Quote to Cash | K11: =_xlfn.XLOOKUP($H11,'Taxonomy and Epics'!$H:$H,'Taxonomy and Epics'!F:F) -> Q2C-010 | L11: =_xlfn.XLOOKUP($H11,'Taxonomy and Epics'!$H:$H,'Taxonomy and Epics'!G:G) -> Setup Customer & Credit | M11: =_xlfn.XLOOKUP($H11,'Taxonomy and Epics'!$H:$H,'Taxonomy and Epics'!H:H) -> Q2C-010-050 | N11: =_xlfn.XLOOKUP($H11,'Taxonomy and Epics'!$H:$H,'Taxonomy and Epics'!I:I) -> Perform Customer Closure
A12: US004 | B12: writing up an on account balance | C12: As an Accounts Receivable Officer, I want to wite up a customer's on-account credit balance when closing their account, so that the balance is correctly managed. | D12: - Given a customer with an on-account credit is being made inactive, when I process The customer overpayment, then there is a write-up reflected in the P&L - Given a customer with an on-account credit is being made inactive, when I process The customer overpayment, then there is an approval by the shared services manager | E12: Accounts Receivable Officer | F12: 0 | H12: Q2C-010-050 | I12: =_xlfn.XLOOKUP(H12,'Taxonomy and Epics'!H:H,'Taxonomy and Epics'!I:I) -> Perform Customer Closure | J12: =_xlfn.XLOOKUP($H12,'Taxonomy and Epics'!$H:$H,'Taxonomy and Epics'!E:E) -> 3.0 - Q2C - Quote to Cash | K12: =_xlfn.XLOOKUP($H12,'Taxonomy and Epics'!$H:$H,'Taxonomy and Epics'!F:F) -> Q2C-010 | L12: =_xlfn.XLOOKUP($H12,'Taxonomy and Epics'!$H:$H,'Taxonomy and Epics'!G:G) -> Setup Customer & Credit | M12: =_xlfn.XLOOKUP($H12,'Taxonomy and Epics'!$H:$H,'Taxonomy and Epics'!H:H) -> Q2C-010-050 | N12: =_xlfn.XLOOKUP($H12,'Taxonomy and Epics'!$H:$H,'Taxonomy and Epics'!I:I) -> Perform Customer Closure
A13: US005 | B13: Requesting a new customer contract | C13: As a Business User, I want to request the creation of a new customer contract via Service Now, so that the request is formally logged for the Accounts Receivable team to action. | D13: - Given I am in Service Now, when I access the contract request form, then I can enter all necessary details for a new contract. - Given I submit the request, then it is routed to the Accounts Receivable team with all the information needed to create the contract in Workday. | E13: Business User | F13: 0 | H13: Q2C-020-010 | I13: =_xlfn.XLOOKUP(H13,'Taxonomy and Epics'!H:H,'Taxonomy and Epics'!I:I) -> Establish Contract Portfolio Management | J13: =_xlfn.XLOOKUP($H13,'Taxonomy and Epics'!$H:$H,'Taxonomy and Epics'!E:E) -> 3.0 - Q2C - Quote to Cash | K13: =_xlfn.XLOOKUP($H13,'Taxonomy and Epics'!$H:$H,'Taxonomy and Epics'!F:F) -> Q2C-020 | L13: =_xlfn.XLOOKUP($H13,'Taxonomy and Epics'!$H:$H,'Taxonomy and Epics'!G:G) -> Contract Lifecycle Management (Customer) | M13: =_xlfn.XLOOKUP($H13,'Taxonomy and Epics'!$H:$H,'Taxonomy and Epics'!H:H) -> Q2C-020-010 | N13: =_xlfn.XLOOKUP($H13,'Taxonomy and Epics'!$H:$H,'Taxonomy and Epics'!I:I) -> Establish Contract Portfolio Management
A14: US006 | B14: Processing a customer contract | C14: As an Accounts Receivable Officer, I want to create a new customer contract in Workday, so that billing and revenue can be managed according to agreed terms. | D14: - Given I have a valid contract request, when I use the 'Create Customer Contract' task, then I can enter all contract details, such as for a Property Rental Contract. - Given I submit the new contract, then it becomes active and available for a billing schedule to be created. | E14: Accounts Receivable Officer | F14: 0 | H14: Q2C-020-010 | I14: =_xlfn.XLOOKUP(H14,'Taxonomy and Epics'!H:H,'Taxonomy and Epics'!I:I) -> Establish Contract Portfolio Management | J14: =_xlfn.XLOOKUP($H14,'Taxonomy and Epics'!$H:$H,'Taxonomy and Epics'!E:E) -> 3.0 - Q2C - Quote to Cash | K14: =_xlfn.XLOOKUP($H14,'Taxonomy and Epics'!$H:$H,'Taxonomy and Epics'!F:F) -> Q2C-020 | L14: =_xlfn.XLOOKUP($H14,'Taxonomy and Epics'!$H:$H,'Taxonomy and Epics'!G:G) -> Contract Lifecycle Management (Customer) | M14: =_xlfn.XLOOKUP($H14,'Taxonomy and Epics'!$H:$H,'Taxonomy and Epics'!H:H) -> Q2C-020-010 | N14: =_xlfn.XLOOKUP($H14,'Taxonomy and Epics'!$H:$H,'Taxonomy and Epics'!I:I) -> Establish Contract Portfolio Management
A15: US007 | B15: processing a contract's billing schedule | C15: As an Accounts Receivable Officer, I want to create a billing schedule for a customer contract, so that invoices are generated automatically at the correct intervals. | D15: - Given I am a customer contract exists, when I create a billing schedule associated with the contract, then I can create a billing schedule which defines the billing frequency, amount, and dates. - Given the billing schedule is submitted, when a scheduled billing date arrives, then the system automatically generates the correct customer invoice. | E15: Accounts Receivable Officer | F15: 0 | H15: Q2C-020-010 | I15: =_xlfn.XLOOKUP(H15,'Taxonomy and Epics'!H:H,'Taxonomy and Epics'!I:I) -> Establish Contract Portfolio Management | J15: =_xlfn.XLOOKUP($H15,'Taxonomy and Epics'!$H:$H,'Taxonomy and Epics'!E:E) -> 3.0 - Q2C - Quote to Cash | K15: =_xlfn.XLOOKUP($H15,'Taxonomy and Epics'!$H:$H,'Taxonomy and Epics'!F:F) -> Q2C-020 | L15: =_xlfn.XLOOKUP($H15,'Taxonomy and Epics'!$H:$H,'Taxonomy and Epics'!G:G) -> Contract Lifecycle Management (Customer) | M15: =_xlfn.XLOOKUP($H15,'Taxonomy and Epics'!$H:$H,'Taxonomy and Epics'!H:H) -> Q2C-020-010 | N15: =_xlfn.XLOOKUP($H15,'Taxonomy and Epics'!$H:$H,'Taxonomy and Epics'!I:I) -> Establish Contract Portfolio Management
A16: US008 | B16: Processing a deferred revenue contract's deferred revenue schedule | C16: As a Revenue Specialist, I want to create a revenue recognition schedule for contracts with deferred revenue, so that revenue is recognised in the correct accounting period. | D16: - Given a customer contract is flagged for deferred revenue, when the contract is created, then the system prompts for the creation of a revenue recognition schedule. - Given I create a revenue recognition schedule according to a defined schedule, then the system will then automatically create and post revenue accounting journals each month. | E16: Revenue Specialist | F16: 0 | H16: Q2C-020-010 | I16: =_xlfn.XLOOKUP(H16,'Taxonomy and Epics'!H:H,'Taxonomy and Epics'!I:I) -> Establish Contract Portfolio Management | J16: =_xlfn.XLOOKUP($H16,'Taxonomy and Epics'!$H:$H,'Taxonomy and Epics'!E:E) -> 3.0 - Q2C - Quote to Cash | K16: =_xlfn.XLOOKUP($H16,'Taxonomy and Epics'!$H:$H,'Taxonomy and Epics'!F:F) -> Q2C-020 | L16: =_xlfn.XLOOKUP($H16,'Taxonomy and Epics'!$H:$H,'Taxonomy and Epics'!G:G) -> Contract Lifecycle Management (Customer) | M16: =_xlfn.XLOOKUP($H16,'Taxonomy and Epics'!$H:$H,'Taxonomy and Epics'!H:H) -> Q2C-020-010 | N16: =_xlfn.XLOOKUP($H16,'Taxonomy and Epics'!$H:$H,'Taxonomy and Epics'!I:I) -> Establish Contract Portfolio Management
A17: US009 | B17: amending an existing customer contract | C17: As an Accounts Receivable Officer, I want to amend an existing customer contract's value, so that the changes are reflected in the future billing schedule. | D17: - Given I am viewing an existing contract, when I initiate an amendment, then I can enter a change to the contract value (dollar amount). - Given I submit the amendment, then the future instalments on the associated billing schedule are updated to reflect the new total contract value. | E17: Accounts Receivable Officer | F17: 0 | H17: Q2C-020-030 | I17: =_xlfn.XLOOKUP(H17,'Taxonomy and Epics'!H:H,'Taxonomy and Epics'!I:I) -> Manage Contract Compliance and Administration | J17: =_xlfn.XLOOKUP($H17,'Taxonomy and Epics'!$H:$H,'Taxonomy and Epics'!E:E) -> 3.0 - Q2C - Quote to Cash | K17: =_xlfn.XLOOKUP($H17,'Taxonomy and Epics'!$H:$H,'Taxonomy and Epics'!F:F) -> Q2C-020 | L17: =_xlfn.XLOOKUP($H17,'Taxonomy and Epics'!$H:$H,'Taxonomy and Epics'!G:G) -> Contract Lifecycle Management (Customer) | M17: =_xlfn.XLOOKUP($H17,'Taxonomy and Epics'!$H:$H,'Taxonomy and Epics'!H:H) -> Q2C-020-030 | N17: =_xlfn.XLOOKUP($H17,'Taxonomy and Epics'!$H:$H,'Taxonomy and Epics'!I:I) -> Manage Contract Compliance and Administration
A18: US010 | B18: viewing fully billed contracts | C18: As an Accounts Receivable Officer, I want to view identify contracts that are fully billed, so that I can validate we are able to close a contract | D18: - Given I am viewing an existing contract, then it displays that the amount billed is the total of the contract and has no available installments remaining | E18: Accounts Receivable Officer | F18: 0 | H18: Q2C-020-040 | I18: =_xlfn.XLOOKUP(H18,'Taxonomy and Epics'!H:H,'Taxonomy and Epics'!I:I) -> Close Out Contract | J18: =_xlfn.XLOOKUP($H18,'Taxonomy and Epics'!$H:$H,'Taxonomy and Epics'!E:E) -> 3.0 - Q2C - Quote to Cash | K18: =_xlfn.XLOOKUP($H18,'Taxonomy and Epics'!$H:$H,'Taxonomy and Epics'!F:F) -> Q2C-020 | L18: =_xlfn.XLOOKUP($H18,'Taxonomy and Epics'!$H:$H,'Taxonomy and Epics'!G:G) -> Contract Lifecycle Management (Customer) | M18: =_xlfn.XLOOKUP($H18,'Taxonomy and Epics'!$H:$H,'Taxonomy and Epics'!H:H) -> Q2C-020-040 | N18: =_xlfn.XLOOKUP($H18,'Taxonomy and Epics'!$H:$H,'Taxonomy and Epics'!I:I) -> Close Out Contract
A19: US011 | B19: changing customer payment terms | C19: As an Accounts Receivable Officer, I want to change a customer's default payment terms, so that all future invoices for that customer reflect the new terms. | D19: - Given I am viewing a customer's record, when I edit their payment information, then I can select new payment terms. - Given I have submitted the new terms, when a new invoice is created for this customer, then its due date is calculated based on the new terms. | E19: Accounts Receivable Officer | F19: 0 | H19: Q2C-040-010 | I19: =_xlfn.XLOOKUP(H19,'Taxonomy and Epics'!H:H,'Taxonomy and Epics'!I:I) -> Manage Billing and Payment Methods | J19: =_xlfn.XLOOKUP($H19,'Taxonomy and Epics'!$H:$H,'Taxonomy and Epics'!E:E) -> 3.0 - Q2C - Quote to Cash | K19: =_xlfn.XLOOKUP($H19,'Taxonomy and Epics'!$H:$H,'Taxonomy and Epics'!F:F) -> Q2C-040 | L19: =_xlfn.XLOOKUP($H19,'Taxonomy and Epics'!$H:$H,'Taxonomy and Epics'!G:G) -> Billing Management | M19: =_xlfn.XLOOKUP($H19,'Taxonomy and Epics'!$H:$H,'Taxonomy and Epics'!H:H) -> Q2C-040-010 | N19: =_xlfn.XLOOKUP($H19,'Taxonomy and Epics'!$H:$H,'Taxonomy and Epics'!I:I) -> Manage Billing and Payment Methods
A20: US012 | B20: changing payment terms on a billling schedule | C20: As an Accounts Receivable Officer, I want to override the payment terms on a specific billing schedule, so that its invoices have different terms from the customer's default. | D20: - Given I am editing a billing schedule, when I change the payment terms, then I can set terms that are different from the customer's default. - Given I have submitted the schedule, when an invoice is generated from it, then its due date is based on the schedule's specific terms. | E20: Accounts Receivable Officer | F20: 0 | H20: Q2C-040-010 | I20: =_xlfn.XLOOKUP(H20,'Taxonomy and Epics'!H:H,'Taxonomy and Epics'!I:I) -> Manage Billing and Payment Methods | J20: =_xlfn.XLOOKUP($H20,'Taxonomy and Epics'!$H:$H,'Taxonomy and Epics'!E:E) -> 3.0 - Q2C - Quote to Cash | K20: =_xlfn.XLOOKUP($H20,'Taxonomy and Epics'!$H:$H,'Taxonomy and Epics'!F:F) -> Q2C-040 | L20: =_xlfn.XLOOKUP($H20,'Taxonomy and Epics'!$H:$H,'Taxonomy and Epics'!G:G) -> Billing Management | M20: =_xlfn.XLOOKUP($H20,'Taxonomy and Epics'!$H:$H,'Taxonomy and Epics'!H:H) -> Q2C-040-010 | N20: =_xlfn.XLOOKUP($H20,'Taxonomy and Epics'!$H:$H,'Taxonomy and Epics'!I:I) -> Manage Billing and Payment Methods
A21: US013 | B21: requesting a one-off invoice | C21: As a Business User, I want to request a one-off customer invoice via Service Now, so that the Accounts Receivable team can create it accurately in Workday. | D21: - Given I am in Service Now, when I open the 'Invoice Request' form, then I can enter all required details and attach supporting documents. - Given I submit the request, then it is routed to the Accounts Receivable team's queue for processing. | E21: Business User | F21: D.46 | H21: Q2C-040-020 | I21: =_xlfn.XLOOKUP(H21,'Taxonomy and Epics'!H:H,'Taxonomy and Epics'!I:I) -> Generate, Review & Approve Invoice | J21: =_xlfn.XLOOKUP($H21,'Taxonomy and Epics'!$H:$H,'Taxonomy and Epics'!E:E) -> 3.0 - Q2C - Quote to Cash | K21: =_xlfn.XLOOKUP($H21,'Taxonomy and Epics'!$H:$H,'Taxonomy and Epics'!F:F) -> Q2C-040 | L21: =_xlfn.XLOOKUP($H21,'Taxonomy and Epics'!$H:$H,'Taxonomy and Epics'!G:G) -> Billing Management | M21: =_xlfn.XLOOKUP($H21,'Taxonomy and Epics'!$H:$H,'Taxonomy and Epics'!H:H) -> Q2C-040-020 | N21: =_xlfn.XLOOKUP($H21,'Taxonomy and Epics'!$H:$H,'Taxonomy and Epics'!I:I) -> Generate, Review & Approve Invoice
A22: US014 | B22: processing a one-off invoice | C22: As an Accounts Receivable Officer, I want to create a standalone customer invoice, so that I can bill customers for items not covered by a contract. | D22: - Given I have a valid invoice request, when I use the 'Create Customer Invoice' task, then I can enter all details from the request. - Given I submit the invoice, then it is created and awaits approval before being sent. | E22: Accounts Receivable Officer | F22: D.45 | H22: Q2C-040-020 | I22: =_xlfn.XLOOKUP(H22,'Taxonomy and Epics'!H:H,'Taxonomy and Epics'!I:I) -> Generate, Review & Approve Invoice | J22: =_xlfn.XLOOKUP($H22,'Taxonomy and Epics'!$H:$H,'Taxonomy and Epics'!E:E) -> 3.0 - Q2C - Quote to Cash | K22: =_xlfn.XLOOKUP($H22,'Taxonomy and Epics'!$H:$H,'Taxonomy and Epics'!F:F) -> Q2C-040 | L22: =_xlfn.XLOOKUP($H22,'Taxonomy and Epics'!$H:$H,'Taxonomy and Epics'!G:G) -> Billing Management | M22: =_xlfn.XLOOKUP($H22,'Taxonomy and Epics'!$H:$H,'Taxonomy and Epics'!H:H) -> Q2C-040-020 | N22: =_xlfn.XLOOKUP($H22,'Taxonomy and Epics'!$H:$H,'Taxonomy and Epics'!I:I) -> Generate, Review & Approve Invoice
A23: US015 | B23: distributing attachments to a customer on an invoice | C23: As an Accounts Receivable Officer, I want to add attachments to an invoice and control their visibility, so that I can provide supporting documents to the customer or keep internal notes. | D23: - Given I am creating an invoice, when I add an attachment, then the system prompts me to choose if it is 'internal only' or 'provide to customer'. - Given an attachment is marked 'provide to customer', when the invoice is emailed, then the attachment is included. - Given an attachment is not marked 'provide to customer', when the invoice is emailed, then the attachment is not included. | E23: Accounts Receivable Officer | F23: 0 | H23: Q2C-040-020 | I23: =_xlfn.XLOOKUP(H23,'Taxonomy and Epics'!H:H,'Taxonomy and Epics'!I:I) -> Generate, Review & Approve Invoice | J23: =_xlfn.XLOOKUP($H23,'Taxonomy and Epics'!$H:$H,'Taxonomy and Epics'!E:E) -> 3.0 - Q2C - Quote to Cash | K23: =_xlfn.XLOOKUP($H23,'Taxonomy and Epics'!$H:$H,'Taxonomy and Epics'!F:F) -> Q2C-040 | L23: =_xlfn.XLOOKUP($H23,'Taxonomy and Epics'!$H:$H,'Taxonomy and Epics'!G:G) -> Billing Management | M23: =_xlfn.XLOOKUP($H23,'Taxonomy and Epics'!$H:$H,'Taxonomy and Epics'!H:H) -> Q2C-040-020 | N23: =_xlfn.XLOOKUP($H23,'Taxonomy and Epics'!$H:$H,'Taxonomy and Epics'!I:I) -> Generate, Review & Approve Invoice
A24: US016 | B24: Processing one off invoices with deferred revenue | C24: As a Revenue Specialist, I want a revenue recognition schedule created for any standalone invoice with deferred revenue, so that revenue is recognised in the correct periods. | D24: - Given an invoice is created with items flagged for deferred revenue, when it is submitted, then a To-Do task is created for me to create a revenue recognition schedule. | E24: Revenue Specialist | F24: D.63 | H24: Q2C-040-020 | I24: =_xlfn.XLOOKUP(H24,'Taxonomy and Epics'!H:H,'Taxonomy and Epics'!I:I) -> Generate, Review & Approve Invoice | J24: =_xlfn.XLOOKUP($H24,'Taxonomy and Epics'!$H:$H,'Taxonomy and Epics'!E:E) -> 3.0 - Q2C - Quote to Cash | K24: =_xlfn.XLOOKUP($H24,'Taxonomy and Epics'!$H:$H,'Taxonomy and Epics'!F:F) -> Q2C-040 | L24: =_xlfn.XLOOKUP($H24,'Taxonomy and Epics'!$H:$H,'Taxonomy and Epics'!G:G) -> Billing Management | M24: =_xlfn.XLOOKUP($H24,'Taxonomy and Epics'!$H:$H,'Taxonomy and Epics'!H:H) -> Q2C-040-020 | N24: =_xlfn.XLOOKUP($H24,'Taxonomy and Epics'!$H:$H,'Taxonomy and Epics'!I:I) -> Generate, Review & Approve Invoice
A25: US017 | B25: emailing invoices to a customer | C25: As an Accounts Receivable Officer, I want to email a finalised invoice to a customer, so that they receive it for payment. | D25: - Given an invoice is approved, when it is automatically processed, then a PDF copy is generated and stored in Workday. - Given the customer has a valid email, when I email the invoice, then it is sent to their primary billing contact. - Given the customer has no email address, when I review invoices scheduled to be emailed, then I can view a list of invoices which have not been emailed | E25: Accounts Receivable Officer | F25: 0 | H25: Q2C-040-030 | I25: =_xlfn.XLOOKUP(H25,'Taxonomy and Epics'!H:H,'Taxonomy and Epics'!I:I) -> Distribute Invoice | J25: =_xlfn.XLOOKUP($H25,'Taxonomy and Epics'!$H:$H,'Taxonomy and Epics'!E:E) -> 3.0 - Q2C - Quote to Cash | K25: =_xlfn.XLOOKUP($H25,'Taxonomy and Epics'!$H:$H,'Taxonomy and Epics'!F:F) -> Q2C-040 | L25: =_xlfn.XLOOKUP($H25,'Taxonomy and Epics'!$H:$H,'Taxonomy and Epics'!G:G) -> Billing Management | M25: =_xlfn.XLOOKUP($H25,'Taxonomy and Epics'!$H:$H,'Taxonomy and Epics'!H:H) -> Q2C-040-030 | N25: =_xlfn.XLOOKUP($H25,'Taxonomy and Epics'!$H:$H,'Taxonomy and Epics'!I:I) -> Distribute Invoice
A26: US018 | B26: generating an invoice but not emailing it | C26: As an Accounts Receivable Officer, I want to generate a PDF of an invoice without emailing it, so that I can print it or send it through other channels. | D26: - Given an invoice is marked as "Do Not Send", when the invoice is approved, the invoice Print Run and Email Steps are not triggered. Given an invoice is marked as "Do Not Send", when I select the 'Print Invoice' action, then the system creates a PDF for download without sending an email. | E26: Accounts Receivable Officer | F26: 0 | H26: Q2C-040-030 | I26: =_xlfn.XLOOKUP(H26,'Taxonomy and Epics'!H:H,'Taxonomy and Epics'!I:I) -> Distribute Invoice | J26: =_xlfn.XLOOKUP($H26,'Taxonomy and Epics'!$H:$H,'Taxonomy and Epics'!E:E) -> 3.0 - Q2C - Quote to Cash | K26: =_xlfn.XLOOKUP($H26,'Taxonomy and Epics'!$H:$H,'Taxonomy and Epics'!F:F) -> Q2C-040 | L26: =_xlfn.XLOOKUP($H26,'Taxonomy and Epics'!$H:$H,'Taxonomy and Epics'!G:G) -> Billing Management | M26: =_xlfn.XLOOKUP($H26,'Taxonomy and Epics'!$H:$H,'Taxonomy and Epics'!H:H) -> Q2C-040-030 | N26: =_xlfn.XLOOKUP($H26,'Taxonomy and Epics'!$H:$H,'Taxonomy and Epics'!I:I) -> Distribute Invoice
A27: US019 | B27: updating the PO on a customer invoice | C27: As an Accounts Receivable Officer, I want to add or change the Purchase Order (PO) number on an existing invoice, so that it reflects the correct customer reference. | D27: - Given I am viewing a created invoice, when I edit it, then I can update the PO number field. - Given I have updated the PO number, when I regenerate the invoice PDF, then the new PO number is displayed on the document. | E27: Accounts Receivable Officer | F27: 0 | H27: Q2C-040-030 | I27: =_xlfn.XLOOKUP(H27,'Taxonomy and Epics'!H:H,'Taxonomy and Epics'!I:I) -> Distribute Invoice | J27: =_xlfn.XLOOKUP($H27,'Taxonomy and Epics'!$H:$H,'Taxonomy and Epics'!E:E) -> 3.0 - Q2C - Quote to Cash | K27: =_xlfn.XLOOKUP($H27,'Taxonomy and Epics'!$H:$H,'Taxonomy and Epics'!F:F) -> Q2C-040 | L27: =_xlfn.XLOOKUP($H27,'Taxonomy and Epics'!$H:$H,'Taxonomy and Epics'!G:G) -> Billing Management | M27: =_xlfn.XLOOKUP($H27,'Taxonomy and Epics'!$H:$H,'Taxonomy and Epics'!H:H) -> Q2C-040-030 | N27: =_xlfn.XLOOKUP($H27,'Taxonomy and Epics'!$H:$H,'Taxonomy and Epics'!I:I) -> Distribute Invoice
A28: US020 | B28: scheduling customer statements | C28: As an Accounts Receivable Officer, I want to schedule the automatic monthly delivery of customer statements, so that customers are regularly informed of their account status. | D28: - Given I am configuring statement schedules, when I set up a schedule, then I can select a monthly frequency. - Given the schedule is active, when the scheduled day arrives, then the system automatically generates and emails statements to eligible customers. | E28: Accounts Receivable Officer | F28: D.47 | H28: Q2C-040-040 | I28: =_xlfn.XLOOKUP(H28,'Taxonomy and Epics'!H:H,'Taxonomy and Epics'!I:I) -> Generate and Distribute Statements | J28: =_xlfn.XLOOKUP($H28,'Taxonomy and Epics'!$H:$H,'Taxonomy and Epics'!E:E) -> 3.0 - Q2C - Quote to Cash | K28: =_xlfn.XLOOKUP($H28,'Taxonomy and Epics'!$H:$H,'Taxonomy and Epics'!F:F) -> Q2C-040 | L28: =_xlfn.XLOOKUP($H28,'Taxonomy and Epics'!$H:$H,'Taxonomy and Epics'!G:G) -> Billing Management | M28: =_xlfn.XLOOKUP($H28,'Taxonomy and Epics'!$H:$H,'Taxonomy and Epics'!H:H) -> Q2C-040-040 | N28: =_xlfn.XLOOKUP($H28,'Taxonomy and Epics'!$H:$H,'Taxonomy and Epics'!I:I) -> Generate and Distribute Statements
A29: US021 | B29: generate a customer statement | C29: As an Accounts Receivable Officer, I want to generate and manually email a customer statement on-demand, so that customers are regularly informed of their account status. | D29: - Given I am sending customer statements to eligible customers, when I select 'Print Customer Statement', then the system produces a statement of open items. - Given the statement is generated, when I review the customer statement, then I can optionally email the statement to the customer. | E29: Accounts Receivable Officer | F29: D.47 | H29: Q2C-040-040 | I29: =_xlfn.XLOOKUP(H29,'Taxonomy and Epics'!H:H,'Taxonomy and Epics'!I:I) -> Generate and Distribute Statements | J29: =_xlfn.XLOOKUP($H29,'Taxonomy and Epics'!$H:$H,'Taxonomy and Epics'!E:E) -> 3.0 - Q2C - Quote to Cash | K29: =_xlfn.XLOOKUP($H29,'Taxonomy and Epics'!$H:$H,'Taxonomy and Epics'!F:F) -> Q2C-040 | L29: =_xlfn.XLOOKUP($H29,'Taxonomy and Epics'!$H:$H,'Taxonomy and Epics'!G:G) -> Billing Management | M29: =_xlfn.XLOOKUP($H29,'Taxonomy and Epics'!$H:$H,'Taxonomy and Epics'!H:H) -> Q2C-040-040 | N29: =_xlfn.XLOOKUP($H29,'Taxonomy and Epics'!$H:$H,'Taxonomy and Epics'!I:I) -> Generate and Distribute Statements
A30: US022 | B30: placing invoices in dispute | C30: As a Credit Officer, I want to place one or more invoices in dispute, so that they are excluded from collection activities while the issue is investigated. | D30: - Given I select one invoice and choose the 'Maintain Dispute' action, then the system displays a dispute date, dispute reason and notes. - Given I initiate the "Manage Customer Invoices" task and select one or more invoices and choose the 'Maintain Dispute' action, then the system displays a dispute date, dispute reason and note. - Given an invoice is marked 'In Dispute', then its status is clearly shown as 'Disputed' and it is excluded from the dunning process. | E30: Credit Officer | F30: 0 | H30: Q2C-050-010 | I30: =_xlfn.XLOOKUP(H30,'Taxonomy and Epics'!H:H,'Taxonomy and Epics'!I:I) -> Manage Customer Service Inquiry and Orders | J30: =_xlfn.XLOOKUP($H30,'Taxonomy and Epics'!$H:$H,'Taxonomy and Epics'!E:E) -> 3.0 - Q2C - Quote to Cash | K30: =_xlfn.XLOOKUP($H30,'Taxonomy and Epics'!$H:$H,'Taxonomy and Epics'!F:F) -> Q2C-050 | L30: =_xlfn.XLOOKUP($H30,'Taxonomy and Epics'!$H:$H,'Taxonomy and Epics'!G:G) -> Customer Inquiry and Dispute | M30: =_xlfn.XLOOKUP($H30,'Taxonomy and Epics'!$H:$H,'Taxonomy and Epics'!H:H) -> Q2C-050-010 | N30: =_xlfn.XLOOKUP($H30,'Taxonomy and Epics'!$H:$H,'Taxonomy and Epics'!I:I) -> Manage Customer Service Inquiry and Orders
A31: US023 | B31: removing invoices from dispute | C31: As a Credit Officer, I want to resolve a dispute on an invoice, so that it can be returned to the normal collections process or be credited. | D31: - Given an invoice is marked as 'In Dispute', when I mark the invoice as resolved , then its status is no longer marked as disputed. | E31: Credit Officer | F31: 0 | H31: Q2C-050-010 | I31: =_xlfn.XLOOKUP(H31,'Taxonomy and Epics'!H:H,'Taxonomy and Epics'!I:I) -> Manage Customer Service Inquiry and Orders | J31: =_xlfn.XLOOKUP($H31,'Taxonomy and Epics'!$H:$H,'Taxonomy and Epics'!E:E) -> 3.0 - Q2C - Quote to Cash | K31: =_xlfn.XLOOKUP($H31,'Taxonomy and Epics'!$H:$H,'Taxonomy and Epics'!F:F) -> Q2C-050 | L31: =_xlfn.XLOOKUP($H31,'Taxonomy and Epics'!$H:$H,'Taxonomy and Epics'!G:G) -> Customer Inquiry and Dispute | M31: =_xlfn.XLOOKUP($H31,'Taxonomy and Epics'!$H:$H,'Taxonomy and Epics'!H:H) -> Q2C-050-010 | N31: =_xlfn.XLOOKUP($H31,'Taxonomy and Epics'!$H:$H,'Taxonomy and Epics'!I:I) -> Manage Customer Service Inquiry and Orders
A32: US024 | B32: creating a credit note | C32: As an Accounts Receivable Officer, I want to create a credit note, so that I can reduce the amount a customer owes. | D32: - Given I initiate the 'Create Customer Invoice Adjustment' process, then I can either apply it to a specific invoice or create it as a standalone (on-account) credit. - Given I apply a credit note to an invoice, then the invoice's outstanding balance is reduced. | E32: Accounts Receivable Officer | F32: D.54 | H32: Q2C-050-030 | I32: =_xlfn.XLOOKUP(H32,'Taxonomy and Epics'!H:H,'Taxonomy and Epics'!I:I) -> Process Charge Backs & credit memos | J32: =_xlfn.XLOOKUP($H32,'Taxonomy and Epics'!$H:$H,'Taxonomy and Epics'!E:E) -> 3.0 - Q2C - Quote to Cash | K32: =_xlfn.XLOOKUP($H32,'Taxonomy and Epics'!$H:$H,'Taxonomy and Epics'!F:F) -> Q2C-050 | L32: =_xlfn.XLOOKUP($H32,'Taxonomy and Epics'!$H:$H,'Taxonomy and Epics'!G:G) -> Customer Inquiry and Dispute | M32: =_xlfn.XLOOKUP($H32,'Taxonomy and Epics'!$H:$H,'Taxonomy and Epics'!H:H) -> Q2C-050-030 | N32: =_xlfn.XLOOKUP($H32,'Taxonomy and Epics'!$H:$H,'Taxonomy and Epics'!I:I) -> Process Charge Backs & credit memos
A33: US025 | B33: creating a credit and rebill | C33: As an Accounts Receivable Officer, I want to correct and rebill an invoice in a single step, so that the original is cancelled and a new, correct one is created efficiently. | D33: - Given I am viewing an incorrect invoice, when I select the 'Credit and Rebill' action, then the system creates a new draft invoice with the same details for me to edit. - Given I submit the new invoice, then the system automatically creates and applies a credit note to fully offset the original incorrect invoice. | E33: Accounts Receivable Officer | F33: 0 | H33: Q2C-050-030 | I33: =_xlfn.XLOOKUP(H33,'Taxonomy and Epics'!H:H,'Taxonomy and Epics'!I:I) -> Process Charge Backs & credit memos | J33: =_xlfn.XLOOKUP($H33,'Taxonomy and Epics'!$H:$H,'Taxonomy and Epics'!E:E) -> 3.0 - Q2C - Quote to Cash | K33: =_xlfn.XLOOKUP($H33,'Taxonomy and Epics'!$H:$H,'Taxonomy and Epics'!F:F) -> Q2C-050 | L33: =_xlfn.XLOOKUP($H33,'Taxonomy and Epics'!$H:$H,'Taxonomy and Epics'!G:G) -> Customer Inquiry and Dispute | M33: =_xlfn.XLOOKUP($H33,'Taxonomy and Epics'!$H:$H,'Taxonomy and Epics'!H:H) -> Q2C-050-030 | N33: =_xlfn.XLOOKUP($H33,'Taxonomy and Epics'!$H:$H,'Taxonomy and Epics'!I:I) -> Process Charge Backs & credit memos
A34: US026 | B34: processing a refund | C34: As an Accounts Receivable Officer, I want to process a refund for a customer with an on-account credit, so that I can return their money. | D34: - Given a customer has an on-account credit, when I initiate a refund, then the system checks if a bank account is on file. - Given a bank account exists, when I process the refund, then a refund is created for settling. - Given a refund is created for settling, when a settlement run is processed, the customer receives a refund. - Given no bank account exists, when I try to process the refund, then the system prompts me to add bank details first. | E34: Accounts Receivable Officer | F34: 0 | H34: Q2C-050-030 | I34: =_xlfn.XLOOKUP(H34,'Taxonomy and Epics'!H:H,'Taxonomy and Epics'!I:I) -> Process Charge Backs & credit memos | J34: =_xlfn.XLOOKUP($H34,'Taxonomy and Epics'!$H:$H,'Taxonomy and Epics'!E:E) -> 3.0 - Q2C - Quote to Cash | K34: =_xlfn.XLOOKUP($H34,'Taxonomy and Epics'!$H:$H,'Taxonomy and Epics'!F:F) -> Q2C-050 | L34: =_xlfn.XLOOKUP($H34,'Taxonomy and Epics'!$H:$H,'Taxonomy and Epics'!G:G) -> Customer Inquiry and Dispute | M34: =_xlfn.XLOOKUP($H34,'Taxonomy and Epics'!$H:$H,'Taxonomy and Epics'!H:H) -> Q2C-050-030 | N34: =_xlfn.XLOOKUP($H34,'Taxonomy and Epics'!$H:$H,'Taxonomy and Epics'!I:I) -> Process Charge Backs & credit memos
A35: US027 | B35: updating a customers bank details | C35: As an Accounts Receivable Officer, I want to add a customer's bank account details, so that refunds can be processed. | D35: - Given I am adding a customer's bank account, when I submit the customers bank details, then the request is sent to another Accounts Receivable Officer for approval. - Given the details are approved, then the bank account becomes active and available for refunds. | E35: Accounts Receivable Officer | F35: 0 | H35: Q2C-050-030 | I35: =_xlfn.XLOOKUP(H35,'Taxonomy and Epics'!H:H,'Taxonomy and Epics'!I:I) -> Process Charge Backs & credit memos | J35: =_xlfn.XLOOKUP($H35,'Taxonomy and Epics'!$H:$H,'Taxonomy and Epics'!E:E) -> 3.0 - Q2C - Quote to Cash | K35: =_xlfn.XLOOKUP($H35,'Taxonomy and Epics'!$H:$H,'Taxonomy and Epics'!F:F) -> Q2C-050 | L35: =_xlfn.XLOOKUP($H35,'Taxonomy and Epics'!$H:$H,'Taxonomy and Epics'!G:G) -> Customer Inquiry and Dispute | M35: =_xlfn.XLOOKUP($H35,'Taxonomy and Epics'!$H:$H,'Taxonomy and Epics'!H:H) -> Q2C-050-030 | N35: =_xlfn.XLOOKUP($H35,'Taxonomy and Epics'!$H:$H,'Taxonomy and Epics'!I:I) -> Process Charge Backs & credit memos
A36: US028 | B36: automatically generating a customer payment | C36: As a Bank Reconcilation Offcer, I want the system to automatically match and apply customer payments from an imported bank statement, so that manual processing is reduced. | D36: - Given a bank statement is imported, when a payment line contains a reference matching an open invoice number (e.g., CINV00001), then the system automatically applies the payment to that invoice. - Given a payment reference does not match, then the payment will not be created and will require manual reconciliation. | E36: Bank Reconciliation Officer | F36: D.56 | H36: Q2C-060-010 | I36: =_xlfn.XLOOKUP(H36,'Taxonomy and Epics'!H:H,'Taxonomy and Epics'!I:I) -> Process Payments & Apply Receipts | J36: =_xlfn.XLOOKUP($H36,'Taxonomy and Epics'!$H:$H,'Taxonomy and Epics'!E:E) -> 3.0 - Q2C - Quote to Cash | K36: =_xlfn.XLOOKUP($H36,'Taxonomy and Epics'!$H:$H,'Taxonomy and Epics'!F:F) -> Q2C-060 | L36: =_xlfn.XLOOKUP($H36,'Taxonomy and Epics'!$H:$H,'Taxonomy and Epics'!G:G) -> Cash Applications | M36: =_xlfn.XLOOKUP($H36,'Taxonomy and Epics'!$H:$H,'Taxonomy and Epics'!H:H) -> Q2C-060-010 | N36: =_xlfn.XLOOKUP($H36,'Taxonomy and Epics'!$H:$H,'Taxonomy and Epics'!I:I) -> Process Payments & Apply Receipts
A37: US029 | B37: manually creating a customer payment | C37: As a Bank Reconciliation Officer, I want to manually create and apply a customer payment based on a bank statement line, so that I can process payments the system could not match. | D37: - Given I am viewing a bank statement, when I view a customer payment line, then I can create a customer payment and enter any available remittance advice. - Given I have created the payment, when I apply it to an open invoices, then their balance is reduced. | E37: Bank Reconciliation Officer | F37: D.56;D.44 | H37: Q2C-060-010 | I37: =_xlfn.XLOOKUP(H37,'Taxonomy and Epics'!H:H,'Taxonomy and Epics'!I:I) -> Process Payments & Apply Receipts | J37: =_xlfn.XLOOKUP($H37,'Taxonomy and Epics'!$H:$H,'Taxonomy and Epics'!E:E) -> 3.0 - Q2C - Quote to Cash | K37: =_xlfn.XLOOKUP($H37,'Taxonomy and Epics'!$H:$H,'Taxonomy and Epics'!F:F) -> Q2C-060 | L37: =_xlfn.XLOOKUP($H37,'Taxonomy and Epics'!$H:$H,'Taxonomy and Epics'!G:G) -> Cash Applications | M37: =_xlfn.XLOOKUP($H37,'Taxonomy and Epics'!$H:$H,'Taxonomy and Epics'!H:H) -> Q2C-060-010 | N37: =_xlfn.XLOOKUP($H37,'Taxonomy and Epics'!$H:$H,'Taxonomy and Epics'!I:I) -> Process Payments & Apply Receipts
A38: US030 | B38: applying a payment to account | C38: As a Bank Reconciliation Officer, I want to create and apply an unidentified payment to a customer's account, so that the cash is recorded against the customer while I investigate. | D38: - Given a payment cannot be matched to an invoice, when I process it, then I can apply it 'on account' for the identified customer, creating a credit balance on their account. | E38: Bank Reconciliation Officer | F38: D.56 | H38: Q2C-060-010 | I38: =_xlfn.XLOOKUP(H38,'Taxonomy and Epics'!H:H,'Taxonomy and Epics'!I:I) -> Process Payments & Apply Receipts | J38: =_xlfn.XLOOKUP($H38,'Taxonomy and Epics'!$H:$H,'Taxonomy and Epics'!E:E) -> 3.0 - Q2C - Quote to Cash | K38: =_xlfn.XLOOKUP($H38,'Taxonomy and Epics'!$H:$H,'Taxonomy and Epics'!F:F) -> Q2C-060 | L38: =_xlfn.XLOOKUP($H38,'Taxonomy and Epics'!$H:$H,'Taxonomy and Epics'!G:G) -> Cash Applications | M38: =_xlfn.XLOOKUP($H38,'Taxonomy and Epics'!$H:$H,'Taxonomy and Epics'!H:H) -> Q2C-060-010 | N38: =_xlfn.XLOOKUP($H38,'Taxonomy and Epics'!$H:$H,'Taxonomy and Epics'!I:I) -> Process Payments & Apply Receipts
A39: US031 | B39: automatically process small write offs | C39: As a Bank Reconciliation Officer, I want the system to automatically write off small remaining balances on invoices after payment, so that the ledger remains clean without manual effort. | D39: - Given a payment is applied to an invoice, when the remaining balance is less than $1.00, then the system automatically creates a write-off for the remaining amount. - Given the write-off is created, then the amount is posted to the designated central cost center and ledger account for small balances. | E39: Bank Reconciliation Officer | F39: 0 | H39: Q2C-060-010 | I39: =_xlfn.XLOOKUP(H39,'Taxonomy and Epics'!H:H,'Taxonomy and Epics'!I:I) -> Process Payments & Apply Receipts | J39: =_xlfn.XLOOKUP($H39,'Taxonomy and Epics'!$H:$H,'Taxonomy and Epics'!E:E) -> 3.0 - Q2C - Quote to Cash | K39: =_xlfn.XLOOKUP($H39,'Taxonomy and Epics'!$H:$H,'Taxonomy and Epics'!F:F) -> Q2C-060 | L39: =_xlfn.XLOOKUP($H39,'Taxonomy and Epics'!$H:$H,'Taxonomy and Epics'!G:G) -> Cash Applications | M39: =_xlfn.XLOOKUP($H39,'Taxonomy and Epics'!$H:$H,'Taxonomy and Epics'!H:H) -> Q2C-060-010 | N39: =_xlfn.XLOOKUP($H39,'Taxonomy and Epics'!$H:$H,'Taxonomy and Epics'!I:I) -> Process Payments & Apply Receipts
A40: US031a | B40: Manually process small write offs | C40: As a Bank Reconciliation Officer, I want to manually write off small balances on invoices at the point of creating payment, so that I can accommodate differences short payments due bank fees/ forex. | D40: - Given a customer has short-paid due to a bank fee, when I create the payment, then I can write-off the remaining balance. - Given the write-off is created, then the amount is posted to the designated cost center and ledger (P&L account) | E40: Bank Reconciliation Officer | F40: 0 | H40: Q2C-060-010 | I40: =_xlfn.XLOOKUP(H40,'Taxonomy and Epics'!H:H,'Taxonomy and Epics'!I:I) -> Process Payments & Apply Receipts | J40: =_xlfn.XLOOKUP($H40,'Taxonomy and Epics'!$H:$H,'Taxonomy and Epics'!E:E) -> 3.0 - Q2C - Quote to Cash | K40: =_xlfn.XLOOKUP($H40,'Taxonomy and Epics'!$H:$H,'Taxonomy and Epics'!F:F) -> Q2C-060 | L40: =_xlfn.XLOOKUP($H40,'Taxonomy and Epics'!$H:$H,'Taxonomy and Epics'!G:G) -> Cash Applications | M40: =_xlfn.XLOOKUP($H40,'Taxonomy and Epics'!$H:$H,'Taxonomy and Epics'!H:H) -> Q2C-060-010 | N40: =_xlfn.XLOOKUP($H40,'Taxonomy and Epics'!$H:$H,'Taxonomy and Epics'!I:I) -> Process Payments & Apply Receipts
A41: US032 | B41: correcting misapplied payments | C41: As a Bank Reconciliation Officer, I want to correct a misapplied payment, so that customer accounts are accurate. | D41: - Given a payment is incorrectly applied, when I view the payment, then I can 'Unapply' it, which restores the original invoice's balance. - Given the payment is unapplied, then I can re-apply it to the correct invoice. | E41: Bank Reconciliation Officer | F41: D.56 | H41: Q2C-060-020 | I41: =_xlfn.XLOOKUP(H41,'Taxonomy and Epics'!H:H,'Taxonomy and Epics'!I:I) -> Reconcile Unapplied, Misapplied, and Unidentified Payments | J41: =_xlfn.XLOOKUP($H41,'Taxonomy and Epics'!$H:$H,'Taxonomy and Epics'!E:E) -> 3.0 - Q2C - Quote to Cash | K41: =_xlfn.XLOOKUP($H41,'Taxonomy and Epics'!$H:$H,'Taxonomy and Epics'!F:F) -> Q2C-060 | L41: =_xlfn.XLOOKUP($H41,'Taxonomy and Epics'!$H:$H,'Taxonomy and Epics'!G:G) -> Cash Applications | M41: =_xlfn.XLOOKUP($H41,'Taxonomy and Epics'!$H:$H,'Taxonomy and Epics'!H:H) -> Q2C-060-020 | N41: =_xlfn.XLOOKUP($H41,'Taxonomy and Epics'!$H:$H,'Taxonomy and Epics'!I:I) -> Reconcile Unapplied, Misapplied, and Unidentified Payments
A42: US033 | B42: adding remittance advice to a processed payment | C42: As a Bank Reconciliation Officer, I want to add remittance information to an on-account payment, so that the system can then automatically match it to the correct invoice. | D42: - Given a payment is on a customer's account, when I edit the payment, then I can add or update the remittance advice with invoice numbers. - Given I have updated the remittance, when I run the 'Auto Apply Customer Payments' process, then the system uses the new information to match and apply the payment. | E42: Bank Reconciliation Officer | F42: D.56 | H42: Q2C-060-020 | I42: =_xlfn.XLOOKUP(H42,'Taxonomy and Epics'!H:H,'Taxonomy and Epics'!I:I) -> Reconcile Unapplied, Misapplied, and Unidentified Payments | J42: =_xlfn.XLOOKUP($H42,'Taxonomy and Epics'!$H:$H,'Taxonomy and Epics'!E:E) -> 3.0 - Q2C - Quote to Cash | K42: =_xlfn.XLOOKUP($H42,'Taxonomy and Epics'!$H:$H,'Taxonomy and Epics'!F:F) -> Q2C-060 | L42: =_xlfn.XLOOKUP($H42,'Taxonomy and Epics'!$H:$H,'Taxonomy and Epics'!G:G) -> Cash Applications | M42: =_xlfn.XLOOKUP($H42,'Taxonomy and Epics'!$H:$H,'Taxonomy and Epics'!H:H) -> Q2C-060-020 | N42: =_xlfn.XLOOKUP($H42,'Taxonomy and Epics'!$H:$H,'Taxonomy and Epics'!I:I) -> Reconcile Unapplied, Misapplied, and Unidentified Payments
A43: US034 | B43: running a receivables aging report | C43: As a Credit Officer, I want to run a receivables aging report, so that I can identify overdue invoices and prioritise collection activities. | D43: - Given I run the aging report, then it displays customers with outstanding balances categorised into aging buckets (e.g., 30, 60, 90+ days). | E43: Credit Officer | F43: D.51;D.52;D.65 | H43: Q2C-070-020 | I43: =_xlfn.XLOOKUP(H43,'Taxonomy and Epics'!H:H,'Taxonomy and Epics'!I:I) -> Perform Collection Activity | J43: =_xlfn.XLOOKUP($H43,'Taxonomy and Epics'!$H:$H,'Taxonomy and Epics'!E:E) -> 3.0 - Q2C - Quote to Cash | K43: =_xlfn.XLOOKUP($H43,'Taxonomy and Epics'!$H:$H,'Taxonomy and Epics'!F:F) -> Q2C-070 | L43: =_xlfn.XLOOKUP($H43,'Taxonomy and Epics'!$H:$H,'Taxonomy and Epics'!G:G) -> Collections Management | M43: =_xlfn.XLOOKUP($H43,'Taxonomy and Epics'!$H:$H,'Taxonomy and Epics'!H:H) -> Q2C-070-020 | N43: =_xlfn.XLOOKUP($H43,'Taxonomy and Epics'!$H:$H,'Taxonomy and Epics'!I:I) -> Perform Collection Activity
A44: US035 | B44: mark an invoice as in collection | C44: As a Credit Officer, I want to mark an invoice as 'In Collection', so that I can track my collection activities and the invoice's status. | D44: - Given I have identified an overdue invoice, when I select the 'Maintain Collection' action, then the system allows me to enter collection date, reason and notes, and the invoice status is updated to 'In Collection'. | E44: Credit Officer | F44: 0 | H44: Q2C-070-020 | I44: =_xlfn.XLOOKUP(H44,'Taxonomy and Epics'!H:H,'Taxonomy and Epics'!I:I) -> Perform Collection Activity | J44: =_xlfn.XLOOKUP($H44,'Taxonomy and Epics'!$H:$H,'Taxonomy and Epics'!E:E) -> 3.0 - Q2C - Quote to Cash | K44: =_xlfn.XLOOKUP($H44,'Taxonomy and Epics'!$H:$H,'Taxonomy and Epics'!F:F) -> Q2C-070 | L44: =_xlfn.XLOOKUP($H44,'Taxonomy and Epics'!$H:$H,'Taxonomy and Epics'!G:G) -> Collections Management | M44: =_xlfn.XLOOKUP($H44,'Taxonomy and Epics'!$H:$H,'Taxonomy and Epics'!H:H) -> Q2C-070-020 | N44: =_xlfn.XLOOKUP($H44,'Taxonomy and Epics'!$H:$H,'Taxonomy and Epics'!I:I) -> Perform Collection Activity
A45: US036 | B45: emailing dunning letters | C45: As a Credit Officer, I want the system to generate and email the correct dunning letter to a customer, so that I can automate the reminder process. | D45: - Given an invoice is overdue, when the system automatically prints a dunning letter, then the system selects the correct letter template (Level 1, 2, or 3) based on the invoice's age. - Given the customer has an email on file, then the system emails the letter. | E45: Credit Officer | F45: D.57 | H45: Q2C-070-020 | I45: =_xlfn.XLOOKUP(H45,'Taxonomy and Epics'!H:H,'Taxonomy and Epics'!I:I) -> Perform Collection Activity | J45: =_xlfn.XLOOKUP($H45,'Taxonomy and Epics'!$H:$H,'Taxonomy and Epics'!E:E) -> 3.0 - Q2C - Quote to Cash | K45: =_xlfn.XLOOKUP($H45,'Taxonomy and Epics'!$H:$H,'Taxonomy and Epics'!F:F) -> Q2C-070 | L45: =_xlfn.XLOOKUP($H45,'Taxonomy and Epics'!$H:$H,'Taxonomy and Epics'!G:G) -> Collections Management | M45: =_xlfn.XLOOKUP($H45,'Taxonomy and Epics'!$H:$H,'Taxonomy and Epics'!H:H) -> Q2C-070-020 | N45: =_xlfn.XLOOKUP($H45,'Taxonomy and Epics'!$H:$H,'Taxonomy and Epics'!I:I) -> Perform Collection Activity
A46: US037 | B46: putting a customer on hold | C46: As a Credit Officer, I want to request a customer be put on credit hold due to poor payment history, so that we can prevent further risk. | D46: - Given I am a Credit Officer, when I initiate the 'Place on Hold' action for a customer, then the request is routed to an Accounts Receivable Officer for approval. - Given the request is approved, then the customer's status is changed to 'On Hold'. | E46: Credit Officer | F46: 0 | H46: Q2C-070-030 | I46: =_xlfn.XLOOKUP(H46,'Taxonomy and Epics'!H:H,'Taxonomy and Epics'!I:I) -> Perform Escalation & Follow-up | J46: =_xlfn.XLOOKUP($H46,'Taxonomy and Epics'!$H:$H,'Taxonomy and Epics'!E:E) -> 3.0 - Q2C - Quote to Cash | K46: =_xlfn.XLOOKUP($H46,'Taxonomy and Epics'!$H:$H,'Taxonomy and Epics'!F:F) -> Q2C-070 | L46: =_xlfn.XLOOKUP($H46,'Taxonomy and Epics'!$H:$H,'Taxonomy and Epics'!G:G) -> Collections Management | M46: =_xlfn.XLOOKUP($H46,'Taxonomy and Epics'!$H:$H,'Taxonomy and Epics'!H:H) -> Q2C-070-030 | N46: =_xlfn.XLOOKUP($H46,'Taxonomy and Epics'!$H:$H,'Taxonomy and Epics'!I:I) -> Perform Escalation & Follow-up
A47: US038 | B47: processing invoice write offs | C47: As a Credit Officer, I want to process an invoice write-off, so that bad debt can be correctly accounted for. | D47: - Given I have a valid request to write off an invoice, when I initiate the 'Write Off Customer Invoice' process, then the request is routed to the Accounts Receivable Team Lead for approval. - Given the Team Lead approves the write-off, then the invoice balance becomes zero and its status is | E47: Credit Officer | F47: 0 | H47: Q2C-070-030 | I47: =_xlfn.XLOOKUP(H47,'Taxonomy and Epics'!H:H,'Taxonomy and Epics'!I:I) -> Perform Escalation & Follow-up | J47: =_xlfn.XLOOKUP($H47,'Taxonomy and Epics'!$H:$H,'Taxonomy and Epics'!E:E) -> 3.0 - Q2C - Quote to Cash | K47: =_xlfn.XLOOKUP($H47,'Taxonomy and Epics'!$H:$H,'Taxonomy and Epics'!F:F) -> Q2C-070 | L47: =_xlfn.XLOOKUP($H47,'Taxonomy and Epics'!$H:$H,'Taxonomy and Epics'!G:G) -> Collections Management | M47: =_xlfn.XLOOKUP($H47,'Taxonomy and Epics'!$H:$H,'Taxonomy and Epics'!H:H) -> Q2C-070-030 | N47: =_xlfn.XLOOKUP($H47,'Taxonomy and Epics'!$H:$H,'Taxonomy and Epics'!I:I) -> Perform Escalation & Follow-up
A48: US039 | B48: Validations on Customer Invoices | C48: As a Accounts Receivable Officer I want to be alerted to key conditions during invoicing (credit limit exceedance, mail delivery flag, no document delivery flag or non-todays invoice date) so that I can take appropriate action before the invoice is issued or sent. | D48: 1. Given a customer invoice is being prepared, when the customer’s credit limit is exceeded, then the system shows a warning. 2. Given the customer is set to mail delivery, when the invoice is generated, then the system shows a warning about mail delivery. 3. Given the invoice date is not today's date, when preparing the invoice, then the system shows a warning. | E48: Accounts Receivable Officer | F48: 0 | G48: REQ002 | H48: Q2C-040-020 | I48: =_xlfn.XLOOKUP(H48,'Taxonomy and Epics'!H:H,'Taxonomy and Epics'!I:I) -> Generate, Review & Approve Invoice | J48: =_xlfn.XLOOKUP($H48,'Taxonomy and Epics'!$H:$H,'Taxonomy and Epics'!E:E) -> 3.0 - Q2C - Quote to Cash | K48: =_xlfn.XLOOKUP($H48,'Taxonomy and Epics'!$H:$H,'Taxonomy and Epics'!F:F) -> Q2C-040 | L48: =_xlfn.XLOOKUP($H48,'Taxonomy and Epics'!$H:$H,'Taxonomy and Epics'!G:G) -> Billing Management | M48: =_xlfn.XLOOKUP($H48,'Taxonomy and Epics'!$H:$H,'Taxonomy and Epics'!H:H) -> Q2C-040-020 | N48: =_xlfn.XLOOKUP($H48,'Taxonomy and Epics'!$H:$H,'Taxonomy and Epics'!I:I) -> Generate, Review & Approve Invoice
A49: US040 | B49: Sponsorship invoice | C49: As a Accounts Receivable Officer I want to process a student sponsorship invoice so that income from student placements by a third party is captured correctly as a sponsorship scenario. | D49: - Given I am an accounts receivable officer, when I create an invoice to capture student placements by a third party, then the system posts to the correct sponsorship income account | E49: Accounts Receivable Officer | F49: 0 | G49: REQ003 | H49: Q2C-040-020 | I49: =_xlfn.XLOOKUP(H49,'Taxonomy and Epics'!H:H,'Taxonomy and Epics'!I:I) -> Generate, Review & Approve Invoice | J49: =_xlfn.XLOOKUP($H49,'Taxonomy and Epics'!$H:$H,'Taxonomy and Epics'!E:E) -> 3.0 - Q2C - Quote to Cash | K49: =_xlfn.XLOOKUP($H49,'Taxonomy and Epics'!$H:$H,'Taxonomy and Epics'!F:F) -> Q2C-040 | L49: =_xlfn.XLOOKUP($H49,'Taxonomy and Epics'!$H:$H,'Taxonomy and Epics'!G:G) -> Billing Management | M49: =_xlfn.XLOOKUP($H49,'Taxonomy and Epics'!$H:$H,'Taxonomy and Epics'!H:H) -> Q2C-040-020 | N49: =_xlfn.XLOOKUP($H49,'Taxonomy and Epics'!$H:$H,'Taxonomy and Epics'!I:I) -> Generate, Review & Approve Invoice
A50: US041 | B50: Automated generation of invoices from billing schedule | C50: As an Accounts Receivable Officer, I want invoices to be automatically generated based on a customer contract’s billing schedule for rental contracts in the correct invoice format. | D50: 1. Given a rental contract with a defined billing schedule, when due dates arrive, then the system automatically generates invoices without manual intervention. 2. Given the rental invoices require a different printed layout, when the invoice is generated, then it is produced using the alternate layout configured for rental invoices. | E50: Accounts Receivable Officer | F50: 0 | G50: REQ004 | H50: Q2C-040-020 | I50: =_xlfn.XLOOKUP(H50,'Taxonomy and Epics'!H:H,'Taxonomy and Epics'!I:I) -> Generate, Review & Approve Invoice | J50: =_xlfn.XLOOKUP($H50,'Taxonomy and Epics'!$H:$H,'Taxonomy and Epics'!E:E) -> 3.0 - Q2C - Quote to Cash | K50: =_xlfn.XLOOKUP($H50,'Taxonomy and Epics'!$H:$H,'Taxonomy and Epics'!F:F) -> Q2C-040 | L50: =_xlfn.XLOOKUP($H50,'Taxonomy and Epics'!$H:$H,'Taxonomy and Epics'!G:G) -> Billing Management | M50: =_xlfn.XLOOKUP($H50,'Taxonomy and Epics'!$H:$H,'Taxonomy and Epics'!H:H) -> Q2C-040-020 | N50: =_xlfn.XLOOKUP($H50,'Taxonomy and Epics'!$H:$H,'Taxonomy and Epics'!I:I) -> Generate, Review & Approve Invoice
A51: US042 | B51: Create Donations invoice | C51: As an Accounts Receivable Officer I want to process a philanthropic invoice so that income from donations are captured correctly. | D51: - Given I am an accounts receivable officer, when I create a 'donation' invoice, then the system does not automatically trigger the print and email customer invoice events - Given I generated an invoice with the 'Donations' invoice type, when I print the invoice, then the invoice PDF contains the bank details for the donations bank account | E51: Accounts Receivable Officer | F51: 0 | G51: REQ003 | H51: Q2C-040-020 | I51: =_xlfn.XLOOKUP(H51,'Taxonomy and Epics'!H:H,'Taxonomy and Epics'!I:I) -> Generate, Review & Approve Invoice | J51: =_xlfn.XLOOKUP($H51,'Taxonomy and Epics'!$H:$H,'Taxonomy and Epics'!E:E) -> 3.0 - Q2C - Quote to Cash | K51: =_xlfn.XLOOKUP($H51,'Taxonomy and Epics'!$H:$H,'Taxonomy and Epics'!F:F) -> Q2C-040 | L51: =_xlfn.XLOOKUP($H51,'Taxonomy and Epics'!$H:$H,'Taxonomy and Epics'!G:G) -> Billing Management | M51: =_xlfn.XLOOKUP($H51,'Taxonomy and Epics'!$H:$H,'Taxonomy and Epics'!H:H) -> Q2C-040-020 | N51: =_xlfn.XLOOKUP($H51,'Taxonomy and Epics'!$H:$H,'Taxonomy and Epics'!I:I) -> Generate, Review & Approve Invoice
A52: US043 | B52: Create customer invoice en-masse via bulk upload | C52: As an Accounts Receivable Officer I want to submit a flat file (excel) upload so I can create multiple invoices en masse. | D52: 1. Given I am an Accounts Receivable Officer and I have populated an EIB with customer invoice information for multiple invoices, when the EIB is launched/ submitted, then multiple invoices are created in Workday. | E52: Accounts Receivable Officer | F52: 0 | H52: Q2C-050-030 | I52: =_xlfn.XLOOKUP(H52,'Taxonomy and Epics'!H:H,'Taxonomy and Epics'!I:I) -> Process Charge Backs & credit memos | J52: =_xlfn.XLOOKUP($H52,'Taxonomy and Epics'!$H:$H,'Taxonomy and Epics'!E:E) -> 3.0 - Q2C - Quote to Cash | K52: =_xlfn.XLOOKUP($H52,'Taxonomy and Epics'!$H:$H,'Taxonomy and Epics'!F:F) -> Q2C-050 | L52: =_xlfn.XLOOKUP($H52,'Taxonomy and Epics'!$H:$H,'Taxonomy and Epics'!G:G) -> Customer Inquiry and Dispute | M52: =_xlfn.XLOOKUP($H52,'Taxonomy and Epics'!$H:$H,'Taxonomy and Epics'!H:H) -> Q2C-050-030 | N52: =_xlfn.XLOOKUP($H52,'Taxonomy and Epics'!$H:$H,'Taxonomy and Epics'!I:I) -> Process Charge Backs & credit memos
A53: US044 | B53: Adding notes to Customer record | C53: As an Accounts Receivable Officer I want to be able to capture customer feedback, reporting and insights as notes against the customer record | D53: 1. Given I am an Accounts Receivable Officer I am able to add notes to the customer record to capture any required information including recording feedback, reporting or insights. | F53: D.68 | H53: Q2C-010-030 | I53: =_xlfn.XLOOKUP(H53,'Taxonomy and Epics'!H:H,'Taxonomy and Epics'!I:I) -> Setup Customer Financial Master Data | J53: =_xlfn.XLOOKUP($H53,'Taxonomy and Epics'!$H:$H,'Taxonomy and Epics'!E:E) -> 3.0 - Q2C - Quote to Cash | K53: =_xlfn.XLOOKUP($H53,'Taxonomy and Epics'!$H:$H,'Taxonomy and Epics'!F:F) -> Q2C-010 | L53: =_xlfn.XLOOKUP($H53,'Taxonomy and Epics'!$H:$H,'Taxonomy and Epics'!G:G) -> Setup Customer & Credit | M53: =_xlfn.XLOOKUP($H53,'Taxonomy and Epics'!$H:$H,'Taxonomy and Epics'!H:H) -> Q2C-010-030 | N53: =_xlfn.XLOOKUP($H53,'Taxonomy and Epics'!$H:$H,'Taxonomy and Epics'!I:I) -> Setup Customer Financial Master Data
A54: US045 | B54: Ability automate the calculation and posting of bad debt provisional journal | C54: As a Revenue Accountant I want to be able to automatically calculate and generate a bad debt provision journal. | D54: 1. I want to utilise the 'Customer Invoice Bad Debt Provision Boomerang' boomerang integration to generate a provisional bad debt journal. 2. The provisional journal should calculate and provisionally write off 2.26% of all customer invoices that are overdue by 120 days or longer. | F54: D.64 | H54: Q2C-080-020 | I54: =_xlfn.XLOOKUP(H54,'Taxonomy and Epics'!H:H,'Taxonomy and Epics'!I:I) -> Close AR Sub Ledger and Reconcile with GL | J54: =_xlfn.XLOOKUP($H54,'Taxonomy and Epics'!$H:$H,'Taxonomy and Epics'!E:E) -> 3.0 - Q2C - Quote to Cash | K54: =_xlfn.XLOOKUP($H54,'Taxonomy and Epics'!$H:$H,'Taxonomy and Epics'!F:F) -> Q2C-080 | L54: =_xlfn.XLOOKUP($H54,'Taxonomy and Epics'!$H:$H,'Taxonomy and Epics'!G:G) -> Period End Close | M54: =_xlfn.XLOOKUP($H54,'Taxonomy and Epics'!$H:$H,'Taxonomy and Epics'!H:H) -> Q2C-080-020 | N54: =_xlfn.XLOOKUP($H54,'Taxonomy and Epics'!$H:$H,'Taxonomy and Epics'!I:I) -> Close AR Sub Ledger and Reconcile with GL
A55: US046 | B55: Ability to create Credit Card Customer Refunds | C55: As an Accounts Receivable Officer, I want to process a refund for a customer with an on-account credit, so that I can return their money. | D55: - Given a customer has an on-account credit, or an invoice adjustment available, when I initiate a refund - Given the payment type is Credit Card on the customer refund is 'Credit Card', no bank account is required on the customer to process the refund - The customer refund will go to the Accounts Receivable Manager for approval. Pending approval, a To Do message is sent to the Accounts Receivable manager to process the refund on the NAB portal. | E55: Accounts Receivable Officer | F55: 0 | H55: Q2C-050-030 | I55: =_xlfn.XLOOKUP(H55,'Taxonomy and Epics'!H:H,'Taxonomy and Epics'!I:I) -> Process Charge Backs & credit memos | J55: =_xlfn.XLOOKUP($H55,'Taxonomy and Epics'!$H:$H,'Taxonomy and Epics'!E:E) -> 3.0 - Q2C - Quote to Cash | K55: =_xlfn.XLOOKUP($H55,'Taxonomy and Epics'!$H:$H,'Taxonomy and Epics'!F:F) -> Q2C-050 | L55: =_xlfn.XLOOKUP($H55,'Taxonomy and Epics'!$H:$H,'Taxonomy and Epics'!G:G) -> Customer Inquiry and Dispute | M55: =_xlfn.XLOOKUP($H55,'Taxonomy and Epics'!$H:$H,'Taxonomy and Epics'!H:H) -> Q2C-050-030 | N55: =_xlfn.XLOOKUP($H55,'Taxonomy and Epics'!$H:$H,'Taxonomy and Epics'!I:I) -> Process Charge Backs & credit memos
A56: US-A2R-001 | B56: As a Fixed Asset Accountant, I want an asset to be automatically created from a supplier invoice that meets our capitalisation rules, so that assets are recorded accurately and efficiently. | C56: As a Fixed Asset Accountant, after asset creation review, I want an asset to be automatically created from a supplier invoice that meets our capitalisation rules, so that assets are recorded accurately and efficiently. | D56: 1. Given a supplier invoice contains only items from an expense spend category, when the invoice is processed, then no asset record is created 2. Given a supplier invoice contains only items from an asset spend category, when the invoice is processed, then no asset record is created 3. Given an asset is being created from an invoice, when the system processes the invoice, then a confirmation task is sent to my inbox to review the asset details. 4. Given I have received the task to review the spend is for an asset, when i click confirm then an asset record is automatically created 5. Given I am reviewing the asset creation task, when I open the asset record, then it must contain a description and a location | E56: Fixed Asset Accountant | F56: D.224 | G56: A2R0001 | H56: A2R-020-010 | I56: =_xlfn.XLOOKUP(H56,'Taxonomy and Epics'!H:H,'Taxonomy and Epics'!I:I) -> Create Book/Tax Asset Record & Components | J56: =_xlfn.XLOOKUP($H56,'Taxonomy and Epics'!$H:$H,'Taxonomy and Epics'!E:E) -> 6.0 - A2R - Acquire to Retire | K56: =_xlfn.XLOOKUP($H56,'Taxonomy and Epics'!$H:$H,'Taxonomy and Epics'!F:F) -> A2R-020 | L56: =_xlfn.XLOOKUP($H56,'Taxonomy and Epics'!$H:$H,'Taxonomy and Epics'!G:G) -> Asset Creation | M56: =_xlfn.XLOOKUP($H56,'Taxonomy and Epics'!$H:$H,'Taxonomy and Epics'!H:H) -> A2R-020-010 | N56: =_xlfn.XLOOKUP($H56,'Taxonomy and Epics'!$H:$H,'Taxonomy and Epics'!I:I) -> Create Book/Tax Asset Record & Components
A57: US-A2R-002 | B57: As a Fixed Asset Accountant, I want an asset to be automatically created when goods are receipted against a purchase order for a capital item, so that assets are recorded promptly even before an invoice arrives | C57: As a Fixed Asset Accountant, after asset creation review, I want an asset to be automatically created when goods are receipted against a purchase order for a capital item, so that assets are recorded promptly even before an invoice arrives | D57: 1. Given goods for a capital item are receipted before the supplier invoice is received, when the goods receipt is completed, then an asset record is automatically created 2. Given a goods receipt is for an item in a capital spend category, when the receipt is processed, then an asset record is created 3. Given a goods receipt is for an item in an expense spend category, when the receipt is processed, then no asset record is created 4. Given an asset is being created from a goods receipt, when the system processes the receipt, then a confirmation task is sent to my inbox to review the asset details. | E57: Fixed Asset Accountant | G57: A2R0002 | H57: A2R-020-010 | I57: =_xlfn.XLOOKUP(H57,'Taxonomy and Epics'!H:H,'Taxonomy and Epics'!I:I) -> Create Book/Tax Asset Record & Components | J57: =_xlfn.XLOOKUP($H57,'Taxonomy and Epics'!$H:$H,'Taxonomy and Epics'!E:E) -> 6.0 - A2R - Acquire to Retire | K57: =_xlfn.XLOOKUP($H57,'Taxonomy and Epics'!$H:$H,'Taxonomy and Epics'!F:F) -> A2R-020 | L57: =_xlfn.XLOOKUP($H57,'Taxonomy and Epics'!$H:$H,'Taxonomy and Epics'!G:G) -> Asset Creation | M57: =_xlfn.XLOOKUP($H57,'Taxonomy and Epics'!$H:$H,'Taxonomy and Epics'!H:H) -> A2R-020-010 | N57: =_xlfn.XLOOKUP($H57,'Taxonomy and Epics'!$H:$H,'Taxonomy and Epics'!I:I) -> Create Book/Tax Asset Record & Components
A58: US-A2R-003 | B58: As a Fixed Asset Accountant, I want certain assets to be created from a receipt but not be placed in service immediately, so that I can track them before they are actively being used and depreciated. | C58: As a Fixed Asset Accountant, I want certain assets to be created from a receipt but not be placed in service immediately, so that I can track them before they are actively being used and depreciated. | D58: 1. Given a receipt is processed for an item in a specific spend category (e.g., Laptops), when the receipt is approved, then an asset record is created with a status of 'Registered' 2. Given an asset is created with a 'Registered' status, when I review the asset, then depreciation should not have started. | E58: Fixed Asset Accountant | G58: A2R0003 | H58: A2R-020-010 | I58: =_xlfn.XLOOKUP(H58,'Taxonomy and Epics'!H:H,'Taxonomy and Epics'!I:I) -> Create Book/Tax Asset Record & Components | J58: =_xlfn.XLOOKUP($H58,'Taxonomy and Epics'!$H:$H,'Taxonomy and Epics'!E:E) -> 6.0 - A2R - Acquire to Retire | K58: =_xlfn.XLOOKUP($H58,'Taxonomy and Epics'!$H:$H,'Taxonomy and Epics'!F:F) -> A2R-020 | L58: =_xlfn.XLOOKUP($H58,'Taxonomy and Epics'!$H:$H,'Taxonomy and Epics'!G:G) -> Asset Creation | M58: =_xlfn.XLOOKUP($H58,'Taxonomy and Epics'!$H:$H,'Taxonomy and Epics'!H:H) -> A2R-020-010 | N58: =_xlfn.XLOOKUP($H58,'Taxonomy and Epics'!$H:$H,'Taxonomy and Epics'!I:I) -> Create Book/Tax Asset Record & Components
A59: US-A2R-004 | B59: As a Fixed Asset Accountant, I want to review the details of an asset created from a completed capital project, so that I can verify its accuracy and ensure it has been correctly transferred from 'Work in Progress' (WIP). | C59: As a Fixed Asset Accountant, I want to review the details of an asset created from a completed capital project, so that I can verify its accuracy and ensure it has been correctly transferred from 'Work in Progress' (WIP). | D59: 1. Given a capital project has been completed and its costs capitalised, when the project closes, then a corresponding asset record is created 2. Given an asset has been created from a capital project, when I search for and open the asset, then I can view all its details, including cost and in-service date. 3. given an asset has been created from a capital project, when i view the accounting then there should be no value remaning in WIP | E59: Fixed Asset Accountant | F59: D.231 | G59: A2R0004 | H59: A2R-020-010 | I59: =_xlfn.XLOOKUP(H59,'Taxonomy and Epics'!H:H,'Taxonomy and Epics'!I:I) -> Create Book/Tax Asset Record & Components | J59: =_xlfn.XLOOKUP($H59,'Taxonomy and Epics'!$H:$H,'Taxonomy and Epics'!E:E) -> 6.0 - A2R - Acquire to Retire | K59: =_xlfn.XLOOKUP($H59,'Taxonomy and Epics'!$H:$H,'Taxonomy and Epics'!F:F) -> A2R-020 | L59: =_xlfn.XLOOKUP($H59,'Taxonomy and Epics'!$H:$H,'Taxonomy and Epics'!G:G) -> Asset Creation | M59: =_xlfn.XLOOKUP($H59,'Taxonomy and Epics'!$H:$H,'Taxonomy and Epics'!H:H) -> A2R-020-010 | N59: =_xlfn.XLOOKUP($H59,'Taxonomy and Epics'!$H:$H,'Taxonomy and Epics'!I:I) -> Create Book/Tax Asset Record & Components
A60: US-A2R-005 | B60: As a Fixed Asset Accountant, I want to manually register a donated asset, so that we can accurately track non-purchased, in-kind contributions. | C60: As a Fixed Asset Accountant, I want to manually register a donated asset, so that we can accurately track non-purchased, in-kind contributions. | D60: 1. Given I need to register a donated asset, when I use the manual asset registration process, then I can flag the asset as 'In-Kind' 2. Given I am registering an in-kind asset, when I save the record, then I must be warned if i do not associate it with a 'gift' worktag for financial tracking 3. Given an in-kind asset has been registered, when the process is complete, then a task is created for to assign accounting information | E60: Fixed Asset Accountant | F60: D.228 | G60: A2R0005 | H60: A2R-020-010 | I60: =_xlfn.XLOOKUP(H60,'Taxonomy and Epics'!H:H,'Taxonomy and Epics'!I:I) -> Create Book/Tax Asset Record & Components | J60: =_xlfn.XLOOKUP($H60,'Taxonomy and Epics'!$H:$H,'Taxonomy and Epics'!E:E) -> 6.0 - A2R - Acquire to Retire | K60: =_xlfn.XLOOKUP($H60,'Taxonomy and Epics'!$H:$H,'Taxonomy and Epics'!F:F) -> A2R-020 | L60: =_xlfn.XLOOKUP($H60,'Taxonomy and Epics'!$H:$H,'Taxonomy and Epics'!G:G) -> Asset Creation | M60: =_xlfn.XLOOKUP($H60,'Taxonomy and Epics'!$H:$H,'Taxonomy and Epics'!H:H) -> A2R-020-010 | N60: =_xlfn.XLOOKUP($H60,'Taxonomy and Epics'!$H:$H,'Taxonomy and Epics'!I:I) -> Create Book/Tax Asset Record & Components
A61: US-A2R-006 | B61: As a Fixed Asset Accountant, I want to remove an asset that was manually registered by mistake, so that I can correct errors and maintain an accurate asset register. | C61: As a Fixed Asset Accountant, I want to remove an asset that was manually registered by mistake, so that I can correct errors and maintain an accurate asset register. | D61: 1. Given an asset was registered manually in error, when I initiate the removal process, then the asset record is reversed or deleted 2. Given the removal of a manually registered asset is processed, when the process is complete, then the asset status is updated to reflect its removal | E61: Fixed Asset Accountant | G61: A2R0006 | H61: A2R-020-010 | I61: =_xlfn.XLOOKUP(H61,'Taxonomy and Epics'!H:H,'Taxonomy and Epics'!I:I) -> Create Book/Tax Asset Record & Components | J61: =_xlfn.XLOOKUP($H61,'Taxonomy and Epics'!$H:$H,'Taxonomy and Epics'!E:E) -> 6.0 - A2R - Acquire to Retire | K61: =_xlfn.XLOOKUP($H61,'Taxonomy and Epics'!$H:$H,'Taxonomy and Epics'!F:F) -> A2R-020 | L61: =_xlfn.XLOOKUP($H61,'Taxonomy and Epics'!$H:$H,'Taxonomy and Epics'!G:G) -> Asset Creation | M61: =_xlfn.XLOOKUP($H61,'Taxonomy and Epics'!$H:$H,'Taxonomy and Epics'!H:H) -> A2R-020-010 | N61: =_xlfn.XLOOKUP($H61,'Taxonomy and Epics'!$H:$H,'Taxonomy and Epics'!I:I) -> Create Book/Tax Asset Record & Components
A62: US-A2R-007 | B62: As an Asset Control Officer, I want to manually register an asset in exceptional circumstances, so that we can account for assets acquired outside of the standard procurement process. | C62: As an Asset Control Officer, I want to manually register an asset in exceptional circumstances, so that we can account for assets acquired outside of the standard procurement process. | D62: 1. Given I need to register an asset manually, when I submit the asset details, then the request is sent to the Fixed Asset Accountant | E62: Asset Control Officer | F62: D.228;D.233 | G62: A2R0007 | H62: A2R-020-010 | I62: =_xlfn.XLOOKUP(H62,'Taxonomy and Epics'!H:H,'Taxonomy and Epics'!I:I) -> Create Book/Tax Asset Record & Components | J62: =_xlfn.XLOOKUP($H62,'Taxonomy and Epics'!$H:$H,'Taxonomy and Epics'!E:E) -> 6.0 - A2R - Acquire to Retire | K62: =_xlfn.XLOOKUP($H62,'Taxonomy and Epics'!$H:$H,'Taxonomy and Epics'!F:F) -> A2R-020 | L62: =_xlfn.XLOOKUP($H62,'Taxonomy and Epics'!$H:$H,'Taxonomy and Epics'!G:G) -> Asset Creation | M62: =_xlfn.XLOOKUP($H62,'Taxonomy and Epics'!$H:$H,'Taxonomy and Epics'!H:H) -> A2R-020-010 | N62: =_xlfn.XLOOKUP($H62,'Taxonomy and Epics'!$H:$H,'Taxonomy and Epics'!I:I) -> Create Book/Tax Asset Record & Components
A63: US-A2R-008 | B63: As an Asset Control Officer, I want to request the removal of an asset that was manually registered by mistake, so that I can correct errors subject to financial review | C63: As an Asset Control Officer, I want to request the removal of an asset that was manually registered by mistake, so that I can correct errors subject to financial review | D63: 1. Given an asset was registered manually in error, when I initiate the removal process, then the request is sent to the Fixed Asset Accountant for approval 2. Given the Fixed Asset Accountant approves the removal, when the process is complete, then the asset record and its associated accounting are reversed 3. Given the Fixed Asset Accountant denies the removal request, when the request is denied, then I receive a notification informing me of the denial | E63: Asset Control Officer | G63: A2R0008 | H63: A2R-020-010 | I63: =_xlfn.XLOOKUP(H63,'Taxonomy and Epics'!H:H,'Taxonomy and Epics'!I:I) -> Create Book/Tax Asset Record & Components | J63: =_xlfn.XLOOKUP($H63,'Taxonomy and Epics'!$H:$H,'Taxonomy and Epics'!E:E) -> 6.0 - A2R - Acquire to Retire | K63: =_xlfn.XLOOKUP($H63,'Taxonomy and Epics'!$H:$H,'Taxonomy and Epics'!F:F) -> A2R-020 | L63: =_xlfn.XLOOKUP($H63,'Taxonomy and Epics'!$H:$H,'Taxonomy and Epics'!G:G) -> Asset Creation | M63: =_xlfn.XLOOKUP($H63,'Taxonomy and Epics'!$H:$H,'Taxonomy and Epics'!H:H) -> A2R-020-010 | N63: =_xlfn.XLOOKUP($H63,'Taxonomy and Epics'!$H:$H,'Taxonomy and Epics'!I:I) -> Create Book/Tax Asset Record & Components
A64: US-A2R-009 | B64: As a Fixed Asset Accountant, I want to split the cost and depreciation of a single asset across multiple cost centres, so that costs are allocated accurately to the faculties/divisions that use the asset | C64: As a Fixed Asset Accountant, I want to split the cost and depreciation of a single asset across multiple cost centres, so that costs are allocated accurately to the faculties/divisions that use the asset | D64: 1. Given an asset is currently assigned to a single cost centre, when I initiate a cost split, then I can nominate multiple cost centres and the percentage to allocate to each 2. Given I have submitted the cost centre split, when the process is complete, then the system automatically creates accounting journals to reclassify the asset's cost and future depreciation according to the new allocation | E64: Fixed Asset Accountant | F64: D.239 | G64: A2R0009 | H64: A2R-020-010 | I64: =_xlfn.XLOOKUP(H64,'Taxonomy and Epics'!H:H,'Taxonomy and Epics'!I:I) -> Create Book/Tax Asset Record & Components | J64: =_xlfn.XLOOKUP($H64,'Taxonomy and Epics'!$H:$H,'Taxonomy and Epics'!E:E) -> 6.0 - A2R - Acquire to Retire | K64: =_xlfn.XLOOKUP($H64,'Taxonomy and Epics'!$H:$H,'Taxonomy and Epics'!F:F) -> A2R-020 | L64: =_xlfn.XLOOKUP($H64,'Taxonomy and Epics'!$H:$H,'Taxonomy and Epics'!G:G) -> Asset Creation | M64: =_xlfn.XLOOKUP($H64,'Taxonomy and Epics'!$H:$H,'Taxonomy and Epics'!H:H) -> A2R-020-010 | N64: =_xlfn.XLOOKUP($H64,'Taxonomy and Epics'!$H:$H,'Taxonomy and Epics'!I:I) -> Create Book/Tax Asset Record & Components
A65: US-A2R-010 | B65: As a Fixed Asset Accountant, I want to adjust the useful life of an asset in the tax book, so that our tax depreciation calculations are correct without affecting our financial accounting | C65: As a Fixed Asset Accountant, I want to adjust the useful life of an asset in the tax book, so that our tax depreciation calculations are correct without affecting our financial accounting | D65: 1. Given an asset's useful life in the tax book is incorrect, when I update the useful life value in the secondary (tax) book, then the change is saved 2. Given the useful life in the tax book has been changed, when the change is processed, then no financial accounting journals are created | E65: Fixed Asset Accountant | F65: D.225 | G65: A2R0010 | H65: A2R-020-010 | I65: =_xlfn.XLOOKUP(H65,'Taxonomy and Epics'!H:H,'Taxonomy and Epics'!I:I) -> Create Book/Tax Asset Record & Components | J65: =_xlfn.XLOOKUP($H65,'Taxonomy and Epics'!$H:$H,'Taxonomy and Epics'!E:E) -> 6.0 - A2R - Acquire to Retire | K65: =_xlfn.XLOOKUP($H65,'Taxonomy and Epics'!$H:$H,'Taxonomy and Epics'!F:F) -> A2R-020 | L65: =_xlfn.XLOOKUP($H65,'Taxonomy and Epics'!$H:$H,'Taxonomy and Epics'!G:G) -> Asset Creation | M65: =_xlfn.XLOOKUP($H65,'Taxonomy and Epics'!$H:$H,'Taxonomy and Epics'!H:H) -> A2R-020-010 | N65: =_xlfn.XLOOKUP($H65,'Taxonomy and Epics'!$H:$H,'Taxonomy and Epics'!I:I) -> Create Book/Tax Asset Record & Components
A66: US-A2R-011 | B66: As a Fixed Asset Accountant, I want to run a report of all created assets (the fixed asset register), so that I can provide this data to an external system for additional recording | C66: As a Fixed Asset Accountant, I want to run a report of all created assets (the fixed asset register), so that I can provide this data to an external system for additional recording | D66: 1. Given I need a list of all assets, when I run the Fixed Asset Register report, then it returns a complete list of all registered assets with their key details 2. Given I have run the report, when I view the output, then I can export it in a format suitable for an external system (e.g., CSV, Excel). | E66: Fixed Asset Accountant | F66: D.226 | G66: A2R0011 | H66: A2R-020-010 | I66: =_xlfn.XLOOKUP(H66,'Taxonomy and Epics'!H:H,'Taxonomy and Epics'!I:I) -> Create Book/Tax Asset Record & Components | J66: =_xlfn.XLOOKUP($H66,'Taxonomy and Epics'!$H:$H,'Taxonomy and Epics'!E:E) -> 6.0 - A2R - Acquire to Retire | K66: =_xlfn.XLOOKUP($H66,'Taxonomy and Epics'!$H:$H,'Taxonomy and Epics'!F:F) -> A2R-020 | L66: =_xlfn.XLOOKUP($H66,'Taxonomy and Epics'!$H:$H,'Taxonomy and Epics'!G:G) -> Asset Creation | M66: =_xlfn.XLOOKUP($H66,'Taxonomy and Epics'!$H:$H,'Taxonomy and Epics'!H:H) -> A2R-020-010 | N66: =_xlfn.XLOOKUP($H66,'Taxonomy and Epics'!$H:$H,'Taxonomy and Epics'!I:I) -> Create Book/Tax Asset Record & Components
A67: US-A2R-012 | B67: As a Fixed Asset Accountant, I want to run a report on all assets that are registered but not yet in service, so that I can track and manage our inventory of unused assets. | C67: As a Fixed Asset Accountant, I want to run a report on all assets that are registered but not yet in service, so that I can track and manage our inventory of unused assets. | D67: 1. Given I need to see assets awaiting deployment, when I run the 'Find Assets' report, then it returns a list of all assets with a status of 'Registered' | E67: Fixed Asset Accountant | F67: D.250 | G67: A2R0012 | H67: A2R-020-040 | I67: =_xlfn.XLOOKUP(H67,'Taxonomy and Epics'!H:H,'Taxonomy and Epics'!I:I) -> Place in Service & Issue Asset | J67: =_xlfn.XLOOKUP($H67,'Taxonomy and Epics'!$H:$H,'Taxonomy and Epics'!E:E) -> 6.0 - A2R - Acquire to Retire | K67: =_xlfn.XLOOKUP($H67,'Taxonomy and Epics'!$H:$H,'Taxonomy and Epics'!F:F) -> A2R-020 | L67: =_xlfn.XLOOKUP($H67,'Taxonomy and Epics'!$H:$H,'Taxonomy and Epics'!G:G) -> Asset Creation | M67: =_xlfn.XLOOKUP($H67,'Taxonomy and Epics'!$H:$H,'Taxonomy and Epics'!H:H) -> A2R-020-040 | N67: =_xlfn.XLOOKUP($H67,'Taxonomy and Epics'!$H:$H,'Taxonomy and Epics'!I:I) -> Place in Service & Issue Asset
A68: US-A2R-013 | B68: As a Fixed Asset Accountant, I want to change an asset's status to 'In Service', so that it begins depreciating from the correct date | C68: As a Fixed Asset Accountant, I want to change an asset's status to 'In Service', so that it begins depreciating from the correct date | D68: 1. Given an asset has a status of 'Registered', when I initiate the 'Place in Service' action and specify an in-service date, then the asset's status is updated to 'In Service' 2. Given an asset has been placed in service, when the next depreciation run occurs, then the asset is included in the depreciation calculation | E68: Fixed Asset Accountant | G68: A2R0013 | H68: A2R-020-040 | I68: =_xlfn.XLOOKUP(H68,'Taxonomy and Epics'!H:H,'Taxonomy and Epics'!I:I) -> Place in Service & Issue Asset | J68: =_xlfn.XLOOKUP($H68,'Taxonomy and Epics'!$H:$H,'Taxonomy and Epics'!E:E) -> 6.0 - A2R - Acquire to Retire | K68: =_xlfn.XLOOKUP($H68,'Taxonomy and Epics'!$H:$H,'Taxonomy and Epics'!F:F) -> A2R-020 | L68: =_xlfn.XLOOKUP($H68,'Taxonomy and Epics'!$H:$H,'Taxonomy and Epics'!G:G) -> Asset Creation | M68: =_xlfn.XLOOKUP($H68,'Taxonomy and Epics'!$H:$H,'Taxonomy and Epics'!H:H) -> A2R-020-040 | N68: =_xlfn.XLOOKUP($H68,'Taxonomy and Epics'!$H:$H,'Taxonomy and Epics'!I:I) -> Place in Service & Issue Asset
A69: US-A2R-015 | B69: As a Fixed Asset Accountant, I want to preview the expected depreciation charge for current or future months, so that I can forecast expenses and review for anomalies before posting | C69: As a Fixed Asset Accountant, I want to preview the expected depreciation charge for current or future months, so that I can forecast expenses and review for anomalies before posting | D69: 1. Given I want to see future depreciation, when I run the depreciation preview report for a specific month, then the system displays the calculated depreciation amount for each asset without posting any journals | E69: Fixed Asset Accountant | F69: D.221;D.234 | G69: A2R0015 | H69: A2R-030-010 | I69: =_xlfn.XLOOKUP(H69,'Taxonomy and Epics'!H:H,'Taxonomy and Epics'!I:I) -> Run & Review Depreciation | J69: =_xlfn.XLOOKUP($H69,'Taxonomy and Epics'!$H:$H,'Taxonomy and Epics'!E:E) -> 6.0 - A2R - Acquire to Retire | K69: =_xlfn.XLOOKUP($H69,'Taxonomy and Epics'!$H:$H,'Taxonomy and Epics'!F:F) -> A2R-030 | L69: =_xlfn.XLOOKUP($H69,'Taxonomy and Epics'!$H:$H,'Taxonomy and Epics'!G:G) -> Asset Lifecycle | M69: =_xlfn.XLOOKUP($H69,'Taxonomy and Epics'!$H:$H,'Taxonomy and Epics'!H:H) -> A2R-030-010 | N69: =_xlfn.XLOOKUP($H69,'Taxonomy and Epics'!$H:$H,'Taxonomy and Epics'!I:I) -> Run & Review Depreciation
A70: US-A2R-016 | B70: As a Fixed Asset Accountant, I want to run the depreciation process for the current month, so that asset values are updated and the expense is recorded in the general ledger | C70: As a Fixed Asset Accountant, I want to run the depreciation process for the current month, so that asset values are updated and the expense is recorded in the general ledger | D70: 1. Given the month-end is approaching, when I initiate the depreciation run for the period, then the system calculates and posts the depreciation journals for all 'In Service' assets | E70: Fixed Asset Accountant | F70: D.234;D.235 | G70: A2R0016 | H70: A2R-030-010 | I70: =_xlfn.XLOOKUP(H70,'Taxonomy and Epics'!H:H,'Taxonomy and Epics'!I:I) -> Run & Review Depreciation | J70: =_xlfn.XLOOKUP($H70,'Taxonomy and Epics'!$H:$H,'Taxonomy and Epics'!E:E) -> 6.0 - A2R - Acquire to Retire | K70: =_xlfn.XLOOKUP($H70,'Taxonomy and Epics'!$H:$H,'Taxonomy and Epics'!F:F) -> A2R-030 | L70: =_xlfn.XLOOKUP($H70,'Taxonomy and Epics'!$H:$H,'Taxonomy and Epics'!G:G) -> Asset Lifecycle | M70: =_xlfn.XLOOKUP($H70,'Taxonomy and Epics'!$H:$H,'Taxonomy and Epics'!H:H) -> A2R-030-010 | N70: =_xlfn.XLOOKUP($H70,'Taxonomy and Epics'!$H:$H,'Taxonomy and Epics'!I:I) -> Run & Review Depreciation
A71: US-A2R-017 | B71: As an Asset Control Officer, I want to generate and review the Fixed Asset Register report, so that I can perform asset audits and verify our records | C71: As an Asset Control Officer, I want to generate and review the Fixed Asset Register report, so that I can perform asset audits and verify our records | D71: 1. Given I need a complete list of our assets, when I run the Fixed Asset Register report, then it provides a detailed list of all assets, including their location and value. | E71: Asset Control Officer | F71: D.227;D.229 | G71: A2R0017 | H71: A2R-030-020 | I71: =_xlfn.XLOOKUP(H71,'Taxonomy and Epics'!H:H,'Taxonomy and Epics'!I:I) -> Identify Asset Retirements | J71: =_xlfn.XLOOKUP($H71,'Taxonomy and Epics'!$H:$H,'Taxonomy and Epics'!E:E) -> 6.0 - A2R - Acquire to Retire | K71: =_xlfn.XLOOKUP($H71,'Taxonomy and Epics'!$H:$H,'Taxonomy and Epics'!F:F) -> A2R-030 | L71: =_xlfn.XLOOKUP($H71,'Taxonomy and Epics'!$H:$H,'Taxonomy and Epics'!G:G) -> Asset Lifecycle | M71: =_xlfn.XLOOKUP($H71,'Taxonomy and Epics'!$H:$H,'Taxonomy and Epics'!H:H) -> A2R-030-020 | N71: =_xlfn.XLOOKUP($H71,'Taxonomy and Epics'!$H:$H,'Taxonomy and Epics'!I:I) -> Identify Asset Retirements
A72: US-A2R-018 | B72: As a Fixed Asset Accountant, I want to report on the secondary (tax) book values for an asset, so that I can understand the tax implications and ensure compliance. | C72: As a Fixed Asset Accountant, I want to report on the secondary (tax) book values for an asset, so that I can understand the tax implications and ensure compliance. | D72: 1. Given I need to see the tax value of an asset, when I run a report on an asset's secondary book, then the report shows details like tax cost, accumulated tax depreciation, and tax net book value | E72: Fixed Asset Accountant | G72: A2R0018 | H72: A2R-030-030 | I72: =_xlfn.XLOOKUP(H72,'Taxonomy and Epics'!H:H,'Taxonomy and Epics'!I:I) -> Communicate Secondary Book Retirement Implications | J72: =_xlfn.XLOOKUP($H72,'Taxonomy and Epics'!$H:$H,'Taxonomy and Epics'!E:E) -> 6.0 - A2R - Acquire to Retire | K72: =_xlfn.XLOOKUP($H72,'Taxonomy and Epics'!$H:$H,'Taxonomy and Epics'!F:F) -> A2R-030 | L72: =_xlfn.XLOOKUP($H72,'Taxonomy and Epics'!$H:$H,'Taxonomy and Epics'!G:G) -> Asset Lifecycle | M72: =_xlfn.XLOOKUP($H72,'Taxonomy and Epics'!$H:$H,'Taxonomy and Epics'!H:H) -> A2R-030-030 | N72: =_xlfn.XLOOKUP($H72,'Taxonomy and Epics'!$H:$H,'Taxonomy and Epics'!I:I) -> Communicate Secondary Book Retirement Implications
A73: US-A2R-019 | B73: As a Fixed Asset Accountant, I want to dispose of fully depreciated assets with a zero carrying value, so that I can remove them from the active asset register | C73: As a Fixed Asset Accountant, I want to dispose of fully depreciated assets with a zero carrying value, so that I can remove them from the active asset register | D73: 1. Given an asset has a net book value of $0, when I initiate the disposal process, then the asset is retired and its status is updated to 'Disposed' | E73: Fixed Asset Accountant | F73: D.236;D.241 | G73: A2R0019 | H73: A2R-030-040 | I73: =_xlfn.XLOOKUP(H73,'Taxonomy and Epics'!H:H,'Taxonomy and Epics'!I:I) -> Record Asset Retirement | J73: =_xlfn.XLOOKUP($H73,'Taxonomy and Epics'!$H:$H,'Taxonomy and Epics'!E:E) -> 6.0 - A2R - Acquire to Retire | K73: =_xlfn.XLOOKUP($H73,'Taxonomy and Epics'!$H:$H,'Taxonomy and Epics'!F:F) -> A2R-030 | L73: =_xlfn.XLOOKUP($H73,'Taxonomy and Epics'!$H:$H,'Taxonomy and Epics'!G:G) -> Asset Lifecycle | M73: =_xlfn.XLOOKUP($H73,'Taxonomy and Epics'!$H:$H,'Taxonomy and Epics'!H:H) -> A2R-030-040 | N73: =_xlfn.XLOOKUP($H73,'Taxonomy and Epics'!$H:$H,'Taxonomy and Epics'!I:I) -> Record Asset Retirement
A74: US-A2R-020 | B74: As a Fixed Asset Accountant, I want to dispose of an asset that still has a carrying value, so that the system correctly calculates and posts any resulting gain or loss | C74: As a Fixed Asset Accountant, I want to dispose of an asset that still has a carrying value, so that the system correctly calculates and posts any resulting gain or loss | D74: 1. Given an asset with a non-zero carrying value is being disposed, when I process the disposal, then the system automatically calculates the gain or loss on disposal 2. Given an asset disposal has been submitted, when I record the sale in Workday, then the request is routed to the Financial Accounting Manager for final approval 3. Given the Financial Accounting Manager approves the disposal, when the process is complete, then the asset is recorded as disposed 4. Given a gain or loss has been calculated, when the disposal is finalised, then the system posts the corresponding accounting journals to the general ledger | E74: Fixed Asset Accountant | F74: D.236;D.242 | G74: A2R0020 | H74: A2R-030-040 | I74: =_xlfn.XLOOKUP(H74,'Taxonomy and Epics'!H:H,'Taxonomy and Epics'!I:I) -> Record Asset Retirement | J74: =_xlfn.XLOOKUP($H74,'Taxonomy and Epics'!$H:$H,'Taxonomy and Epics'!E:E) -> 6.0 - A2R - Acquire to Retire | K74: =_xlfn.XLOOKUP($H74,'Taxonomy and Epics'!$H:$H,'Taxonomy and Epics'!F:F) -> A2R-030 | L74: =_xlfn.XLOOKUP($H74,'Taxonomy and Epics'!$H:$H,'Taxonomy and Epics'!G:G) -> Asset Lifecycle | M74: =_xlfn.XLOOKUP($H74,'Taxonomy and Epics'!$H:$H,'Taxonomy and Epics'!H:H) -> A2R-030-040 | N74: =_xlfn.XLOOKUP($H74,'Taxonomy and Epics'!$H:$H,'Taxonomy and Epics'!I:I) -> Record Asset Retirement
A75: US-A2R-021 | B75: As a Fixed Asset Accountant, I want to reinstate an asset that was previously disposed of in error, so that I can correct the record and reverse the disposal accounting | C75: As a Fixed Asset Accountant, I want to reinstate an asset that was previously disposed of in error, so that I can correct the record and reverse the disposal accounting | D75: 1. Given an asset has a 'Disposed' status, when I initiate the reinstatement process, then the asset's status is returned to its pre-disposal state (e.g., 'In Service') 2. Given an asset is reinstated, when the process is complete, then the system automatically posts journals to reverse the original disposal accounting entries | E75: Fixed Asset Accountant | G75: A2R0021 | H75: A2R-030-040 | I75: =_xlfn.XLOOKUP(H75,'Taxonomy and Epics'!H:H,'Taxonomy and Epics'!I:I) -> Record Asset Retirement | J75: =_xlfn.XLOOKUP($H75,'Taxonomy and Epics'!$H:$H,'Taxonomy and Epics'!E:E) -> 6.0 - A2R - Acquire to Retire | K75: =_xlfn.XLOOKUP($H75,'Taxonomy and Epics'!$H:$H,'Taxonomy and Epics'!F:F) -> A2R-030 | L75: =_xlfn.XLOOKUP($H75,'Taxonomy and Epics'!$H:$H,'Taxonomy and Epics'!G:G) -> Asset Lifecycle | M75: =_xlfn.XLOOKUP($H75,'Taxonomy and Epics'!$H:$H,'Taxonomy and Epics'!H:H) -> A2R-030-040 | N75: =_xlfn.XLOOKUP($H75,'Taxonomy and Epics'!$H:$H,'Taxonomy and Epics'!I:I) -> Record Asset Retirement
A76: US-A2R-022 | B76: As an Asset Owner, I want to request the sale of an asset I am responsible for using Service Now, so that the formal disposal process can be initiated | C76: As an Asset Owner, I want to request the sale of an asset I am responsible for using Service Now, so that the formal disposal process can be initiated | D76: 1. Given I am an Asset Owner in Service Now, when I submit a request to sell an asset, then the request is logged and routed for approval within Service Now | E76: Asset Owner | F76: D.230;D.238;D.240 | G76: A2R0022 | H76: A2R-030-050 | I76: =_xlfn.XLOOKUP(H76,'Taxonomy and Epics'!H:H,'Taxonomy and Epics'!I:I) -> Record Asset Sale/Trade | J76: =_xlfn.XLOOKUP($H76,'Taxonomy and Epics'!$H:$H,'Taxonomy and Epics'!E:E) -> 6.0 - A2R - Acquire to Retire | K76: =_xlfn.XLOOKUP($H76,'Taxonomy and Epics'!$H:$H,'Taxonomy and Epics'!F:F) -> A2R-030 | L76: =_xlfn.XLOOKUP($H76,'Taxonomy and Epics'!$H:$H,'Taxonomy and Epics'!G:G) -> Asset Lifecycle | M76: =_xlfn.XLOOKUP($H76,'Taxonomy and Epics'!$H:$H,'Taxonomy and Epics'!H:H) -> A2R-030-050 | N76: =_xlfn.XLOOKUP($H76,'Taxonomy and Epics'!$H:$H,'Taxonomy and Epics'!I:I) -> Record Asset Sale/Trade
A77: US-A2R-023 | B77: As a Fixed Asset Accountant, I want to record the sale of an asset in Workday based on an approved request, so that the asset is correctly disposed of and the financial impact is recorded | C77: As a Fixed Asset Accountant, I want to record the sale of an asset in Workday based on an approved request, so that the asset is correctly disposed of and the financial impact is recorded | D77: 1. Given an asset sale has been approved, when I record the sale in Workday, then the request is routed to the Financial Accounting Manager for final approval 2. Given the Financial Accounting Manager approves the sale, when the process is complete, then the asset is recorded as disposed by sale 3. Given the sale is recorded, when the process is finalised, then a 'To-Do' notification is sent to the Accounts Receivable Officer to create the customer invoice | E77: Fixed Asset Accountant | F77: D.237;D.242 | G77: A2R0023 | H77: A2R-030-050 | I77: =_xlfn.XLOOKUP(H77,'Taxonomy and Epics'!H:H,'Taxonomy and Epics'!I:I) -> Record Asset Sale/Trade | J77: =_xlfn.XLOOKUP($H77,'Taxonomy and Epics'!$H:$H,'Taxonomy and Epics'!E:E) -> 6.0 - A2R - Acquire to Retire | K77: =_xlfn.XLOOKUP($H77,'Taxonomy and Epics'!$H:$H,'Taxonomy and Epics'!F:F) -> A2R-030 | L77: =_xlfn.XLOOKUP($H77,'Taxonomy and Epics'!$H:$H,'Taxonomy and Epics'!G:G) -> Asset Lifecycle | M77: =_xlfn.XLOOKUP($H77,'Taxonomy and Epics'!$H:$H,'Taxonomy and Epics'!H:H) -> A2R-030-050 | N77: =_xlfn.XLOOKUP($H77,'Taxonomy and Epics'!$H:$H,'Taxonomy and Epics'!I:I) -> Record Asset Sale/Trade
A78: US-A2R-024 | B78: As an Accounts Receivable Officer, I want to create a customer invoice for a sold asset after being notified, so that we can bill the customer and ensure the profit and loss is accurate | C78: As an Accounts Receivable Officer, I want to create a customer invoice for a sold asset after being notified, so that we can bill the customer and ensure the profit and loss is accurate | D78: 1. Given an asset sale has been recorded by the Fixed Asset Accountant, when the process is complete, then I receive a 'To-Do' task in my inbox to create a customer invoice 2. Given I have created and completed the customer invoice for the asset sale, when the accounting is posted, then it correctly offsets the accounting from the asset disposal transaction | E78: Accounts Receivable Officer | G78: A2R0024 | H78: A2R-030-050 | I78: =_xlfn.XLOOKUP(H78,'Taxonomy and Epics'!H:H,'Taxonomy and Epics'!I:I) -> Record Asset Sale/Trade | J78: =_xlfn.XLOOKUP($H78,'Taxonomy and Epics'!$H:$H,'Taxonomy and Epics'!E:E) -> 6.0 - A2R - Acquire to Retire | K78: =_xlfn.XLOOKUP($H78,'Taxonomy and Epics'!$H:$H,'Taxonomy and Epics'!F:F) -> A2R-030 | L78: =_xlfn.XLOOKUP($H78,'Taxonomy and Epics'!$H:$H,'Taxonomy and Epics'!G:G) -> Asset Lifecycle | M78: =_xlfn.XLOOKUP($H78,'Taxonomy and Epics'!$H:$H,'Taxonomy and Epics'!H:H) -> A2R-030-050 | N78: =_xlfn.XLOOKUP($H78,'Taxonomy and Epics'!$H:$H,'Taxonomy and Epics'!I:I) -> Record Asset Sale/Trade
A79: US-A2R-025 | B79: As a Fixed Asset Accountant, I want to adjust the cost of an asset after it has been acquired, so that the asset's value is accurate and reflects subsequent costs or corrections | C79: As a Fixed Asset Accountant, I want to adjust the cost of an asset after it has been acquired, so that the asset's value is accurate and reflects subsequent costs or corrections | D79: 1. Given I need to adjust an asset's cost, when I initiate the cost adjustment, then the request is sent to the Financial Accounting Manager for approval 2. Given a cost adjustment is based on a subsequent supplier invoice, when I link the invoice to the adjustment, then the asset's cost is updated upon approval 3. Given a cost adjustment is not linked to a supplier invoice, when the adjustment is approved, then a 'To-Do' notification is sent to an accountant to create a manual journal | E79: Fixed Asset Accountant | F79: D.243;D.239;D.246 | G79: A2R0025 | H79: A2R-030-060 | I79: =_xlfn.XLOOKUP(H79,'Taxonomy and Epics'!H:H,'Taxonomy and Epics'!I:I) -> Perform Asset Revaluation | J79: =_xlfn.XLOOKUP($H79,'Taxonomy and Epics'!$H:$H,'Taxonomy and Epics'!E:E) -> 6.0 - A2R - Acquire to Retire | K79: =_xlfn.XLOOKUP($H79,'Taxonomy and Epics'!$H:$H,'Taxonomy and Epics'!F:F) -> A2R-030 | L79: =_xlfn.XLOOKUP($H79,'Taxonomy and Epics'!$H:$H,'Taxonomy and Epics'!G:G) -> Asset Lifecycle | M79: =_xlfn.XLOOKUP($H79,'Taxonomy and Epics'!$H:$H,'Taxonomy and Epics'!H:H) -> A2R-030-060 | N79: =_xlfn.XLOOKUP($H79,'Taxonomy and Epics'!$H:$H,'Taxonomy and Epics'!I:I) -> Perform Asset Revaluation
A80: US-A2R-026 | B80: As a Fixed Asset Accountant, I want to record an impairment for an asset, so that its carrying value is reduced to its recoverable amount in line with accounting standards | C80: As a Fixed Asset Accountant, I want to record an impairment for an asset, so that its carrying value is reduced to its recoverable amount in line with accounting standards | D80: 1. Given I need to impair an asset, when I submit the impairment details, then the request is sent to the Financial Accounting Manager for approval 2. Given the Financial Accounting Manager approves the impairment, when the process is complete, then the asset's value is reduced and the impairment loss is recorded 3. Given the Financial Accounting Manager denies the impairment request, when the request is denied, then I receive a notification informing me of the denial | E80: Fixed Asset Accountant | F80: D.244;D.239 | G80: A2R0026 | H80: A2R-030-070 | I80: =_xlfn.XLOOKUP(H80,'Taxonomy and Epics'!H:H,'Taxonomy and Epics'!I:I) -> Record Asset Impairment | J80: =_xlfn.XLOOKUP($H80,'Taxonomy and Epics'!$H:$H,'Taxonomy and Epics'!E:E) -> 6.0 - A2R - Acquire to Retire | K80: =_xlfn.XLOOKUP($H80,'Taxonomy and Epics'!$H:$H,'Taxonomy and Epics'!F:F) -> A2R-030 | L80: =_xlfn.XLOOKUP($H80,'Taxonomy and Epics'!$H:$H,'Taxonomy and Epics'!G:G) -> Asset Lifecycle | M80: =_xlfn.XLOOKUP($H80,'Taxonomy and Epics'!$H:$H,'Taxonomy and Epics'!H:H) -> A2R-030-070 | N80: =_xlfn.XLOOKUP($H80,'Taxonomy and Epics'!$H:$H,'Taxonomy and Epics'!I:I) -> Record Asset Impairment
A81: US-A2R-027 | B81: As an Asset Owner, I want to request a transfer of my asset using Service Now, so that the process to update its location, cost centre, or custodian can be initiated | C81: As an Asset Owner, I want to request a transfer of my asset using Service Now, so that the process to update its location, cost centre, or custodian can be initiated | D81: 1. Given I am an Asset Owner in Service Now, when I submit a request to transfer an asset, then the request is logged and routed for approval within Service Now | E81: Asset Owner | F81: D.230 | G81: A2R0027 | H81: A2R-030-090 | I81: =_xlfn.XLOOKUP(H81,'Taxonomy and Epics'!H:H,'Taxonomy and Epics'!I:I) -> Process Transfers | J81: =_xlfn.XLOOKUP($H81,'Taxonomy and Epics'!$H:$H,'Taxonomy and Epics'!E:E) -> 6.0 - A2R - Acquire to Retire | K81: =_xlfn.XLOOKUP($H81,'Taxonomy and Epics'!$H:$H,'Taxonomy and Epics'!F:F) -> A2R-030 | L81: =_xlfn.XLOOKUP($H81,'Taxonomy and Epics'!$H:$H,'Taxonomy and Epics'!G:G) -> Asset Lifecycle | M81: =_xlfn.XLOOKUP($H81,'Taxonomy and Epics'!$H:$H,'Taxonomy and Epics'!H:H) -> A2R-030-090 | N81: =_xlfn.XLOOKUP($H81,'Taxonomy and Epics'!$H:$H,'Taxonomy and Epics'!I:I) -> Process Transfers
A82: US-A2R-028 | B82: As a Fixed Asset Accountant, I want to transfer an asset to a different cost centre, so that its depreciation is charged to the correct department | C82: As a Fixed Asset Accountant, I want to transfer an asset to a different cost centre, so that its depreciation is charged to the correct department | D82: 1. Given I am a Fixed Asset Accountant, when I initiate an asset transfer to a new cost centre, then the change is processed immediately without requiring an approval step | E82: Fixed Asset Accountant | F82: D.247;D.248 | G82: A2R0028 | H82: A2R-030-090 | I82: =_xlfn.XLOOKUP(H82,'Taxonomy and Epics'!H:H,'Taxonomy and Epics'!I:I) -> Process Transfers | J82: =_xlfn.XLOOKUP($H82,'Taxonomy and Epics'!$H:$H,'Taxonomy and Epics'!E:E) -> 6.0 - A2R - Acquire to Retire | K82: =_xlfn.XLOOKUP($H82,'Taxonomy and Epics'!$H:$H,'Taxonomy and Epics'!F:F) -> A2R-030 | L82: =_xlfn.XLOOKUP($H82,'Taxonomy and Epics'!$H:$H,'Taxonomy and Epics'!G:G) -> Asset Lifecycle | M82: =_xlfn.XLOOKUP($H82,'Taxonomy and Epics'!$H:$H,'Taxonomy and Epics'!H:H) -> A2R-030-090 | N82: =_xlfn.XLOOKUP($H82,'Taxonomy and Epics'!$H:$H,'Taxonomy and Epics'!I:I) -> Process Transfers
A83: US-A2R-030 | B83: As a Fixed Asset Accountant, I want to transfer an asset to a different location, so that the physical location of the asset is accurately tracked in the system | C83: As a Fixed Asset Accountant, I want to transfer an asset to a different location, so that the physical location of the asset is accurately tracked in the system | D83: 1. Given I am a Fixed Asset Accountant, when I initiate an asset transfer to a new location (e.g., building or room), then the change is processed immediately without requiring an approval step | E83: Fixed Asset Accountant | F83: D.245 | G83: A2R0030 | H83: A2R-030-090 | I83: =_xlfn.XLOOKUP(H83,'Taxonomy and Epics'!H:H,'Taxonomy and Epics'!I:I) -> Process Transfers | J83: =_xlfn.XLOOKUP($H83,'Taxonomy and Epics'!$H:$H,'Taxonomy and Epics'!E:E) -> 6.0 - A2R - Acquire to Retire | K83: =_xlfn.XLOOKUP($H83,'Taxonomy and Epics'!$H:$H,'Taxonomy and Epics'!F:F) -> A2R-030 | L83: =_xlfn.XLOOKUP($H83,'Taxonomy and Epics'!$H:$H,'Taxonomy and Epics'!G:G) -> Asset Lifecycle | M83: =_xlfn.XLOOKUP($H83,'Taxonomy and Epics'!$H:$H,'Taxonomy and Epics'!H:H) -> A2R-030-090 | N83: =_xlfn.XLOOKUP($H83,'Taxonomy and Epics'!$H:$H,'Taxonomy and Epics'!I:I) -> Process Transfers
A84: US-A2R-031 | B84: As an Asset Control Officer, I want to process a request to transfer an asset to a different cost centre, so that the change can be reviewed and approved by the accounting team | C84: As an Asset Control Officer, I want to process a request to transfer an asset to a different cost centre, so that the change can be reviewed and approved by the accounting team | D84: 1. Given I am an Asset Control Officer, when I initiate an asset transfer to a new cost centre, then the request is sent to the Fixed Asset Accountant for approval | E84: Asset Control Officer | G84: A2R0031 | H84: A2R-030-090 | I84: =_xlfn.XLOOKUP(H84,'Taxonomy and Epics'!H:H,'Taxonomy and Epics'!I:I) -> Process Transfers | J84: =_xlfn.XLOOKUP($H84,'Taxonomy and Epics'!$H:$H,'Taxonomy and Epics'!E:E) -> 6.0 - A2R - Acquire to Retire | K84: =_xlfn.XLOOKUP($H84,'Taxonomy and Epics'!$H:$H,'Taxonomy and Epics'!F:F) -> A2R-030 | L84: =_xlfn.XLOOKUP($H84,'Taxonomy and Epics'!$H:$H,'Taxonomy and Epics'!G:G) -> Asset Lifecycle | M84: =_xlfn.XLOOKUP($H84,'Taxonomy and Epics'!$H:$H,'Taxonomy and Epics'!H:H) -> A2R-030-090 | N84: =_xlfn.XLOOKUP($H84,'Taxonomy and Epics'!$H:$H,'Taxonomy and Epics'!I:I) -> Process Transfers
A85: US-A2R-033 | B85: As an Asset Control Officer, I want to process a request to transfer an asset to a different location, so that the physical location change can be reviewed and approved by the accounting team | C85: As an Asset Control Officer, I want to process a request to transfer an asset to a different location, so that the physical location change can be reviewed and approved by the accounting team | D85: 1. Given I am an Asset Control Officer, when I initiate an asset transfer to a new location, then the request is sent to the Fixed Asset Accountant for approval | E85: Asset Control Officer | G85: A2R0033 | H85: A2R-030-090 | I85: =_xlfn.XLOOKUP(H85,'Taxonomy and Epics'!H:H,'Taxonomy and Epics'!I:I) -> Process Transfers | J85: =_xlfn.XLOOKUP($H85,'Taxonomy and Epics'!$H:$H,'Taxonomy and Epics'!E:E) -> 6.0 - A2R - Acquire to Retire | K85: =_xlfn.XLOOKUP($H85,'Taxonomy and Epics'!$H:$H,'Taxonomy and Epics'!F:F) -> A2R-030 | L85: =_xlfn.XLOOKUP($H85,'Taxonomy and Epics'!$H:$H,'Taxonomy and Epics'!G:G) -> Asset Lifecycle | M85: =_xlfn.XLOOKUP($H85,'Taxonomy and Epics'!$H:$H,'Taxonomy and Epics'!H:H) -> A2R-030-090 | N85: =_xlfn.XLOOKUP($H85,'Taxonomy and Epics'!$H:$H,'Taxonomy and Epics'!I:I) -> Process Transfers
A86: US-A2R-034 | B86: As a Fixed Asset Accountant, I want to change an asset's acquisition cost, so that I can correct errors made during the initial recording of the asset | C86: As a Fixed Asset Accountant, I want to change an asset's acquisition cost, so that I can correct errors made during the initial recording of the asset | D86: 1. Given an asset's acquisition cost is incorrect, when I submit a change to the acquisition cost, then the request is sent to the Financial Accounting Manager for approval 2. Given an acquisition cost is linked to a supplier invoice, when the Financial Accounting Manager approves the change, then the asset's cost basis is updated and corresponding accounting adjustments are posted 3. Given an acquisition cost adjustment is not linked to a supplier invoice, when the adjustment is approved, then a 'To-Do' notification is sent to an accountant to create a manual journal | E86: Fixed Asset Accountant | F86: D.239;D.246 | G86: A2R0034 | H86: A2R-030-080 | I86: =_xlfn.XLOOKUP(H86,'Taxonomy and Epics'!H:H,'Taxonomy and Epics'!I:I) -> Record Adjustments to Asset Details | J86: =_xlfn.XLOOKUP($H86,'Taxonomy and Epics'!$H:$H,'Taxonomy and Epics'!E:E) -> 6.0 - A2R - Acquire to Retire | K86: =_xlfn.XLOOKUP($H86,'Taxonomy and Epics'!$H:$H,'Taxonomy and Epics'!F:F) -> A2R-030 | L86: =_xlfn.XLOOKUP($H86,'Taxonomy and Epics'!$H:$H,'Taxonomy and Epics'!G:G) -> Asset Lifecycle | M86: =_xlfn.XLOOKUP($H86,'Taxonomy and Epics'!$H:$H,'Taxonomy and Epics'!H:H) -> A2R-030-080 | N86: =_xlfn.XLOOKUP($H86,'Taxonomy and Epics'!$H:$H,'Taxonomy and Epics'!I:I) -> Record Adjustments to Asset Details
A87: US-A2R-035 | B87: As a Fixed Asset Accountant, I want to change an asset's useful life, so that the depreciation calculation accurately reflects its expected operational life | C87: As a Fixed Asset Accountant, I want to change an asset's useful life, so that the depreciation calculation accurately reflects its expected operational life | D87: 1. Given I need to change an asset's useful life, when I submit the change, then the request is sent to the Financial Accounting Manager for approval 2. Given I change the useful life with a backdated effective date, when the change is approved, then the system posts a journal to account for the catch-up depreciation difference 3. Given I adjust the useful life with a backdated effective date, when the change is approved, then the system posts a journal to account for the catch-up depreciation difference 4. Given I adjust the useful life with a current or future effective date, when the change is approved, then only the future depreciation amounts are recalculated, with no immediate journal posting | E87: Fixed Asset Accountant | F87: D.225 | G87: A2R0035 | H87: A2R-030-080 | I87: =_xlfn.XLOOKUP(H87,'Taxonomy and Epics'!H:H,'Taxonomy and Epics'!I:I) -> Record Adjustments to Asset Details | J87: =_xlfn.XLOOKUP($H87,'Taxonomy and Epics'!$H:$H,'Taxonomy and Epics'!E:E) -> 6.0 - A2R - Acquire to Retire | K87: =_xlfn.XLOOKUP($H87,'Taxonomy and Epics'!$H:$H,'Taxonomy and Epics'!F:F) -> A2R-030 | L87: =_xlfn.XLOOKUP($H87,'Taxonomy and Epics'!$H:$H,'Taxonomy and Epics'!G:G) -> Asset Lifecycle | M87: =_xlfn.XLOOKUP($H87,'Taxonomy and Epics'!$H:$H,'Taxonomy and Epics'!H:H) -> A2R-030-080 | N87: =_xlfn.XLOOKUP($H87,'Taxonomy and Epics'!$H:$H,'Taxonomy and Epics'!I:I) -> Record Adjustments to Asset Details
A88: US-A2R-036 | B88: As a Fixed Asset Accountant, I want to change an asset's 'in-service' date, so that I can correct the start date of its depreciation | C88: As a Fixed Asset Accountant, I want to change an asset's 'in-service' date, so that I can correct the start date of its depreciation | D88: 1. Given an asset's 'in-service' date is incorrect, when I change the date to a past date, then the system posts a journal to account for the backdated depreciation adjustment | E88: Fixed Asset Accountant | G88: A2R0036 | H88: A2R-030-080 | I88: =_xlfn.XLOOKUP(H88,'Taxonomy and Epics'!H:H,'Taxonomy and Epics'!I:I) -> Record Adjustments to Asset Details | J88: =_xlfn.XLOOKUP($H88,'Taxonomy and Epics'!$H:$H,'Taxonomy and Epics'!E:E) -> 6.0 - A2R - Acquire to Retire | K88: =_xlfn.XLOOKUP($H88,'Taxonomy and Epics'!$H:$H,'Taxonomy and Epics'!F:F) -> A2R-030 | L88: =_xlfn.XLOOKUP($H88,'Taxonomy and Epics'!$H:$H,'Taxonomy and Epics'!G:G) -> Asset Lifecycle | M88: =_xlfn.XLOOKUP($H88,'Taxonomy and Epics'!$H:$H,'Taxonomy and Epics'!H:H) -> A2R-030-080 | N88: =_xlfn.XLOOKUP($H88,'Taxonomy and Epics'!$H:$H,'Taxonomy and Epics'!I:I) -> Record Adjustments to Asset Details
A89: US-A2R-037 | B89: As a Fixed Asset Accountant, I want to reclassify an asset to a different spend category, so that the asset is categorised correctly for financial reporting | C89: As a Fixed Asset Accountant, I want to reclassify an asset to a different spend category, so that the asset is categorised correctly for financial reporting | D89: 1. Given an asset is in the wrong spend category, when I reclassify it to the correct category, then the system posts journals to move the asset's cost and accumulated depreciation between the old and new general ledger accounts | E89: Fixed Asset Accountant | F89: D.229;D.246 | G89: A2R0037 | H89: A2R-030-080 | I89: =_xlfn.XLOOKUP(H89,'Taxonomy and Epics'!H:H,'Taxonomy and Epics'!I:I) -> Record Adjustments to Asset Details | J89: =_xlfn.XLOOKUP($H89,'Taxonomy and Epics'!$H:$H,'Taxonomy and Epics'!E:E) -> 6.0 - A2R - Acquire to Retire | K89: =_xlfn.XLOOKUP($H89,'Taxonomy and Epics'!$H:$H,'Taxonomy and Epics'!F:F) -> A2R-030 | L89: =_xlfn.XLOOKUP($H89,'Taxonomy and Epics'!$H:$H,'Taxonomy and Epics'!G:G) -> Asset Lifecycle | M89: =_xlfn.XLOOKUP($H89,'Taxonomy and Epics'!$H:$H,'Taxonomy and Epics'!H:H) -> A2R-030-080 | N89: =_xlfn.XLOOKUP($H89,'Taxonomy and Epics'!$H:$H,'Taxonomy and Epics'!I:I) -> Record Adjustments to Asset Details
A90: US-A2R-038 | B90: As a Fixed Asset Accountant, I want to post a manual journal to register a new asset, so that I can ensure all company assets are accurately recorded in the financial system. | C90: As a Fixed Asset Accountant, I want to post a manual journal to register a new asset in the GL, so that I can ensure all company assets are accurately recorded in the financial system. | D90: 1. Given I am posting a journal for a manually registered asset, when I select 'manual asset registration' as the journal source, enter the asset details including a location and cost center on the relevant journal lines, and submit it for posting, then the journal should enter the workflow successfully. 2. Given I am posting a journal for a manually registered asset, when I attempt to post the journal without selecting 'manual asset registration' as the journal source, then the system should prevent the journal from posting and display an error message instructing me to use the correct journal source. 3. Given I am posting a journal for a manually registered asset using the 'manual asset registration' source, when I attempt to post the journal without specifying a location on the asset-related journal lines, then the system should prevent the journal from posting and display an error message indicating that a location is required. 4. Given I am posting a journal for a manually registered asset using the 'manual asset registration' source, when I attempt to post the journal without specifying a cpst center on the asset-related journal lines, then the system should prevent the journal from posting and display an error message indicating that a cost center is required. | E90: Fixed Asset Accountant | F90: D.233 | G90: A2R0038 | H90: A2R-020-010 | I90: =_xlfn.XLOOKUP(H90,'Taxonomy and Epics'!H:H,'Taxonomy and Epics'!I:I) -> Create Book/Tax Asset Record & Components | J90: =_xlfn.XLOOKUP($H90,'Taxonomy and Epics'!$H:$H,'Taxonomy and Epics'!E:E) -> 6.0 - A2R - Acquire to Retire | K90: =_xlfn.XLOOKUP($H90,'Taxonomy and Epics'!$H:$H,'Taxonomy and Epics'!F:F) -> A2R-020 | L90: =_xlfn.XLOOKUP($H90,'Taxonomy and Epics'!$H:$H,'Taxonomy and Epics'!G:G) -> Asset Creation | M90: =_xlfn.XLOOKUP($H90,'Taxonomy and Epics'!$H:$H,'Taxonomy and Epics'!H:H) -> A2R-020-010 | N90: =_xlfn.XLOOKUP($H90,'Taxonomy and Epics'!$H:$H,'Taxonomy and Epics'!I:I) -> Create Book/Tax Asset Record & Components
A91: US-A2R-039 | B91: As a Fixed Asset Accountant, I want to process a lease contract with fixed or variable payments, so that I can accurately record our financial obligations for leased assets. | C91: As a Fixed Asset Accountant, I want to process a lease contract with fixed or variable payments, so that I can accurately record our financial obligations for leased assets. | D91: 1. Given I am creating a new lease contract, when I select the fixed payment option and enter all required details, then the system successfully creates the contract 2. Given I am creating a new lease contract, when I select the variable payment option and enter all required details, then the system successfully creates the contract. 3. Given I am creating a new lease contract, when it is submitted and complete, I should be able to view the financial impact on the general ledger. | E91: Fixed Asset Accountant | F91: D.284;D.285 | G91: A2R0039 | H91: A2R-020-020 | I91: =_xlfn.XLOOKUP(H91,'Taxonomy and Epics'!H:H,'Taxonomy and Epics'!I:I) -> Setup Right of Use Assets (Leases) | J91: =_xlfn.XLOOKUP($H91,'Taxonomy and Epics'!$H:$H,'Taxonomy and Epics'!E:E) -> 6.0 - A2R - Acquire to Retire | K91: =_xlfn.XLOOKUP($H91,'Taxonomy and Epics'!$H:$H,'Taxonomy and Epics'!F:F) -> A2R-020 | L91: =_xlfn.XLOOKUP($H91,'Taxonomy and Epics'!$H:$H,'Taxonomy and Epics'!G:G) -> Asset Creation | M91: =_xlfn.XLOOKUP($H91,'Taxonomy and Epics'!$H:$H,'Taxonomy and Epics'!H:H) -> A2R-020-020 | N91: =_xlfn.XLOOKUP($H91,'Taxonomy and Epics'!$H:$H,'Taxonomy and Epics'!I:I) -> Setup Right of Use Assets (Leases)
A92: US-A2R-040 | B92: As a Fixed Asset Accountant, I want the system to enforce mandatory fields when creating a lease contract, so that all contracts contain complete and consistent information. | C92: As a Fixed Asset Accountant, I want the system to enforce mandatory fields when creating a lease contract, so that all contracts contain complete and consistent information. | D92: 1. Given I am creating a lease contract, when I try to submit for a spend category not designated for leases, then the system should display an error message and prevent submission. 2. Given I am creating a lease contract, when I try to submit it without a location on the goods line, then the system should display an error message and prevent submission. 3. Given I am creating a lease contract, when I try to submit it without a description on the goods line, then the system should display an error message and prevent submission. 4. Given I am creating a lease contract, when I have entered both a location and a description, then the system allows me to submit the contract successfully. | E92: Fixed Asset Accountant | G92: A2R0040 | H92: A2R-020-020 | I92: =_xlfn.XLOOKUP(H92,'Taxonomy and Epics'!H:H,'Taxonomy and Epics'!I:I) -> Setup Right of Use Assets (Leases) | J92: =_xlfn.XLOOKUP($H92,'Taxonomy and Epics'!$H:$H,'Taxonomy and Epics'!E:E) -> 6.0 - A2R - Acquire to Retire | K92: =_xlfn.XLOOKUP($H92,'Taxonomy and Epics'!$H:$H,'Taxonomy and Epics'!F:F) -> A2R-020 | L92: =_xlfn.XLOOKUP($H92,'Taxonomy and Epics'!$H:$H,'Taxonomy and Epics'!G:G) -> Asset Creation | M92: =_xlfn.XLOOKUP($H92,'Taxonomy and Epics'!$H:$H,'Taxonomy and Epics'!H:H) -> A2R-020-020 | N92: =_xlfn.XLOOKUP($H92,'Taxonomy and Epics'!$H:$H,'Taxonomy and Epics'!I:I) -> Setup Right of Use Assets (Leases)
A93: US-A2R-041 | B93: As a Fixed Asset Accountant, I want the system to automatically create a leased asset when a relevant lease contract is receipted, so that assets are registered efficiently and accurately. | C93: As a Fixed Asset Accountant, I want the system to automatically create a leased asset when a relevant lease contract is receipted, so that assets are registered efficiently and accurately. | D93: 1. Given a lease contract with a specific spend category (e.g., property rent) is receipted, when the process is initiated, then a review task is sent to the Fixed Asset Accountant. 2. Given the Fixed Asset Accountant has received the asset creation review task, when they complete the review step, then the system automatically registers the new asset with the confirmed details. | E93: Fixed Asset Accountant | F93: D.232;D.283;D.285 | G93: A2R0041 | H93: A2R-020-020 | I93: =_xlfn.XLOOKUP(H93,'Taxonomy and Epics'!H:H,'Taxonomy and Epics'!I:I) -> Setup Right of Use Assets (Leases) | J93: =_xlfn.XLOOKUP($H93,'Taxonomy and Epics'!$H:$H,'Taxonomy and Epics'!E:E) -> 6.0 - A2R - Acquire to Retire | K93: =_xlfn.XLOOKUP($H93,'Taxonomy and Epics'!$H:$H,'Taxonomy and Epics'!F:F) -> A2R-020 | L93: =_xlfn.XLOOKUP($H93,'Taxonomy and Epics'!$H:$H,'Taxonomy and Epics'!G:G) -> Asset Creation | M93: =_xlfn.XLOOKUP($H93,'Taxonomy and Epics'!$H:$H,'Taxonomy and Epics'!H:H) -> A2R-020-020 | N93: =_xlfn.XLOOKUP($H93,'Taxonomy and Epics'!$H:$H,'Taxonomy and Epics'!I:I) -> Setup Right of Use Assets (Leases)
A94: US-A2R-042 | B94: As a Fixed Asset Accountant, I want to run a report of all created assets (the fixed asset register), with an ability to isolate leased assets. | C94: As a Fixed Asset Accountant, I want to run a report of all created assets (the fixed asset register), with an ability to isolate leased assets. | D94: 1. Given I need a list of all assets, when I run the Fixed Asset Register report, I can apply a filter to only view leased assets, which shows assets created from lease contracts. | E94: Fixed Asset Accountant | F94: D.227;D.229 | G94: A2R0042 | H94: A2R-020-020 | I94: =_xlfn.XLOOKUP(H94,'Taxonomy and Epics'!H:H,'Taxonomy and Epics'!I:I) -> Setup Right of Use Assets (Leases) | J94: =_xlfn.XLOOKUP($H94,'Taxonomy and Epics'!$H:$H,'Taxonomy and Epics'!E:E) -> 6.0 - A2R - Acquire to Retire | K94: =_xlfn.XLOOKUP($H94,'Taxonomy and Epics'!$H:$H,'Taxonomy and Epics'!F:F) -> A2R-020 | L94: =_xlfn.XLOOKUP($H94,'Taxonomy and Epics'!$H:$H,'Taxonomy and Epics'!G:G) -> Asset Creation | M94: =_xlfn.XLOOKUP($H94,'Taxonomy and Epics'!$H:$H,'Taxonomy and Epics'!H:H) -> A2R-020-020 | N94: =_xlfn.XLOOKUP($H94,'Taxonomy and Epics'!$H:$H,'Taxonomy and Epics'!I:I) -> Setup Right of Use Assets (Leases)
A95: US-A2R-043 | B95: As a Fixed Asset Accountant, I want to amend an existing lease contract, so that I can update its terms and ensure it is sent for review. | C95: As a Fixed Asset Accountant, I want to amend an existing lease contract, so that I can update its terms and ensure it is sent for review. | D95: 1. Given I have opened an existing lease contract, when I make changes and submit the amendment, then a review task is sent to the Fixed Asset Accountant. 2. Given the Fixed Asset Accountant has received the review task, when they submit their review of the changes, then the lease contract is updated with the new information. 3. Given I have applied an amendment to the lease, I should be able to identify the impact of the amendment on the payment schedule, interest expense schedule and depreciation schedule. 4. Given I have applied an amendment to the lease, when it is submitted and complete, I should be able to view the financial impact on the general ledger. | E95: Fixed Asset Accountant | G95: A2R0043 | H95: A2R-030-110 | I95: =_xlfn.XLOOKUP(H95,'Taxonomy and Epics'!H:H,'Taxonomy and Epics'!I:I) -> Lease Amendments & Terminations | J95: =_xlfn.XLOOKUP($H95,'Taxonomy and Epics'!$H:$H,'Taxonomy and Epics'!E:E) -> 6.0 - A2R - Acquire to Retire | K95: =_xlfn.XLOOKUP($H95,'Taxonomy and Epics'!$H:$H,'Taxonomy and Epics'!F:F) -> A2R-030 | L95: =_xlfn.XLOOKUP($H95,'Taxonomy and Epics'!$H:$H,'Taxonomy and Epics'!G:G) -> Asset Lifecycle | M95: =_xlfn.XLOOKUP($H95,'Taxonomy and Epics'!$H:$H,'Taxonomy and Epics'!H:H) -> A2R-030-110 | N95: =_xlfn.XLOOKUP($H95,'Taxonomy and Epics'!$H:$H,'Taxonomy and Epics'!I:I) -> Lease Amendments & Terminations
A96: US-A2R-044 | B96: As a Fixed Asset Accountant, I want to terminate a lease contract before its end date, so that the system correctly processes the termination through the required approval workflow. | C96: As a Fixed Asset Accountant, I want to terminate a lease contract before its end date, so that the system correctly processes the termination through the required approval workflow. | D96: 1. Given I am the designated 'contract specialist' on a contract, when I initiate an early termination, then the process skips the first approval step and proceeds to the next step. 2. Given I am neither the 'contract specialist' nor the Financial Accounting Manager, when I initiate an early termination, then the process requires an approval step from the Financial Accounting Manager. | E96: Fixed Asset Accountant | G96: A2R0044 | H96: A2R-030-110 | I96: =_xlfn.XLOOKUP(H96,'Taxonomy and Epics'!H:H,'Taxonomy and Epics'!I:I) -> Lease Amendments & Terminations | J96: =_xlfn.XLOOKUP($H96,'Taxonomy and Epics'!$H:$H,'Taxonomy and Epics'!E:E) -> 6.0 - A2R - Acquire to Retire | K96: =_xlfn.XLOOKUP($H96,'Taxonomy and Epics'!$H:$H,'Taxonomy and Epics'!F:F) -> A2R-030 | L96: =_xlfn.XLOOKUP($H96,'Taxonomy and Epics'!$H:$H,'Taxonomy and Epics'!G:G) -> Asset Lifecycle | M96: =_xlfn.XLOOKUP($H96,'Taxonomy and Epics'!$H:$H,'Taxonomy and Epics'!H:H) -> A2R-030-110 | N96: =_xlfn.XLOOKUP($H96,'Taxonomy and Epics'!$H:$H,'Taxonomy and Epics'!I:I) -> Lease Amendments & Terminations
A97: US-A2R-045 | B97: As a Fixed Asset Accountant, I want to dispose of a leased asset after its originating lease contract is terminated, so that the asset is correctly disposed from the asset register and financial records are updated. | C97: As a Fixed Asset Accountant, I want to dispose of a leased asset after its originating lease contract is terminated, so that the asset is correctly disposed from the asset register and financial records are updated. | D97: 1. Given a lease contract has been successfully terminated, when I initiate the disposal of the associated leased asset, then the system allows the disposal process to begin. 2. Given I have entered the required disposal information (e.g., disposal date), when I submit the disposal, it should enter the standard workflow. 3. Given the disposal workflow is complete, then the system updates the asset's status to 'Disposed' in the asset register. 4. Given the disposal is complete, then the system calculates and posts the corresponding financial journals for the gain or loss on disposal to the general ledger. 5. Given the disposal is complete, then the system notifies the Financial Accountant that a Lease Accounting Adjustment may be necessary to close out residual lease balances. | E97: Fixed Asset Accountant | F97: D.236;D.242 | G97: A2R0045 | H97: A2R-030-110 | I97: =_xlfn.XLOOKUP(H97,'Taxonomy and Epics'!H:H,'Taxonomy and Epics'!I:I) -> Lease Amendments & Terminations | J97: =_xlfn.XLOOKUP($H97,'Taxonomy and Epics'!$H:$H,'Taxonomy and Epics'!E:E) -> 6.0 - A2R - Acquire to Retire | K97: =_xlfn.XLOOKUP($H97,'Taxonomy and Epics'!$H:$H,'Taxonomy and Epics'!F:F) -> A2R-030 | L97: =_xlfn.XLOOKUP($H97,'Taxonomy and Epics'!$H:$H,'Taxonomy and Epics'!G:G) -> Asset Lifecycle | M97: =_xlfn.XLOOKUP($H97,'Taxonomy and Epics'!$H:$H,'Taxonomy and Epics'!H:H) -> A2R-030-110 | N97: =_xlfn.XLOOKUP($H97,'Taxonomy and Epics'!$H:$H,'Taxonomy and Epics'!I:I) -> Lease Amendments & Terminations
A98: US-A2R-046 | B98: As an Accounts Payable Officer, I want to generate a supplier invoice from a lease contract, so that payments can be processed efficiently with the correct reviews. | C98: As an Accounts Payable Officer, I want to generate a supplier invoice from a lease contract, so that payments can be processed efficiently with the correct reviews. | D98: 1. Given I am generating a supplier invoice from a lease, when I try to submit it without an invoice attachment or without an invoice number, then the system should display an error and prevent submission. 2. Given a supplier invoice is generated from a lease, when it is submitted, then it does not require standard approvals like DOA or cost centre manager approval. 3. Given a supplier invoice is generated from a lease, when it is submitted, then it is sent to the designated 'contract specialist' for review before payment processing. 4. Given a supplier invoice is successfully generated from a lease, when it is submitted, then it should be marked as 'complete' on the payment schedule and impact the general ledger. | E98: Accounts Payable Officer | F98: D.232 | G98: A2R0046 | H98: A2R-040-020 | I98: =_xlfn.XLOOKUP(H98,'Taxonomy and Epics'!H:H,'Taxonomy and Epics'!I:I) -> Close Leased Asset Sub ledger and Reconcile with GL | J98: =_xlfn.XLOOKUP($H98,'Taxonomy and Epics'!$H:$H,'Taxonomy and Epics'!E:E) -> 6.0 - A2R - Acquire to Retire | K98: =_xlfn.XLOOKUP($H98,'Taxonomy and Epics'!$H:$H,'Taxonomy and Epics'!F:F) -> A2R-040 | L98: =_xlfn.XLOOKUP($H98,'Taxonomy and Epics'!$H:$H,'Taxonomy and Epics'!G:G) -> Period End Close, Reporting & Analytics | M98: =_xlfn.XLOOKUP($H98,'Taxonomy and Epics'!$H:$H,'Taxonomy and Epics'!H:H) -> A2R-040-020 | N98: =_xlfn.XLOOKUP($H98,'Taxonomy and Epics'!$H:$H,'Taxonomy and Epics'!I:I) -> Close Leased Asset Sub ledger and Reconcile with GL
A99: US-A2R-047 | B99: As a Fixed Asset Accountant, I want to initiate the generation of month-end interest expense for lease contracts, so that our financial records are accurate and up-to-date. | C99: As a Fixed Asset Accountant, I want to initiate the generation of month-end interest expense for lease contracts, so that our financial records are accurate and up-to-date. | D99: 1. Given it is the end of the month, when I as the Fixed Asset Accountant run the process to recognise interest expense, then the system calculates and posts the interest for all active lease contracts to the general ledger. 2. Given it is the end of the month, when I as the Fixed Asset Accountant recognise the interest expense, its status should be 'complete' and impact the general ledger. | E99: Fixed Asset Accountant | G99: A2R0047 | H99: A2R-040-020 | I99: =_xlfn.XLOOKUP(H99,'Taxonomy and Epics'!H:H,'Taxonomy and Epics'!I:I) -> Close Leased Asset Sub ledger and Reconcile with GL | J99: =_xlfn.XLOOKUP($H99,'Taxonomy and Epics'!$H:$H,'Taxonomy and Epics'!E:E) -> 6.0 - A2R - Acquire to Retire | K99: =_xlfn.XLOOKUP($H99,'Taxonomy and Epics'!$H:$H,'Taxonomy and Epics'!F:F) -> A2R-040 | L99: =_xlfn.XLOOKUP($H99,'Taxonomy and Epics'!$H:$H,'Taxonomy and Epics'!G:G) -> Period End Close, Reporting & Analytics | M99: =_xlfn.XLOOKUP($H99,'Taxonomy and Epics'!$H:$H,'Taxonomy and Epics'!H:H) -> A2R-040-020 | N99: =_xlfn.XLOOKUP($H99,'Taxonomy and Epics'!$H:$H,'Taxonomy and Epics'!I:I) -> Close Leased Asset Sub ledger and Reconcile with GL
A100: US-A2R-048 | B100: As a Fixed Asset Accountant, I want to create and post a journal for prepaid lease payments, so that the prepayment is accurately recorded and automatically reverses in the correct period. | C100: As a Fixed Asset Accountant, I want to create and post a journal for prepaid lease payments, so that the prepayment is accurately recorded and automatically reverses in the correct period. | D100: 1. Given I need to record a lease prepayment, when I run the specified report, then the system generates the necessary journal details for me to validate against the offsetting prepaid invoice(s). 2. Given I have validated the journal details, when I submit the journal entry, then it enters the standard approval workflow for review. 3. Given the journal has been fully approved, when I check the General Ledger, then the transaction is posted and visible in financial reports. 4. Given the journal has a status of 'posted', when the system date reaches the designated month of recognition, then the journal entry automatically reverses without manual intervention. | E100: Fixed Asset Accountant | F100: D.288 | H100: A2R-040-020 | I100: =_xlfn.XLOOKUP(H100,'Taxonomy and Epics'!H:H,'Taxonomy and Epics'!I:I) -> Close Leased Asset Sub ledger and Reconcile with GL | J100: =_xlfn.XLOOKUP($H100,'Taxonomy and Epics'!$H:$H,'Taxonomy and Epics'!E:E) -> 6.0 - A2R - Acquire to Retire | K100: =_xlfn.XLOOKUP($H100,'Taxonomy and Epics'!$H:$H,'Taxonomy and Epics'!F:F) -> A2R-040 | L100: =_xlfn.XLOOKUP($H100,'Taxonomy and Epics'!$H:$H,'Taxonomy and Epics'!G:G) -> Period End Close, Reporting & Analytics | M100: =_xlfn.XLOOKUP($H100,'Taxonomy and Epics'!$H:$H,'Taxonomy and Epics'!H:H) -> A2R-040-020 | N100: =_xlfn.XLOOKUP($H100,'Taxonomy and Epics'!$H:$H,'Taxonomy and Epics'!I:I) -> Close Leased Asset Sub ledger and Reconcile with GL
...

Sheet Test Scenarios
A1: Review Status | B1: Test Scenario ID | C1: Test Scenario | D1: Test Scenario Description | E1: Test Scenario Type | F1: Expected Result | G1: Pre-requisites | H1: Key Business Role | I1: Integration to be run | J1: Priority | K1: User Story ID | L1: User Story | M1: Linked Epic ID | N1: Linked Epic | O1: Comments | P1: To be discussed | Q1: Code | U1: Linked Epic ID Copied
A2: Review Complete | B2: S2P-TS001 | C2: Process matched goods invoice | D2: This test verifies that a supplier invoice for goods, which has a corresponding purchase order and goods receipt, is processed automatically without manual intervention. This scenario validates the acceptance criterion: "Given an invoice for goods has a matching purchase order (PO) and goods receipt, when I submit it, the system automatically matches it and proceeds." Variation: This is a positive test case confirming the standard 'happy path' for a three-way matched invoice. | E2: Positive | F2: • The invoice is automatically matched to the PO and receipt. • The invoice proceeds to the next step for payment processing. | G2: • A Purchase Order (PO) for goods exists and is approved. • A Goods Receipt is recorded against the PO. | H2: Accounts Payable Officer | J2: High | K2: US-P2P-001 | L2: As an Accounts Payable Officer, I want to process different types of supplier invoices so that suppliers are paid accurately and on time. | M2: S2P-100-010 | N2: Receive Invoices & Credit Notes (incl. Self Billing & Prepayments) | Q2: =LEFT(M2,3) -> S2P | U2: S2P-100-010
A3: Review Complete | B3: S2P-TS002 | C3: Process service invoice with PO | D3: This test confirms that an invoice for services with a matching purchase order is correctly routed to the person who originally requested the service for confirmation. This scenario validates the acceptance criterion: "Given an invoice for services has a matching PO, when I submit it, the system sends it to the original requester to confirm the service was completed before it can be paid." Variation: This positive test case verifies the specific approval routing for service-based invoices. | F3: • The system sends a task to the original requester of the service. • The invoice cannot proceed to payment until the requester confirms the service was completed. | G3: • A Purchase Order (PO) for services exists and is approved. | H3: Accounts Payable Officer | J3: High | K3: US-P2P-001 | L3: As an Accounts Payable Officer, I want to process different types of supplier invoices so that suppliers are paid accurately and on time. | M3: S2P-100-010 | N3: Receive Invoices & Credit Notes (incl. Self Billing & Prepayments) | Q3: =LEFT(M3,3) -> S2P | U3: S2P-100-010
A4: Deferred | B4: S2P-TS003 | C4: Process non-PO invoice (Rejected - TO BE DELETED) | D4: This test ensures that an invoice submitted without a purchase order is sent to the correct manager for approval based on its financial details (costings). This scenario validates the acceptance criterion: "Given an invoice does not have a PO, when I submit it, the system routes it to the correct manager for approval based on the costings." Variation: This positive test case confirms the approval workflow for invoices that do not have a pre-approved purchase order. | E4: Positive | F4: • The system automatically sends the invoice to the appropriate manager for approval. • The invoice cannot be paid until the manager approves it. | G4: • A Supplier Invoice is created without linking it to a Purchase Order. • The invoice includes financial details like cost centre and spend category. | H4: Accounts Payable Officer | J4: High | K4: US-P2P-001 | L4: As an Accounts Payable Officer, I want to process different types of supplier invoices so that suppliers are paid accurately and on time. | M4: S2P-100-010 | N4: Receive Invoices & Credit Notes (incl. Self Billing & Prepayments) | Q4: =LEFT(M4,3) -> S2P | U4: S2P-100-010
A5: Review Complete | B5: S2P-TS004 | C5: Reject non-PO invoice | D5: This test ensures that if a manager rejects an invoice that was submitted without a purchase order, the process stops and the invoice is not approved for payment. This scenario validates the acceptance criterion: "Given an invoice does not have a PO, when I submit it, the system routes it to the correct manager for approval based on the costings." Variation: This is a negative test case to confirm the outcome of a manager rejecting a non-PO invoice during the approval step. | E5: Negative | F5: • The manager rejects the invoice. • The invoice status is updated to 'Rejected' or 'Cancelled'. • The invoice does not proceed to payment. | G5: • A non-PO Supplier Invoice has been submitted and is awaiting manager approval. | H5: Accounts Payable Officer | J5: High | K5: US-P2P-001 | L5: As an Accounts Payable Officer, I want to process different types of supplier invoices so that suppliers are paid accurately and on time. | M5: S2P-100-010 | N5: Receive Invoices & Credit Notes (incl. Self Billing & Prepayments) | Q5: =LEFT(M5,3) -> S2P | U5: S2P-100-010
